Workbook

Sheet Promotion
B1: Promotion Samsung | X1: https://nimbus.copperwired.co.th/ofs/query/InventoryControl.asp
E2: Stock ชั้น1 | F2: Stock ชั้น2 | G2: PROMOTION | H2: ราคาหลังหักส่วนลด PROMOTION | I2: คูปอง | J2: PROMOTION | K2: ราคาหลังหักส่วนลด PROMOTION | L2: คูปอง | M2: PROMOTION | N2: ราคาหลังหักส่วนลด PROMOTION | O2: คูปอง | P2: PROMOTION Student | Q2: ราคาหลังหักส่วนลด PROMOTION | S2: PROMOTION | T2: ราคาหลังหักส่วนลด PROMOTION | U2: คูปอง | V2: Remark | W2: หมายเหยุ
A3: *กรณีสินค้ามีราคาพิเศษ Flash Sales งดแถมของ Premium* | G3: 2Aug - 6 Sep 2026 | P3: Student
A4: Galaxy A07 4G 4/64 GB | B4: SM-A075FLVDTHL | C4: Light Violet | D4: 4599 | E4: {=_xlfn.XLOOKUP(B4,Stock1!F:F,Stock1!J:J,"")} -> 2 | F4: {=_xlfn.XLOOKUP(B4,Stock2!F:F,Stock2!J:J,"")} -> 5 | G4: 800 | H4: =D4-G4 -> 3799 | I4: 01 *ร่วม SF+
B5: SM-A075FZKDTHL | C5: Black | D5: 4599 | E5: {=_xlfn.XLOOKUP(B5,Stock1!F:F,Stock1!J:J,"")} | F5: {=_xlfn.XLOOKUP(B5,Stock2!F:F,Stock2!J:J,"")} | G5: 800 | H5: =D5-G5 -> 3799
B6: SM-A075FLVJTHL | C6: Light Violet | D6: 4599 | E6: {=_xlfn.XLOOKUP(B6,Stock1!F:F,Stock1!J:J,"")} | F6: {=_xlfn.XLOOKUP(B6,Stock2!F:F,Stock2!J:J,"")} | G6: 800 | H6: =D6-G6 -> 3799
B7: SM-A075FZKJTHL | C7: Black | D7: 4599 | E7: {=_xlfn.XLOOKUP(B7,Stock1!F:F,Stock1!J:J,"")} | F7: {=_xlfn.XLOOKUP(B7,Stock2!F:F,Stock2!J:J,"")} | G7: 800 | H7: =D7-G7 -> 3799
A8: Galaxy A07 4/64GB - BOM SET | B8: F-A074G064VDTH | C8: Light Violet | D8: 4599 | E8: {=_xlfn.XLOOKUP(B8,Stock1!F:F,Stock1!J:J,"")} | F8: {=_xlfn.XLOOKUP(B8,Stock2!F:F,Stock2!J:J,"")} | G8: 800 | H8: =D8-G8 -> 3799
B9: F-A074G064KDTH | C9: Black | D9: 4599 | E9: {=_xlfn.XLOOKUP(B9,Stock1!F:F,Stock1!J:J,"")} | F9: {=_xlfn.XLOOKUP(B9,Stock2!F:F,Stock2!J:J,"")} | G9: 800 | H9: =D9-G9 -> 3799
A10: Galaxy A07 4/128GB - BOM SET | B10: F-A074G128VGTH | C10: Light Violet | D10: 5299 | E10: {=_xlfn.XLOOKUP(B10,Stock1!F:F,Stock1!J:J,"")} | F10: {=_xlfn.XLOOKUP(B10,Stock2!F:F,Stock2!J:J,"")} | G10: 1000 | H10: =D10-G10 -> 4299
B11: F-A074G128KGTH | C11: Black | D11: 5299 | E11: {=_xlfn.XLOOKUP(B11,Stock1!F:F,Stock1!J:J,"")} | F11: {=_xlfn.XLOOKUP(B11,Stock2!F:F,Stock2!J:J,"")} | G11: 1000 | H11: =D11-G11 -> 4299
A12: Galaxy A07 4/128GB | B12: SM-A075FLVGTHL | C12: Light Violet | D12: 5299 | E12: {=_xlfn.XLOOKUP(B12,Stock1!F:F,Stock1!J:J,"")} | F12: {=_xlfn.XLOOKUP(B12,Stock2!F:F,Stock2!J:J,"")} -> 1 | G12: 1000 | H12: =D12-G12 -> 4299
B13: SM-A075FZKGTHL | C13: Black | D13: 5299 | E13: {=_xlfn.XLOOKUP(B13,Stock1!F:F,Stock1!J:J,"")} | F13: {=_xlfn.XLOOKUP(B13,Stock2!F:F,Stock2!J:J,"")} -> 12 | G13: 1000 | H13: =D13-G13 -> 4299
A14: Galaxy A07 6/128GB | B14: SM-A075FLVHTHL | C14: Light Violet | D14: 5999 | E14: {=_xlfn.XLOOKUP(B14,Stock1!F:F,Stock1!J:J,"")} -> 4 | F14: {=_xlfn.XLOOKUP(B14,Stock2!F:F,Stock2!J:J,"")} -> 3 | G14: 1000 | H14: =D14-G14 -> 4999
B15: SM-A075FZKHTHL | C15: Black | D15: 5999 | E15: {=_xlfn.XLOOKUP(B15,Stock1!F:F,Stock1!J:J,"")} -> 5 | F15: {=_xlfn.XLOOKUP(B15,Stock2!F:F,Stock2!J:J,"")} -> 2 | G15: 1000 | H15: =D15-G15 -> 4999
A16: Galaxy A07 5G 6/128GB | B16: SM-A076BLVCTHL | C16: Light Violet | D16: 6999 | E16: {=_xlfn.XLOOKUP(B16,Stock1!F:F,Stock1!J:J,"")} -> 6 | F16: {=_xlfn.XLOOKUP(B16,Stock2!F:F,Stock2!J:J,"")} -> 5 | I16: ดาวน์ไม่เกิน 13% | J16: 500 | K16: =D16-J16 -> 6499 | L16: 01 *ไม่ร่วม SF+ | P16: 0.1 | Q16: =ROUNDUP(D16-(D16*0.1),0) -> 6300
B17: SM-A076BZKCTHL | C17: Black | D17: 6999 | E17: {=_xlfn.XLOOKUP(B17,Stock1!F:F,Stock1!J:J,"")} -> 5 | F17: {=_xlfn.XLOOKUP(B17,Stock2!F:F,Stock2!J:J,"")} -> 7 | J17: 500 | K17: =D17-J17 -> 6499 | P17: 0.1 | Q17: =ROUNDUP(D17-(D17*0.1),0) -> 6300
A18: Galaxy A17 LTE 8/128 GB | B18: F-A174G128BDTH | C18: Light Blue | D18: 7999 | E18: {=_xlfn.XLOOKUP(B18,Stock1!F:F,Stock1!J:J,"")} | F18: {=_xlfn.XLOOKUP(B18,Stock2!F:F,Stock2!J:J,"")} | G18: 1000 | H18: =D18-G18 -> 6999 | I18: 01 *ร่วม SF+
B19: F-A174G128KDTH | C19: Black | D19: 7999 | E19: {=_xlfn.XLOOKUP(B19,Stock1!F:F,Stock1!J:J,"")} | F19: {=_xlfn.XLOOKUP(B19,Stock2!F:F,Stock2!J:J,"")} | G19: 1000 | H19: =D19-G19 -> 6999
B20: SM-A175FLBDTHL | C20: Light Blue | D20: 7999 | E20: {=_xlfn.XLOOKUP(B20,Stock1!F:F,Stock1!J:J,"")} | F20: {=_xlfn.XLOOKUP(B20,Stock2!F:F,Stock2!J:J,"")} -> 4 | G20: 1000 | H20: =D20-G20 -> 6999
B21: SM-A175FZKDTHL | C21: Black | D21: 7999 | E21: {=_xlfn.XLOOKUP(B21,Stock1!F:F,Stock1!J:J,"")} | F21: {=_xlfn.XLOOKUP(B21,Stock2!F:F,Stock2!J:J,"")} | G21: 1000 | H21: =D21-G21 -> 6999
A22: Galaxy A17 5G 8/128 GB | B22: SM-A176BZBJTHL | C22: Blue | D22: 8999 | E22: {=_xlfn.XLOOKUP(B22,Stock1!F:F,Stock1!J:J,"")} -> 3 | F22: {=_xlfn.XLOOKUP(B22,Stock2!F:F,Stock2!J:J,"")} -> 6 | G22: 1500 | H22: =D22-G22 -> 7499
B23: SM-A176BZKJTHL | C23: Black | D23: 8999 | E23: {=_xlfn.XLOOKUP(B23,Stock1!F:F,Stock1!J:J,"")} -> 7 | F23: {=_xlfn.XLOOKUP(B23,Stock2!F:F,Stock2!J:J,"")} -> 7 | G23: 1500 | H23: =D23-G23 -> 7499
B24: F-A175G128BLTH | C24: Blue | D24: 8999 | E24: {=_xlfn.XLOOKUP(B24,Stock1!F:F,Stock1!J:J,"")} | F24: {=_xlfn.XLOOKUP(B24,Stock2!F:F,Stock2!J:J,"")} | G24: 1500 | H24: =D24-G24 -> 7499
B25: F-A175G128BKTH | C25: Black | D25: 8999 | E25: {=_xlfn.XLOOKUP(B25,Stock1!F:F,Stock1!J:J,"")} | F25: {=_xlfn.XLOOKUP(B25,Stock2!F:F,Stock2!J:J,"")} | G25: 1500 | H25: =D25-G25 -> 7499
A26: Galaxy A17 5G 8/256 GB | B26: SM-A176BZBKTHL | C26: Blue | D26: 10599 | E26: {=_xlfn.XLOOKUP(B26,Stock1!F:F,Stock1!J:J,"")} -> 3 | F26: {=_xlfn.XLOOKUP(B26,Stock2!F:F,Stock2!J:J,"")} -> 5 | G26: 1600 | H26: =D26-G26 -> 8999 | P26: 0.1 | Q26: =ROUNDUP(D26-(D26*0.1),0) -> 9540
B27: SM-A176BZKKTHL | C27: Black | D27: 10599 | E27: {=_xlfn.XLOOKUP(B27,Stock1!F:F,Stock1!J:J,"")} -> 2 | F27: {=_xlfn.XLOOKUP(B27,Stock2!F:F,Stock2!J:J,"")} -> 4 | G27: 1600 | H27: =D27-G27 -> 8999 | P27: 0.1 | Q27: =ROUNDUP(D27-(D27*0.1),0) -> 9540
B28: F-A175G256BLTH | C28: Blue | D28: 10599 | E28: {=_xlfn.XLOOKUP(B28,Stock1!F:F,Stock1!J:J,"")} | F28: {=_xlfn.XLOOKUP(B28,Stock2!F:F,Stock2!J:J,"")} | G28: 1600 | H28: =D28-G28 -> 8999 | P28: 0.1 | Q28: =ROUNDUP(D28-(D28*0.1),0) -> 9540
B29: F-A175G256BKTH | C29: Black | D29: 10599 | E29: {=_xlfn.XLOOKUP(B29,Stock1!F:F,Stock1!J:J,"")} | F29: {=_xlfn.XLOOKUP(B29,Stock2!F:F,Stock2!J:J,"")} | G29: 1600 | H29: =D29-G29 -> 8999 | P29: 0.1 | Q29: =ROUNDUP(D29-(D29*0.1),0) -> 9540
A30: Galaxy A27 5G 8/128GB | B30: SM-A276BLIGTHL | C30: LIGHT PINK | D30: 10999 | E30: {=_xlfn.XLOOKUP(B30,Stock1!F:F,Stock1!J:J,"")} -> 5 | F30: {=_xlfn.XLOOKUP(B30,Stock2!F:F,Stock2!J:J,"")} -> 2 | I30: 05 แถม ไมโครเวฟ 23ลิตร มูลค่า 3,990 | J30: 1000 | K30: =D30-J30 -> 9999 | L30: 01 *ร่วม SF+
B31: SM-A276BZKGTHL | C31: Black | D31: 10999 | E31: {=_xlfn.XLOOKUP(B31,Stock1!F:F,Stock1!J:J,"")} -> 4 | F31: {=_xlfn.XLOOKUP(B31,Stock2!F:F,Stock2!J:J,"")} -> 8 | J31: 1000 | K31: =D31-J31 -> 9999
A32: Galaxy A37 5G 8/256GB | B32: SM-A376BDGTTHL | C32: Dark Green | D32: 13999 | E32: {=_xlfn.XLOOKUP(B32,Stock1!F:F,Stock1!J:J,"")} -> 3 | F32: {=_xlfn.XLOOKUP(B32,Stock2!F:F,Stock2!J:J,"")} -> 3 | I32: ดาวน์ไม่เกิน 5% | P32: 0.04 | Q32: =ROUNDUP(D32-(D32*0.04),0) -> 13440 | R32: ไม่ร่วม SF+ Cap Down
B33: SM-A376BLVTTHL | C33: Light Violet | D33: 13999 | E33: {=_xlfn.XLOOKUP(B33,Stock1!F:F,Stock1!J:J,"")} -> 3 | F33: {=_xlfn.XLOOKUP(B33,Stock2!F:F,Stock2!J:J,"")} -> 3 | P33: 0.04 | Q33: =ROUNDUP(D33-(D33*0.04),0) -> 13440
B34: SM-A376BZATTHL | C34: Gray | D34: 13999 | E34: {=_xlfn.XLOOKUP(B34,Stock1!F:F,Stock1!J:J,"")} -> 4 | F34: {=_xlfn.XLOOKUP(B34,Stock2!F:F,Stock2!J:J,"")} -> 4 | P34: 0.04 | Q34: =ROUNDUP(D34-(D34*0.04),0) -> 13440
A35: Galaxy A57 5G 8/256GB | B35: SM-A576BDBSTHL | C35: Dark Blue | D35: 16999 | E35: {=_xlfn.XLOOKUP(B35,Stock1!F:F,Stock1!J:J,"")} -> 3 | F35: {=_xlfn.XLOOKUP(B35,Stock2!F:F,Stock2!J:J,"")} -> 2 | I35: ดาวน์ไม่เกิน 5% | J35: 2000 | K35: =D35-J35 -> 14999 | L35: 01 *ไม่ร่วม SF+ | P35: 0.15 | Q35: =ROUNDUP(D35-(D35*0.15),0) -> 14450
B36: SM-A576BZVSTHL | C36: Violet | D36: 16999 | E36: {=_xlfn.XLOOKUP(B36,Stock1!F:F,Stock1!J:J,"")} | F36: {=_xlfn.XLOOKUP(B36,Stock2!F:F,Stock2!J:J,"")} -> 3 | J36: 2000 | K36: =D36-J36 -> 14999 | P36: 0.15 | Q36: =ROUNDUP(D36-(D36*0.15),0) -> 14450
B37: SM-A576BZASTHL | C37: Gray | D37: 16999 | E37: {=_xlfn.XLOOKUP(B37,Stock1!F:F,Stock1!J:J,"")} -> 2 | F37: {=_xlfn.XLOOKUP(B37,Stock2!F:F,Stock2!J:J,"")} -> 1 | J37: 2000 | K37: =D37-J37 -> 14999 | P37: 0.15 | Q37: =ROUNDUP(D37-(D37*0.15),0) -> 14450
A38: Galaxy A57 5G 12/256GB | B38: SM-A576BDBTTHL | C38: Dark Blue | D38: 17999 | E38: {=_xlfn.XLOOKUP(B38,Stock1!F:F,Stock1!J:J,"")} -> 5 | F38: {=_xlfn.XLOOKUP(B38,Stock2!F:F,Stock2!J:J,"")} -> 5 | I38: ดาวน์ไม่เกิน 7% | J38: 2000 | K38: =D38-J38 -> 15999 | P38: 0.14 | Q38: =ROUNDUP(D38-(D38*0.14),0) -> 15480
B39: SM-A576BZVTTHL | C39: Violet | D39: 17999 | E39: {=_xlfn.XLOOKUP(B39,Stock1!F:F,Stock1!J:J,"")} -> 7 | F39: {=_xlfn.XLOOKUP(B39,Stock2!F:F,Stock2!J:J,"")} -> 11 | J39: 2000 | K39: =D39-J39 -> 15999 | P39: 0.14 | Q39: =ROUNDUP(D39-(D39*0.14),0) -> 15480
B40: SM-A576BZATTHL | C40: Gray | D40: 17999 | E40: {=_xlfn.XLOOKUP(B40,Stock1!F:F,Stock1!J:J,"")} -> 9 | F40: {=_xlfn.XLOOKUP(B40,Stock2!F:F,Stock2!J:J,"")} -> 15 | J40: 2000 | K40: =D40-J40 -> 15999 | P40: 0.14 | Q40: =ROUNDUP(D40-(D40*0.14),0) -> 15480
A41: Galaxy A57 5G 12/512GB | B41: SM-A576BDBUTHL | C41: Dark Blue | D41: 20999 | E41: {=_xlfn.XLOOKUP(B41,Stock1!F:F,Stock1!J:J,"")} -> 9 | F41: {=_xlfn.XLOOKUP(B41,Stock2!F:F,Stock2!J:J,"")} -> 5 | I41: ดาวน์ไม่เกิน 8% | J41: 2000 | K41: =D41-J41 -> 18999 | L41: 02 *ไม่ร่วม SF+ | P41: 0.12 | Q41: =ROUNDUP(D41-(D41*0.12),0) -> 18480
B42: SM-A576BZVUTHL | C42: Violet | D42: 20999 | E42: {=_xlfn.XLOOKUP(B42,Stock1!F:F,Stock1!J:J,"")} -> 8 | F42: {=_xlfn.XLOOKUP(B42,Stock2!F:F,Stock2!J:J,"")} -> 5 | J42: 2000 | K42: =D42-J42 -> 18999 | P42: 0.12 | Q42: =ROUNDUP(D42-(D42*0.12),0) -> 18480
B43: SM-A576BZAUTHL | C43: Gray | D43: 20999 | E43: {=_xlfn.XLOOKUP(B43,Stock1!F:F,Stock1!J:J,"")} -> 9 | F43: {=_xlfn.XLOOKUP(B43,Stock2!F:F,Stock2!J:J,"")} -> 5 | J43: 2000 | K43: =D43-J43 -> 18999 | P43: 0.12 | Q43: =ROUNDUP(D43-(D43*0.12),0) -> 18480
A44: Galaxy S25 FE (8/128GB) | B44: SM-S731BDBBTHL | C44: NAVY | D44: 22900 | E44: {=_xlfn.XLOOKUP(B44,Stock1!F:F,Stock1!J:J,"")} | F44: {=_xlfn.XLOOKUP(B44,Stock2!F:F,Stock2!J:J,"")} | G44: 3000 | H44: =D44-G44 -> 19900 | I44: 01 *ร่วม SF+ ดาวน์ไม่เกิน 10% | J44: 5000 | K44: =D44-J44 -> 17900 | L44: 02 *ไม่ร่วม SF+ | P44: 0.15 | Q44: =ROUNDUP(D44-(D44*0.15),0) -> 19465 | R44: ร่วม SF+ Cap Down
B45: SM-S731BLBBTHL | C45: ICYBLUE | D45: 22900 | E45: {=_xlfn.XLOOKUP(B45,Stock1!F:F,Stock1!J:J,"")} | F45: {=_xlfn.XLOOKUP(B45,Stock2!F:F,Stock2!J:J,"")} | G45: 3000 | H45: =D45-G45 -> 19900 | J45: 5000 | K45: =D45-J45 -> 17900 | P45: 0.15 | Q45: =ROUNDUP(D45-(D45*0.15),0) -> 19465
B46: SM-S731BZKBTHL | C46: JETBLACK | D46: 22900 | E46: {=_xlfn.XLOOKUP(B46,Stock1!F:F,Stock1!J:J,"")} | F46: {=_xlfn.XLOOKUP(B46,Stock2!F:F,Stock2!J:J,"")} | G46: 3000 | H46: =D46-G46 -> 19900 | J46: 5000 | K46: =D46-J46 -> 17900 | P46: 0.15 | Q46: =ROUNDUP(D46-(D46*0.15),0) -> 19465
B47: SM-S731BZWBTHL | C47: WHITE | D47: 22900 | E47: {=_xlfn.XLOOKUP(B47,Stock1!F:F,Stock1!J:J,"")} | F47: {=_xlfn.XLOOKUP(B47,Stock2!F:F,Stock2!J:J,"")} | G47: 3000 | H47: =D47-G47 -> 19900 | J47: 5000 | K47: =D47-J47 -> 17900 | P47: 0.15 | Q47: =ROUNDUP(D47-(D47*0.15),0) -> 19465
A48: Galaxy S25 FE (8/256GB) | B48: SM-S731BDBCTHL | C48: NAVY | D48: 26900 | E48: {=_xlfn.XLOOKUP(B48,Stock1!F:F,Stock1!J:J,"")} -> 3 | F48: {=_xlfn.XLOOKUP(B48,Stock2!F:F,Stock2!J:J,"")} -> 6 | G48: 3000 | H48: =D48-G48 -> 23900 | J48: 6000 | K48: =D48-J48 -> 20900 | P48: 0.15 | Q48: =ROUNDUP(D48-(D48*0.15),0) -> 22865
B49: SM-S731BLBCTHL | C49: ICYBLUE | D49: 26900 | E49: {=_xlfn.XLOOKUP(B49,Stock1!F:F,Stock1!J:J,"")} -> 3 | F49: {=_xlfn.XLOOKUP(B49,Stock2!F:F,Stock2!J:J,"")} -> 3 | G49: 3000 | H49: =D49-G49 -> 23900 | J49: 6000 | K49: =D49-J49 -> 20900 | P49: 0.15 | Q49: =ROUNDUP(D49-(D49*0.15),0) -> 22865
B50: SM-S731BZKCTHL | C50: JETBLACK | D50: 26900 | E50: {=_xlfn.XLOOKUP(B50,Stock1!F:F,Stock1!J:J,"")} -> 4 | F50: {=_xlfn.XLOOKUP(B50,Stock2!F:F,Stock2!J:J,"")} -> 4 | G50: 3000 | H50: =D50-G50 -> 23900 | J50: 6000 | K50: =D50-J50 -> 20900 | P50: 0.15 | Q50: =ROUNDUP(D50-(D50*0.15),0) -> 22865
B51: SM-S731BZWCTHL | C51: WHITE | D51: 26900 | E51: {=_xlfn.XLOOKUP(B51,Stock1!F:F,Stock1!J:J,"")} -> 2 | F51: {=_xlfn.XLOOKUP(B51,Stock2!F:F,Stock2!J:J,"")} | G51: 3000 | H51: =D51-G51 -> 23900 | J51: 6000 | K51: =D51-J51 -> 20900 | P51: 0.15 | Q51: =ROUNDUP(D51-(D51*0.15),0) -> 22865
A52: Galaxy S25 Ultra 5G 12/256GB | B52: F-N1938BZKBTHL | C52: BLACK | D52: 42900 | E52: {=_xlfn.XLOOKUP(B52,Stock1!F:F,Stock1!J:J,"")} -> 11 | F52: {=_xlfn.XLOOKUP(B52,Stock2!F:F,Stock2!J:J,"")} -> 9 | G52: 12000 | H52: =D52-G52 -> 30900 | I52: 01 *ร่วม SF+
B53: SM-S938BZKBTHL | C53: BLACK | D53: 42900 | E53: {=_xlfn.XLOOKUP(B53,Stock1!F:F,Stock1!J:J,"")} | F53: {=_xlfn.XLOOKUP(B53,Stock2!F:F,Stock2!J:J,"")} | G53: 12000 | H53: =D53-G53 -> 30900
B54: SM-S938BZBBTHL | C54: BLUE | D54: 42900 | E54: {=_xlfn.XLOOKUP(B54,Stock1!F:F,Stock1!J:J,"")} | F54: {=_xlfn.XLOOKUP(B54,Stock2!F:F,Stock2!J:J,"")} | G54: 12000 | H54: =D54-G54 -> 30900
B55: SM-S938BZTBTHL | C55: GRAY | D55: 42900 | E55: {=_xlfn.XLOOKUP(B55,Stock1!F:F,Stock1!J:J,"")} | F55: {=_xlfn.XLOOKUP(B55,Stock2!F:F,Stock2!J:J,"")} | G55: 12000 | H55: =D55-G55 -> 30900
B56: SM-S938BZSBTHL | C56: SILVER | D56: 42900 | E56: {=_xlfn.XLOOKUP(B56,Stock1!F:F,Stock1!J:J,"")} | F56: {=_xlfn.XLOOKUP(B56,Stock2!F:F,Stock2!J:J,"")} | G56: 12000 | H56: =D56-G56 -> 30900
B57: F-N1938BZBBTHL | C57: SILVER | D57: 42900 | E57: {=_xlfn.XLOOKUP(B57,Stock1!F:F,Stock1!J:J,"")} -> 13 | F57: {=_xlfn.XLOOKUP(B57,Stock2!F:F,Stock2!J:J,"")} -> 8 | G57: 12000 | H57: =D57-G57 -> 30900
A58: Galaxy S26FE 8/128GB | B58: SM-S741BLGBTHL | C58: Pistachio | D58: 24900 | E58: {=_xlfn.XLOOKUP(B58,Stock1!F:F,Stock1!J:J,"")} -> 3 | F58: {=_xlfn.XLOOKUP(B58,Stock2!F:F,Stock2!J:J,"")} -> 3 | I58: ร่วม SF+ ดาวน์ไม่เกิน 10%
B59: SM-S741BZKBTHL | C59: Graphite | D59: 24900 | E59: {=_xlfn.XLOOKUP(B59,Stock1!F:F,Stock1!J:J,"")} -> 4 | F59: {=_xlfn.XLOOKUP(B59,Stock2!F:F,Stock2!J:J,"")} -> 4
B60: SM-S741BZVBTHL | C60: Blueberry | D60: 24900 | E60: {=_xlfn.XLOOKUP(B60,Stock1!F:F,Stock1!J:J,"")} -> 2 | F60: {=_xlfn.XLOOKUP(B60,Stock2!F:F,Stock2!J:J,"")} -> 1
A61: Galaxy S26FE 8/256GB รหัส F | B61: F-NS741BLGCLSV | C61: Pistachio | D61: 24900 | E61: {=_xlfn.XLOOKUP(B61,Stock1!F:F,Stock1!J:J,"")} -> 2 | F61: {=_xlfn.XLOOKUP(B61,Stock2!F:F,Stock2!J:J,"")} -> 3 | I61: ไม่ร่วม SF+ ดาวน์ไม่เกิน 10%
B62: F-NS741BZKCLSV | C62: Graphite | D62: 24900 | E62: {=_xlfn.XLOOKUP(B62,Stock1!F:F,Stock1!J:J,"")} -> 5 | F62: {=_xlfn.XLOOKUP(B62,Stock2!F:F,Stock2!J:J,"")} -> 3
B63: F-NS741BZVCLSV | C63: Blueberry | D63: 24900 | E63: {=_xlfn.XLOOKUP(B63,Stock1!F:F,Stock1!J:J,"")} -> 1 | F63: {=_xlfn.XLOOKUP(B63,Stock2!F:F,Stock2!J:J,"")} -> 2
A64: Galaxy S26 5G 12/256GB | B64: SM-S942BZKCTHL | C64: BLACK | D64: 33900 | E64: {=_xlfn.XLOOKUP(B64,Stock1!F:F,Stock1!J:J,"")} -> 1 | F64: {=_xlfn.XLOOKUP(B64,Stock2!F:F,Stock2!J:J,"")} | G64: 6000 | H64: =D64-G64 -> 27900 | I64: 01 *ร่วม SF+ ดาวน์ไม่เกิน 10%
B65: SM-S942BLBCTHL | C65: SKY BLUE | D65: 33900 | E65: {=_xlfn.XLOOKUP(B65,Stock1!F:F,Stock1!J:J,"")} -> 1 | F65: {=_xlfn.XLOOKUP(B65,Stock2!F:F,Stock2!J:J,"")} -> 1 | G65: 6000 | H65: =D65-G65 -> 27900
B66: SM-S942BZVCTHL | C66: COBALT VIOLET | D66: 33900 | E66: {=_xlfn.XLOOKUP(B66,Stock1!F:F,Stock1!J:J,"")} | F66: {=_xlfn.XLOOKUP(B66,Stock2!F:F,Stock2!J:J,"")} | G66: 6000 | H66: =D66-G66 -> 27900
B67: SM-S942BZWCTHL | C67: WHITE | D67: 33900 | E67: {=_xlfn.XLOOKUP(B67,Stock1!F:F,Stock1!J:J,"")} | F67: {=_xlfn.XLOOKUP(B67,Stock2!F:F,Stock2!J:J,"")} -> 1 | G67: 6000 | H67: =D67-G67 -> 27900
A68: Galaxy S26 5G 12/512GB | B68: SM-S942BZKQTHL | C68: BLACK | D68: 41900 | E68: {=_xlfn.XLOOKUP(B68,Stock1!F:F,Stock1!J:J,"")} -> 2 | F68: {=_xlfn.XLOOKUP(B68,Stock2!F:F,Stock2!J:J,"")} -> 2 | G68: 12000 | H68: =D68-G68 -> 29900
B69: SM-S942BLBQTHL | C69: SKY BLUE | D69: 41900 | E69: {=_xlfn.XLOOKUP(B69,Stock1!F:F,Stock1!J:J,"")} -> 2 | F69: {=_xlfn.XLOOKUP(B69,Stock2!F:F,Stock2!J:J,"")} -> 3 | G69: 12000 | H69: =D69-G69 -> 29900
B70: SM-S942BZVQTHL | C70: COBALT VIOLET | D70: 41900 | E70: {=_xlfn.XLOOKUP(B70,Stock1!F:F,Stock1!J:J,"")} -> 3 | F70: {=_xlfn.XLOOKUP(B70,Stock2!F:F,Stock2!J:J,"")} -> 2 | G70: 12000 | H70: =D70-G70 -> 29900
B71: SM-S942BZWQTHL | C71: WHITE | D71: 41900 | E71: {=_xlfn.XLOOKUP(B71,Stock1!F:F,Stock1!J:J,"")} -> 1 | F71: {=_xlfn.XLOOKUP(B71,Stock2!F:F,Stock2!J:J,"")} | G71: 12000 | H71: =D71-G71 -> 29900
A72: Galaxy S26+ 5G 12/256GB | B72: SM-S947BZKBTHL | C72: BLACK | D72: 40900 | E72: {=_xlfn.XLOOKUP(B72,Stock1!F:F,Stock1!J:J,"")} | F72: {=_xlfn.XLOOKUP(B72,Stock2!F:F,Stock2!J:J,"")} | G72: 10000 | H72: =D72-G72 -> 30900 | I72: 01 *ร่วม SF+ ดาวน์ไม่เกิน 10%
B73: SM-S947BLBBTHL | C73: SKY BLUE | D73: 40900 | E73: {=_xlfn.XLOOKUP(B73,Stock1!F:F,Stock1!J:J,"")} -> 1 | F73: {=_xlfn.XLOOKUP(B73,Stock2!F:F,Stock2!J:J,"")} -> 1 | G73: 10000 | H73: =D73-G73 -> 30900
B74: SM-S947BZVBTHL | C74: COBALT VIOLET | D74: 40900 | E74: {=_xlfn.XLOOKUP(B74,Stock1!F:F,Stock1!J:J,"")} -> 1 | F74: {=_xlfn.XLOOKUP(B74,Stock2!F:F,Stock2!J:J,"")} -> 1 | G74: 10000 | H74: =D74-G74 -> 30900
B75: SM-S947BZWBTHL | C75: WHITE | D75: 40900 | E75: {=_xlfn.XLOOKUP(B75,Stock1!F:F,Stock1!J:J,"")} -> 1 | F75: {=_xlfn.XLOOKUP(B75,Stock2!F:F,Stock2!J:J,"")} -> 1 | G75: 10000 | H75: =D75-G75 -> 30900
A76: Galaxy S26+ 5G 12/512GB | B76: SM-S947BZKCTHL | C76: BLACK | D76: 48900 | E76: {=_xlfn.XLOOKUP(B76,Stock1!F:F,Stock1!J:J,"")} -> 3 | F76: {=_xlfn.XLOOKUP(B76,Stock2!F:F,Stock2!J:J,"")} -> 3 | G76: 12000 | H76: =D76-G76 -> 36900
B77: SM-S947BLBCTHL | C77: SKY BLUE | D77: 48900 | E77: {=_xlfn.XLOOKUP(B77,Stock1!F:F,Stock1!J:J,"")} -> 3 | F77: {=_xlfn.XLOOKUP(B77,Stock2!F:F,Stock2!J:J,"")} -> 3 | G77: 12000 | H77: =D77-G77 -> 36900
B78: SM-S947BZVCTHL | C78: COBALT VIOLET | D78: 48900 | E78: {=_xlfn.XLOOKUP(B78,Stock1!F:F,Stock1!J:J,"")} -> 2 | F78: {=_xlfn.XLOOKUP(B78,Stock2!F:F,Stock2!J:J,"")} -> 3 | G78: 12000 | H78: =D78-G78 -> 36900
B79: SM-S947BZWCTHL | C79: WHITE | D79: 48900 | E79: {=_xlfn.XLOOKUP(B79,Stock1!F:F,Stock1!J:J,"")} -> 1 | F79: {=_xlfn.XLOOKUP(B79,Stock2!F:F,Stock2!J:J,"")} -> 1 | G79: 12000 | H79: =D79-G79 -> 36900
A80: Galaxy S26 Ultra 5G 12/256GB | B80: SM-S948BZKBTHL | C80: BLACK | D80: 46900 | E80: {=_xlfn.XLOOKUP(B80,Stock1!F:F,Stock1!J:J,"")} -> 4 | F80: {=_xlfn.XLOOKUP(B80,Stock2!F:F,Stock2!J:J,"")} -> 5 | G80: 5000 | H80: =D80-G80 -> 41900 | I80: 01 *ร่วม SF+ และ เทรดอัพ | P80: 0.15 | Q80: =ROUNDUP(D80-(D80*0.15),0) -> 39865 | V80: Discount 5,000 + Trade-Up 2,000
B81: SM-S948BLBBTHL | C81: SKY BLUE | D81: 46900 | E81: {=_xlfn.XLOOKUP(B81,Stock1!F:F,Stock1!J:J,"")} -> 2 | F81: {=_xlfn.XLOOKUP(B81,Stock2!F:F,Stock2!J:J,"")} -> 3 | G81: 5000 | H81: =D81-G81 -> 41900 | P81: 0.15 | Q81: =ROUNDUP(D81-(D81*0.15),0) -> 39865
B82: SM-S948BZVBTHL | C82: COBALT VIOLET | D82: 46900 | E82: {=_xlfn.XLOOKUP(B82,Stock1!F:F,Stock1!J:J,"")} -> 6 | F82: {=_xlfn.XLOOKUP(B82,Stock2!F:F,Stock2!J:J,"")} -> 6 | G82: 5000 | H82: =D82-G82 -> 41900 | P82: 0.15 | Q82: =ROUNDUP(D82-(D82*0.15),0) -> 39865
B83: SM-S948BZWBTHL | C83: WHITE | D83: 46900 | E83: {=_xlfn.XLOOKUP(B83,Stock1!F:F,Stock1!J:J,"")} -> 6 | F83: {=_xlfn.XLOOKUP(B83,Stock2!F:F,Stock2!J:J,"")} -> 4 | G83: 5000 | H83: =D83-G83 -> 41900 | P83: 0.15 | Q83: =ROUNDUP(D83-(D83*0.15),0) -> 39865
A84: Galaxy S26 Ultra 5G 12/512GB | B84: SM-S948BZKCTHL | C84: BLACK | D84: 54900 | E84: {=_xlfn.XLOOKUP(B84,Stock1!F:F,Stock1!J:J,"")} -> 7 | F84: {=_xlfn.XLOOKUP(B84,Stock2!F:F,Stock2!J:J,"")} -> 3 | G84: 5000 | H84: =D84-G84 -> 49900 | P84: 0.15 | Q84: =ROUNDUP(D84-(D84*0.15),0) -> 46665 | V84: Discount 5,000 + Trade-Up 5,000
B85: SM-S948BLBCTHL | C85: SKY BLUE | D85: 54900 | E85: {=_xlfn.XLOOKUP(B85,Stock1!F:F,Stock1!J:J,"")} -> 12 | F85: {=_xlfn.XLOOKUP(B85,Stock2!F:F,Stock2!J:J,"")} -> 12 | G85: 5000 | H85: =D85-G85 -> 49900 | P85: 0.15 | Q85: =ROUNDUP(D85-(D85*0.15),0) -> 46665
B86: SM-S948BZVCTHL | C86: COBALT VIOLET | D86: 54900 | E86: {=_xlfn.XLOOKUP(B86,Stock1!F:F,Stock1!J:J,"")} -> 3 | F86: {=_xlfn.XLOOKUP(B86,Stock2!F:F,Stock2!J:J,"")} -> 5 | G86: 5000 | H86: =D86-G86 -> 49900 | P86: 0.15 | Q86: =ROUNDUP(D86-(D86*0.15),0) -> 46665
B87: SM-S948BZWCTHL | C87: WHITE | D87: 54900 | E87: {=_xlfn.XLOOKUP(B87,Stock1!F:F,Stock1!J:J,"")} -> 3 | F87: {=_xlfn.XLOOKUP(B87,Stock2!F:F,Stock2!J:J,"")} -> 5 | G87: 5000 | H87: =D87-G87 -> 49900 | P87: 0.15 | Q87: =ROUNDUP(D87-(D87*0.15),0) -> 46665
A88: Galaxy S26 Ultra 5G 12/1TB | B88: SM-S948BZKQTHL | C88: BLACK | D88: 66900 | E88: {=_xlfn.XLOOKUP(B88,Stock1!F:F,Stock1!J:J,"")} | F88: {=_xlfn.XLOOKUP(B88,Stock2!F:F,Stock2!J:J,"")} | G88: 5000 | H88: =D88-G88 -> 61900
B89: SM-S948BLBQTHL | C89: SKY BLUE | D89: 66900 | E89: {=_xlfn.XLOOKUP(B89,Stock1!F:F,Stock1!J:J,"")} | F89: {=_xlfn.XLOOKUP(B89,Stock2!F:F,Stock2!J:J,"")} | G89: 5000 | H89: =D89-G89 -> 61900
B90: SM-S948BZVQTHL | C90: COBALT VIOLET | D90: 66900 | E90: {=_xlfn.XLOOKUP(B90,Stock1!F:F,Stock1!J:J,"")} | F90: {=_xlfn.XLOOKUP(B90,Stock2!F:F,Stock2!J:J,"")} | G90: 5000 | H90: =D90-G90 -> 61900
B91: SM-S948BZWQTHL | C91: WHITE | D91: 66900 | E91: {=_xlfn.XLOOKUP(B91,Stock1!F:F,Stock1!J:J,"")} | F91: {=_xlfn.XLOOKUP(B91,Stock2!F:F,Stock2!J:J,"")} | G91: 5000 | H91: =D91-G91 -> 61900
A92: Galaxy Z Flip7 12/256GB | B92: SM-F766BZRATHL | C92: Coralred | D92: 40900 | E92: {=_xlfn.XLOOKUP(B92,Stock1!F:F,Stock1!J:J,"")} | F92: {=_xlfn.XLOOKUP(B92,Stock2!F:F,Stock2!J:J,"")} | G92: 11000 | H92: =D92-G92 -> 29900 | I92: 01 *ร่วม SF+ | V92: ประกันจอ 2 ปี เปลี่ยนฟิล์มฟรี 1 ครั้ง
B93: SM-F766BZKATHL | C93: Jet Black | D93: 40900 | E93: {=_xlfn.XLOOKUP(B93,Stock1!F:F,Stock1!J:J,"")} | F93: {=_xlfn.XLOOKUP(B93,Stock2!F:F,Stock2!J:J,"")} | G93: 11000 | H93: =D93-G93 -> 29900
B94: SM-F766BDBATHL | C94: Blue Shadow | D94: 40900 | E94: {=_xlfn.XLOOKUP(B94,Stock1!F:F,Stock1!J:J,"")} | F94: {=_xlfn.XLOOKUP(B94,Stock2!F:F,Stock2!J:J,"")} | G94: 11000 | H94: =D94-G94 -> 29900
A95: Galaxy Z Flip7 12/512GB | B95: SM-F766BZRETHL | C95: Coralred | D95: 48900 | E95: {=_xlfn.XLOOKUP(B95,Stock1!F:F,Stock1!J:J,"")} | F95: {=_xlfn.XLOOKUP(B95,Stock2!F:F,Stock2!J:J,"")} | G95: 11000 | H95: =D95-G95 -> 37900
B96: SM-F766BZKETHL | C96: Jet Black | D96: 48900 | E96: {=_xlfn.XLOOKUP(B96,Stock1!F:F,Stock1!J:J,"")} | F96: {=_xlfn.XLOOKUP(B96,Stock2!F:F,Stock2!J:J,"")} | G96: 11000 | H96: =D96-G96 -> 37900
B97: SM-F766BDBETHL | C97: Blue Shadow | D97: 48900 | E97: {=_xlfn.XLOOKUP(B97,Stock1!F:F,Stock1!J:J,"")} | F97: {=_xlfn.XLOOKUP(B97,Stock2!F:F,Stock2!J:J,"")} | G97: 11000 | H97: =D97-G97 -> 37900
A98: Galaxy Z Flip 8 12/256GB รหัส F | B98: F-NS776BLIATHL | C98: Pink | D98: 42900 | E98: {=_xlfn.XLOOKUP(B98,Stock1!F:F,Stock1!J:J,"")} | F98: {=_xlfn.XLOOKUP(B98,Stock2!F:F,Stock2!J:J,"")} | G98: 8000 | H98: =D98-G98 -> 34900 | I98: 01 *ร่วม SF+ โปรเครื่องเปล่า ไม่ร่วมเทรดอัพ | K98: แถม Adapter 25W กับ Microwave | L98: ไม่รับของแถม ลดเพิ่ม 1,000 | V98: Trade-Up 8,000
B99: F-NS776BZKATHL | C99: Graphite | D99: 42900 | E99: {=_xlfn.XLOOKUP(B99,Stock1!F:F,Stock1!J:J,"")} | F99: {=_xlfn.XLOOKUP(B99,Stock2!F:F,Stock2!J:J,"")} | G99: 8000 | H99: =D99-G99 -> 34900
B100: F-NS776BZWATHL | C100: Cream | D100: 42900 | E100: {=_xlfn.XLOOKUP(B100,Stock1!F:F,Stock1!J:J,"")} | F100: {=_xlfn.XLOOKUP(B100,Stock2!F:F,Stock2!J:J,"")} | G100: 8000 | H100: =D100-G100 -> 34900
...

Sheet สำเนาของ Promotion
B1: Promotion Samsung
E2: Stock ชั้น1 | F2: Stock ชั้น2 | G2: PROMOTION | H2: ราคาหลังหักส่วนลด PROMOTION | I2: คูปอง | J2: PROMOTION | K2: ราคาหลังหักส่วนลด PROMOTION | L2: คูปอง | M2: Remark
G3: 6 Oct - 2 Nov 2025 | J3: 31 Oct - 2 Nov 2025
A4: Galaxy A06 4/64GB | B4: SM-A065FLGDTHL | C4: Light Green | D4: 3099 | E4: {=_xlfn.XLOOKUP(B4,Stock1!F:F,Stock1!J:J,"")} | F4: {=_xlfn.XLOOKUP(B4,Stock2!F:F,Stock2!J:J,"")} | I4: 01
B5: SM-A065FZKDTHL | C5: Black | D5: 3099 | E5: {=_xlfn.XLOOKUP(B5,Stock1!F:F,Stock1!J:J,"")} | F5: {=_xlfn.XLOOKUP(B5,Stock2!F:F,Stock2!J:J,"")}
A6: Galaxy A06 4/128GB | B6: SM-A065FLGGTHL | C6: Light Green | D6: 3999 | E6: {=_xlfn.XLOOKUP(B6,Stock1!F:F,Stock1!J:J,"")} | F6: {=_xlfn.XLOOKUP(B6,Stock2!F:F,Stock2!J:J,"")} | G6: 700 | H6: =D6-G6 -> 3299
B7: SM-A065FZKGTHL | C7: Black | D7: 3999 | E7: {=_xlfn.XLOOKUP(B7,Stock1!F:F,Stock1!J:J,"")} | F7: {=_xlfn.XLOOKUP(B7,Stock2!F:F,Stock2!J:J,"")} | G7: 700 | H7: =D7-G7 -> 3299
A8: Galaxy A07 4/64GB - BOM SET | B8: F-A074G064VDTH | C8: Light Violet | D8: 2999 | E8: {=_xlfn.XLOOKUP(B8,Stock1!F:F,Stock1!J:J,"")} | F8: {=_xlfn.XLOOKUP(B8,Stock2!F:F,Stock2!J:J,"")}
B9: F-A074G064KDTH | C9: Black | D9: 2999 | E9: {=_xlfn.XLOOKUP(B9,Stock1!F:F,Stock1!J:J,"")} | F9: {=_xlfn.XLOOKUP(B9,Stock2!F:F,Stock2!J:J,"")}
A10: Galaxy A07 4/128GB - BOM SET | B10: F-A074G128VGTH | C10: Light Violet | D10: 3999 | E10: {=_xlfn.XLOOKUP(B10,Stock1!F:F,Stock1!J:J,"")} | F10: {=_xlfn.XLOOKUP(B10,Stock2!F:F,Stock2!J:J,"")}
B11: F-A074G128KGTH | C11: Black | D11: 3999 | E11: {=_xlfn.XLOOKUP(B11,Stock1!F:F,Stock1!J:J,"")} | F11: {=_xlfn.XLOOKUP(B11,Stock2!F:F,Stock2!J:J,"")}
A12: Galaxy A06 5G 6/128GB - BOM SET | B12: F-A066G8OFADTH | C12: Light Green | D12: 4499 | E12: {=_xlfn.XLOOKUP(B12,Stock1!F:F,Stock1!J:J,"")} | F12: {=_xlfn.XLOOKUP(B12,Stock2!F:F,Stock2!J:J,"")} | G12: 500 | H12: =D12-G12 -> 3999 | I12: 01
B13: F-A066K8OFADTH | C13: Black | D13: 4499 | E13: {=_xlfn.XLOOKUP(B13,Stock1!F:F,Stock1!J:J,"")} | F13: {=_xlfn.XLOOKUP(B13,Stock2!F:F,Stock2!J:J,"")} | G13: 500 | H13: =D13-G13 -> 3999
A14: Galaxy A06 5G 6/128GB | B14: SM-A066BLGHTHL | C14: Light Green | D14: 5499 | E14: {=_xlfn.XLOOKUP(B14,Stock1!F:F,Stock1!J:J,"")} | F14: {=_xlfn.XLOOKUP(B14,Stock2!F:F,Stock2!J:J,"")} | G14: 1500 | H14: =D14-G14 -> 3999
B15: SM-A066BZKHTHL | C15: Black | D15: 5499 | E15: {=_xlfn.XLOOKUP(B15,Stock1!F:F,Stock1!J:J,"")} | F15: {=_xlfn.XLOOKUP(B15,Stock2!F:F,Stock2!J:J,"")} | G15: 1500 | H15: =D15-G15 -> 3999
A16: Galaxy A16 LTE 8/256 GB | B16: SM-A165FLGITHL | C16: Light Green | D16: 6999 | E16: {=_xlfn.XLOOKUP(B16,Stock1!F:F,Stock1!J:J,"")} | F16: {=_xlfn.XLOOKUP(B16,Stock2!F:F,Stock2!J:J,"")} | G16: 1500 | H16: =D16-G16 -> 5499
B17: SM-A165FZKITHL | C17: Black | D17: 6999 | E17: {=_xlfn.XLOOKUP(B17,Stock1!F:F,Stock1!J:J,"")} | F17: {=_xlfn.XLOOKUP(B17,Stock2!F:F,Stock2!J:J,"")} | G17: 1500 | H17: =D17-G17 -> 5499
A18: Galaxy A16 5G 4/128 GB - BOM SET | B18: F-A166K128OATH | C18: Black | D18: 4999 | E18: {=_xlfn.XLOOKUP(B18,Stock1!F:F,Stock1!J:J,"")} | F18: {=_xlfn.XLOOKUP(B18,Stock2!F:F,Stock2!J:J,"")}
A19: Galaxy A16 5G 4/128 GB | B19: SM-A166PLGDTHL | C19: Light Green | D19: 5999 | E19: {=_xlfn.XLOOKUP(B19,Stock1!F:F,Stock1!J:J,"")} | F19: {=_xlfn.XLOOKUP(B19,Stock2!F:F,Stock2!J:J,"")} | G19: 1500 | H19: =D19-G19 -> 4499
B20: SM-A166PZKDTHL | C20: Black | D20: 5999 | E20: {=_xlfn.XLOOKUP(B20,Stock1!F:F,Stock1!J:J,"")} | F20: {=_xlfn.XLOOKUP(B20,Stock2!F:F,Stock2!J:J,"")} | G20: 1500 | H20: =D20-G20 -> 4499
A21: Galaxy A16 5G 8/256 GB - BOM SET | B21: F-A166G256OATH | C21: Light Green | D21: 6999 | E21: {=_xlfn.XLOOKUP(B21,Stock1!F:F,Stock1!J:J,"")} | F21: {=_xlfn.XLOOKUP(B21,Stock2!F:F,Stock2!J:J,"")}
B22: F-A166K256OATH | C22: Black | D22: 6999 | E22: {=_xlfn.XLOOKUP(B22,Stock1!F:F,Stock1!J:J,"")} | F22: {=_xlfn.XLOOKUP(B22,Stock2!F:F,Stock2!J:J,"")}
A23: Galaxy A16 5G 8/256 GB | B23: SM-A166PLGITHL | C23: Light Green | D23: 8499 | E23: {=_xlfn.XLOOKUP(B23,Stock1!F:F,Stock1!J:J,"")} | F23: {=_xlfn.XLOOKUP(B23,Stock2!F:F,Stock2!J:J,"")} | G23: 1500 | H23: =D23-G23 -> 6999
B24: SM-A166PZKITHL | C24: Black | D24: 8499 | E24: {=_xlfn.XLOOKUP(B24,Stock1!F:F,Stock1!J:J,"")} | F24: {=_xlfn.XLOOKUP(B24,Stock2!F:F,Stock2!J:J,"")} | G24: 1500 | H24: =D24-G24 -> 6999
A25: Galaxy A17 LTE 8/128 GB | B25: F-A174G128BDTH | C25: Light Blue | D25: 5999 | E25: {=_xlfn.XLOOKUP(B25,Stock1!F:F,Stock1!J:J,"")} | F25: {=_xlfn.XLOOKUP(B25,Stock2!F:F,Stock2!J:J,"")} | G25: 500 | H25: =D25-G25 -> 5499
B26: F-A174G128KDTH | C26: Black | D26: 5999 | E26: {=_xlfn.XLOOKUP(B26,Stock1!F:F,Stock1!J:J,"")} | F26: {=_xlfn.XLOOKUP(B26,Stock2!F:F,Stock2!J:J,"")} | G26: 500 | H26: =D26-G26 -> 5499
A27: Galaxy A17 5G 8/128 GB | B27: SM-A176BZBJTHL | C27: Blue | D27: 7499 | E27: {=_xlfn.XLOOKUP(B27,Stock1!F:F,Stock1!J:J,"")} -> 3 | F27: {=_xlfn.XLOOKUP(B27,Stock2!F:F,Stock2!J:J,"")} -> 6 | G27: 500 | H27: =D27-G27 -> 6999
B28: SM-A176BZKJTHL | C28: Black | D28: 7499 | E28: {=_xlfn.XLOOKUP(B28,Stock1!F:F,Stock1!J:J,"")} -> 7 | F28: {=_xlfn.XLOOKUP(B28,Stock2!F:F,Stock2!J:J,"")} -> 7 | G28: 500 | H28: =D28-G28 -> 6999
B29: F-A175G128BLTH | C29: Blue | D29: 7499 | E29: {=_xlfn.XLOOKUP(B29,Stock1!F:F,Stock1!J:J,"")} | F29: {=_xlfn.XLOOKUP(B29,Stock2!F:F,Stock2!J:J,"")} | G29: 500 | H29: =D29-G29 -> 6999
B30: F-A175G128BKTH | C30: Black | D30: 7499 | E30: {=_xlfn.XLOOKUP(B30,Stock1!F:F,Stock1!J:J,"")} | F30: {=_xlfn.XLOOKUP(B30,Stock2!F:F,Stock2!J:J,"")} | G30: 500 | H30: =D30-G30 -> 6999
A31: Galaxy A17 5G 8/256 GB | B31: SM-A176BZKKTHL | C31: Black | D31: 8999 | E31: {=_xlfn.XLOOKUP(B31,Stock1!F:F,Stock1!J:J,"")} -> 2 | F31: {=_xlfn.XLOOKUP(B31,Stock2!F:F,Stock2!J:J,"")} -> 4 | G31: 1000 | H31: =D31-G31 -> 7999
B32: F-A175G256BLTH | C32: Blue | D32: 8999 | E32: {=_xlfn.XLOOKUP(B32,Stock1!F:F,Stock1!J:J,"")} | F32: {=_xlfn.XLOOKUP(B32,Stock2!F:F,Stock2!J:J,"")} | G32: 1000 | H32: =D32-G32 -> 7999
B33: F-A175G256BKTH | C33: Black | D33: 8999 | E33: {=_xlfn.XLOOKUP(B33,Stock1!F:F,Stock1!J:J,"")} | F33: {=_xlfn.XLOOKUP(B33,Stock2!F:F,Stock2!J:J,"")} | G33: 1000 | H33: =D33-G33 -> 7999
A34: Galaxy A26 5G 8/256GB | B34: SM-A266BZKHTHL | C34: Black | D34: 10999 | E34: {=_xlfn.XLOOKUP(B34,Stock1!F:F,Stock1!J:J,"")} | F34: {=_xlfn.XLOOKUP(B34,Stock2!F:F,Stock2!J:J,"")} | G34: 1000 | H34: =D34-G34 -> 9999 | I34: 01
B35: SM-A266BLGHTHL | C35: Light Green | D35: 10999 | E35: {=_xlfn.XLOOKUP(B35,Stock1!F:F,Stock1!J:J,"")} | F35: {=_xlfn.XLOOKUP(B35,Stock2!F:F,Stock2!J:J,"")} | G35: 1000 | H35: =D35-G35 -> 9999
A36: Galaxy A36 5G 8/128GB | B36: SM-A366BLGSTHL | C36: Light Green | D36: 11999 | E36: {=_xlfn.XLOOKUP(B36,Stock1!F:F,Stock1!J:J,"")} | F36: {=_xlfn.XLOOKUP(B36,Stock2!F:F,Stock2!J:J,"")} | G36: 800 | H36: =D36-G36 -> 11199 | M36: ไม่ร่วม Finance
B37: SM-A366BLVSTHL | C37: Light Violet | D37: 11999 | E37: {=_xlfn.XLOOKUP(B37,Stock1!F:F,Stock1!J:J,"")} | F37: {=_xlfn.XLOOKUP(B37,Stock2!F:F,Stock2!J:J,"")} | G37: 800 | H37: =D37-G37 -> 11199
B38: SM-A366BZKSTHL | C38: Black | D38: 11999 | E38: {=_xlfn.XLOOKUP(B38,Stock1!F:F,Stock1!J:J,"")} | F38: {=_xlfn.XLOOKUP(B38,Stock2!F:F,Stock2!J:J,"")} | G38: 800 | H38: =D38-G38 -> 11199
A39: Galaxy A56 5G 8/128GB | B39: SM-A566BLISTHL | C39: Light Pink | D39: 13999 | E39: {=_xlfn.XLOOKUP(B39,Stock1!F:F,Stock1!J:J,"")} | F39: {=_xlfn.XLOOKUP(B39,Stock2!F:F,Stock2!J:J,"")} | G39: 1000 | H39: =D39-G39 -> 12999
B40: SM-A566BZGSTHL | C40: GREEN | D40: 13999 | E40: {=_xlfn.XLOOKUP(B40,Stock1!F:F,Stock1!J:J,"")} | F40: {=_xlfn.XLOOKUP(B40,Stock2!F:F,Stock2!J:J,"")} | G40: 1000 | H40: =D40-G40 -> 12999
B41: SM-A566BZKSTHL | C41: Black | D41: 13999 | E41: {=_xlfn.XLOOKUP(B41,Stock1!F:F,Stock1!J:J,"")} | F41: {=_xlfn.XLOOKUP(B41,Stock2!F:F,Stock2!J:J,"")} | G41: 1000 | H41: =D41-G41 -> 12999
A42: Galaxy A56 5G 12/256GB | B42: SM-A566BLIUTHL | C42: Light Pink | D42: 15999 | E42: {=_xlfn.XLOOKUP(B42,Stock1!F:F,Stock1!J:J,"")} | F42: {=_xlfn.XLOOKUP(B42,Stock2!F:F,Stock2!J:J,"")} | G42: 1000 | H42: =D42-G42 -> 14999
B43: SM-A566BZGUTHL | C43: GREEN | D43: 15999 | E43: {=_xlfn.XLOOKUP(B43,Stock1!F:F,Stock1!J:J,"")} | F43: {=_xlfn.XLOOKUP(B43,Stock2!F:F,Stock2!J:J,"")} | G43: 1000 | H43: =D43-G43 -> 14999
B44: SM-A566BZKUTHL | C44: Black | D44: 15999 | E44: {=_xlfn.XLOOKUP(B44,Stock1!F:F,Stock1!J:J,"")} | F44: {=_xlfn.XLOOKUP(B44,Stock2!F:F,Stock2!J:J,"")} | G44: 1000 | H44: =D44-G44 -> 14999
A45: Galaxy S24 FE (8/128GB) | B45: SM-S721BLBBTHL | C45: Blue | D45: 19900 | E45: {=_xlfn.XLOOKUP(B45,Stock1!F:F,Stock1!J:J,"")} | F45: {=_xlfn.XLOOKUP(B45,Stock2!F:F,Stock2!J:J,"")} | G45: 4000 | H45: =D45-G45 -> 15900 | I45: 01 | M45: SF+ Capped DP 20%
B46: SM-S721BLGBTHL | C46: MINT | D46: 19900 | E46: {=_xlfn.XLOOKUP(B46,Stock1!F:F,Stock1!J:J,"")} | F46: {=_xlfn.XLOOKUP(B46,Stock2!F:F,Stock2!J:J,"")} | G46: 4000 | H46: =D46-G46 -> 15900
B47: SM-S721BZKBTHL | C47: Graphite | D47: 19900 | E47: {=_xlfn.XLOOKUP(B47,Stock1!F:F,Stock1!J:J,"")} | F47: {=_xlfn.XLOOKUP(B47,Stock2!F:F,Stock2!J:J,"")} | G47: 4000 | H47: =D47-G47 -> 15900
A48: Galaxy S24 FE (8/256GB) | B48: SM-S721BLBCTHL | C48: Blue | D48: 22900 | E48: {=_xlfn.XLOOKUP(B48,Stock1!F:F,Stock1!J:J,"")} | F48: {=_xlfn.XLOOKUP(B48,Stock2!F:F,Stock2!J:J,"")} | G48: 4000 | H48: =D48-G48 -> 18900
B49: SM-S721BLGCTHL | C49: MINT | D49: 22900 | E49: {=_xlfn.XLOOKUP(B49,Stock1!F:F,Stock1!J:J,"")} | F49: {=_xlfn.XLOOKUP(B49,Stock2!F:F,Stock2!J:J,"")} | G49: 4000 | H49: =D49-G49 -> 18900
B50: SM-S721BZKCTHL | C50: Graphite | D50: 22900 | E50: {=_xlfn.XLOOKUP(B50,Stock1!F:F,Stock1!J:J,"")} | F50: {=_xlfn.XLOOKUP(B50,Stock2!F:F,Stock2!J:J,"")} | G50: 4000 | H50: =D50-G50 -> 18900
A51: Galaxy S25 FE (8/128GB) | B51: SM-S731BDBBTHL | C51: NAVY | D51: 22900 | E51: {=_xlfn.XLOOKUP(B51,Stock1!F:F,Stock1!J:J,"")} | F51: {=_xlfn.XLOOKUP(B51,Stock2!F:F,Stock2!J:J,"")}
B52: SM-S731BLBBTHL | C52: ICYBLUE | D52: 22900 | E52: {=_xlfn.XLOOKUP(B52,Stock1!F:F,Stock1!J:J,"")} | F52: {=_xlfn.XLOOKUP(B52,Stock2!F:F,Stock2!J:J,"")}
B53: SM-S731BZKBTHL | C53: JETBLACK | D53: 22900 | E53: {=_xlfn.XLOOKUP(B53,Stock1!F:F,Stock1!J:J,"")} | F53: {=_xlfn.XLOOKUP(B53,Stock2!F:F,Stock2!J:J,"")}
B54: SM-S731BZWBTHL | C54: WHITE | D54: 22900 | E54: {=_xlfn.XLOOKUP(B54,Stock1!F:F,Stock1!J:J,"")} | F54: {=_xlfn.XLOOKUP(B54,Stock2!F:F,Stock2!J:J,"")}
A55: Galaxy S25 FE (8/256GB) | B55: F-N45731BDBCTH | C55: NAVY | D55: 25900 | E55: {=_xlfn.XLOOKUP(B55,Stock1!F:F,Stock1!J:J,"")} | F55: {=_xlfn.XLOOKUP(B55,Stock2!F:F,Stock2!J:J,"")}
B56: F-N45731BLBCTH | C56: ICYBLUE | D56: 25900 | E56: {=_xlfn.XLOOKUP(B56,Stock1!F:F,Stock1!J:J,"")} | F56: {=_xlfn.XLOOKUP(B56,Stock2!F:F,Stock2!J:J,"")}
B57: F-N45731BZKCTH | C57: JETBLACK | D57: 25900 | E57: {=_xlfn.XLOOKUP(B57,Stock1!F:F,Stock1!J:J,"")} | F57: {=_xlfn.XLOOKUP(B57,Stock2!F:F,Stock2!J:J,"")}
B58: F-N45731BZWCTH | C58: WHITE | D58: 25900 | E58: {=_xlfn.XLOOKUP(B58,Stock1!F:F,Stock1!J:J,"")} | F58: {=_xlfn.XLOOKUP(B58,Stock2!F:F,Stock2!J:J,"")}
A59: Galaxy S25 FE (8/256GB) | B59: SM-S731BDBCTHL | C59: NAVY | D59: 25900 | E59: {=_xlfn.XLOOKUP(B59,Stock1!F:F,Stock1!J:J,"")} -> 3 | F59: {=_xlfn.XLOOKUP(B59,Stock2!F:F,Stock2!J:J,"")} -> 6
B60: SM-S731BLBCTHL | C60: ICYBLUE | D60: 25900 | E60: {=_xlfn.XLOOKUP(B60,Stock1!F:F,Stock1!J:J,"")} -> 3 | F60: {=_xlfn.XLOOKUP(B60,Stock2!F:F,Stock2!J:J,"")} -> 3
B61: SM-S731BZKCTHL | C61: JETBLACK | D61: 25900 | E61: {=_xlfn.XLOOKUP(B61,Stock1!F:F,Stock1!J:J,"")} -> 4 | F61: {=_xlfn.XLOOKUP(B61,Stock2!F:F,Stock2!J:J,"")} -> 4
B62: SM-S731BZWCTHL | C62: WHITE | D62: 25900 | E62: {=_xlfn.XLOOKUP(B62,Stock1!F:F,Stock1!J:J,"")} -> 2 | F62: {=_xlfn.XLOOKUP(B62,Stock2!F:F,Stock2!J:J,"")}
A63: Galaxy S24 Ultra 5G 12/256GB | B63: SM-S928BZKCTHL | C63: BLACK | D63: 34900 | E63: {=_xlfn.XLOOKUP(B63,Stock1!F:F,Stock1!J:J,"")} | F63: {=_xlfn.XLOOKUP(B63,Stock2!F:F,Stock2!J:J,"")} | G63: 4000 | H63: =D63-G63 -> 30900
B64: SM-S928BZTCTHL | C64: TITANIUM | D64: 34900 | E64: {=_xlfn.XLOOKUP(B64,Stock1!F:F,Stock1!J:J,"")} | F64: {=_xlfn.XLOOKUP(B64,Stock2!F:F,Stock2!J:J,"")} | G64: 4000 | H64: =D64-G64 -> 30900
B65: SM-S928BZVCTHL | C65: VIOLET | D65: 34900 | E65: {=_xlfn.XLOOKUP(B65,Stock1!F:F,Stock1!J:J,"")} | F65: {=_xlfn.XLOOKUP(B65,Stock2!F:F,Stock2!J:J,"")} | G65: 4000 | H65: =D65-G65 -> 30900
B66: SM-S928BZYCTHL | C66: YELLOW | D66: 34900 | E66: {=_xlfn.XLOOKUP(B66,Stock1!F:F,Stock1!J:J,"")} | F66: {=_xlfn.XLOOKUP(B66,Stock2!F:F,Stock2!J:J,"")} | G66: 4000 | H66: =D66-G66 -> 30900
A67: Galaxy S25 5G 12/256GB | B67: SM-S931BLBCTHL | C67: BLUE | D67: 29900 | E67: {=_xlfn.XLOOKUP(B67,Stock1!F:F,Stock1!J:J,"")} | F67: {=_xlfn.XLOOKUP(B67,Stock2!F:F,Stock2!J:J,"")} | G67: 5000 | H67: =D67-G67 -> 24900 | J67: 8000 | K67: =D67-J67 -> 21900 | L67: 02 | M67: Discount 5,000 + Trade-Up 2,000
B68: SM-S931BLGCTHL | C68: MINT | D68: 29900 | E68: {=_xlfn.XLOOKUP(B68,Stock1!F:F,Stock1!J:J,"")} | F68: {=_xlfn.XLOOKUP(B68,Stock2!F:F,Stock2!J:J,"")} | G68: 5000 | H68: =D68-G68 -> 24900 | J68: 8000 | K68: =D68-J68 -> 21900
B69: SM-S931BDBCTHL | C69: NAVY | D69: 29900 | E69: {=_xlfn.XLOOKUP(B69,Stock1!F:F,Stock1!J:J,"")} | F69: {=_xlfn.XLOOKUP(B69,Stock2!F:F,Stock2!J:J,"")} | G69: 5000 | H69: =D69-G69 -> 24900 | J69: 8000 | K69: =D69-J69 -> 21900
B70: SM-S931BZSCTHL | C70: SILVER SHADOW | D70: 29900 | E70: {=_xlfn.XLOOKUP(B70,Stock1!F:F,Stock1!J:J,"")} | F70: {=_xlfn.XLOOKUP(B70,Stock2!F:F,Stock2!J:J,"")} | G70: 5000 | H70: =D70-G70 -> 24900 | J70: 8000 | K70: =D70-J70 -> 21900
A71: Galaxy S25 5G 12/512GB | B71: SM-S931BLBQTHL | C71: BLUE | D71: 34900 | E71: {=_xlfn.XLOOKUP(B71,Stock1!F:F,Stock1!J:J,"")} | F71: {=_xlfn.XLOOKUP(B71,Stock2!F:F,Stock2!J:J,"")} | G71: 5000 | H71: =D71-G71 -> 29900 | J71: 8000 | K71: =D71-J71 -> 26900
B72: SM-S931BLGQTHL | C72: MINT | D72: 34900 | E72: {=_xlfn.XLOOKUP(B72,Stock1!F:F,Stock1!J:J,"")} | F72: {=_xlfn.XLOOKUP(B72,Stock2!F:F,Stock2!J:J,"")} | G72: 5000 | H72: =D72-G72 -> 29900 | J72: 8000 | K72: =D72-J72 -> 26900
B73: SM-S931BDBQTHL | C73: NAVY | D73: 34900 | E73: {=_xlfn.XLOOKUP(B73,Stock1!F:F,Stock1!J:J,"")} | F73: {=_xlfn.XLOOKUP(B73,Stock2!F:F,Stock2!J:J,"")} | G73: 5000 | H73: =D73-G73 -> 29900 | J73: 8000 | K73: =D73-J73 -> 26900
B74: SM-S931BZSQTHL | C74: SILVER SHADOW | D74: 34900 | E74: {=_xlfn.XLOOKUP(B74,Stock1!F:F,Stock1!J:J,"")} | F74: {=_xlfn.XLOOKUP(B74,Stock2!F:F,Stock2!J:J,"")} | G74: 5000 | H74: =D74-G74 -> 29900 | J74: 8000 | K74: =D74-J74 -> 26900
A75: Galaxy S25+ 5G 12/256GB | B75: SM-S936BLBBTHL | C75: BLUE | D75: 36900 | E75: {=_xlfn.XLOOKUP(B75,Stock1!F:F,Stock1!J:J,"")} | F75: {=_xlfn.XLOOKUP(B75,Stock2!F:F,Stock2!J:J,"")} | G75: 5000 | H75: =D75-G75 -> 31900 | J75: 8000 | K75: =D75-J75 -> 28900
B76: SM-S936BLGBTHL | C76: MINT | D76: 36900 | E76: {=_xlfn.XLOOKUP(B76,Stock1!F:F,Stock1!J:J,"")} | F76: {=_xlfn.XLOOKUP(B76,Stock2!F:F,Stock2!J:J,"")} | G76: 5000 | H76: =D76-G76 -> 31900 | J76: 8000 | K76: =D76-J76 -> 28900
B77: SM-S936BDBBTHL | C77: NAVY | D77: 36900 | E77: {=_xlfn.XLOOKUP(B77,Stock1!F:F,Stock1!J:J,"")} | F77: {=_xlfn.XLOOKUP(B77,Stock2!F:F,Stock2!J:J,"")} | G77: 5000 | H77: =D77-G77 -> 31900 | J77: 8000 | K77: =D77-J77 -> 28900
B78: SM-S936BZSBTHL | C78: SILVER SHADOW | D78: 36900 | E78: {=_xlfn.XLOOKUP(B78,Stock1!F:F,Stock1!J:J,"")} | F78: {=_xlfn.XLOOKUP(B78,Stock2!F:F,Stock2!J:J,"")} | G78: 5000 | H78: =D78-G78 -> 31900 | J78: 8000 | K78: =D78-J78 -> 28900
A79: Galaxy S25+ 5G 12/512GB | B79: SM-S936BLBCTHL | C79: BLUE | D79: 41900 | E79: {=_xlfn.XLOOKUP(B79,Stock1!F:F,Stock1!J:J,"")} | F79: {=_xlfn.XLOOKUP(B79,Stock2!F:F,Stock2!J:J,"")} | G79: 5000 | H79: =D79-G79 -> 36900 | J79: 8000 | K79: =D79-J79 -> 33900
B80: SM-S936BLGCTHL | C80: MINT | D80: 41900 | E80: {=_xlfn.XLOOKUP(B80,Stock1!F:F,Stock1!J:J,"")} | F80: {=_xlfn.XLOOKUP(B80,Stock2!F:F,Stock2!J:J,"")} | G80: 5000 | H80: =D80-G80 -> 36900 | J80: 8000 | K80: =D80-J80 -> 33900
B81: SM-S936BDBCTHL | C81: NAVY | D81: 41900 | E81: {=_xlfn.XLOOKUP(B81,Stock1!F:F,Stock1!J:J,"")} | F81: {=_xlfn.XLOOKUP(B81,Stock2!F:F,Stock2!J:J,"")} | G81: 5000 | H81: =D81-G81 -> 36900 | J81: 8000 | K81: =D81-J81 -> 33900
B82: SM-S936BZSCTHL | C82: SILVER SHADOW | D82: 41900 | E82: {=_xlfn.XLOOKUP(B82,Stock1!F:F,Stock1!J:J,"")} | F82: {=_xlfn.XLOOKUP(B82,Stock2!F:F,Stock2!J:J,"")} | G82: 5000 | H82: =D82-G82 -> 36900 | J82: 8000 | K82: =D82-J82 -> 33900
A83: Galaxy S25 Ultra 5G 12/256GB | B83: SM-S938BZKBTHL | C83: BLACK | D83: 46900 | E83: {=_xlfn.XLOOKUP(B83,Stock1!F:F,Stock1!J:J,"")} | F83: {=_xlfn.XLOOKUP(B83,Stock2!F:F,Stock2!J:J,"")} | G83: 6000 | H83: =D83-G83 -> 40900 | J83: 8000 | K83: =D83-J83 -> 38900 | M83: Discount 6,000 + Trade-Up 2,000
B84: SM-S938BZBBTHL | C84: BLUE | D84: 46900 | E84: {=_xlfn.XLOOKUP(B84,Stock1!F:F,Stock1!J:J,"")} | F84: {=_xlfn.XLOOKUP(B84,Stock2!F:F,Stock2!J:J,"")} | G84: 6000 | H84: =D84-G84 -> 40900 | J84: 8000 | K84: =D84-J84 -> 38900
B85: SM-S938BZTBTHL | C85: GRAY | D85: 46900 | E85: {=_xlfn.XLOOKUP(B85,Stock1!F:F,Stock1!J:J,"")} | F85: {=_xlfn.XLOOKUP(B85,Stock2!F:F,Stock2!J:J,"")} | G85: 6000 | H85: =D85-G85 -> 40900 | J85: 8000 | K85: =D85-J85 -> 38900
B86: SM-S938BZSBTHL | C86: SILVER | D86: 46900 | E86: {=_xlfn.XLOOKUP(B86,Stock1!F:F,Stock1!J:J,"")} | F86: {=_xlfn.XLOOKUP(B86,Stock2!F:F,Stock2!J:J,"")} | G86: 6000 | H86: =D86-G86 -> 40900 | J86: 8000 | K86: =D86-J86 -> 38900
A87: Galaxy S25 Ultra 5G 12/512GB | B87: SM-S938BZKCTHL | C87: BLACK | D87: 52900 | E87: {=_xlfn.XLOOKUP(B87,Stock1!F:F,Stock1!J:J,"")} | F87: {=_xlfn.XLOOKUP(B87,Stock2!F:F,Stock2!J:J,"")} | G87: 6000 | H87: =D87-G87 -> 46900 | J87: 8000 | K87: =D87-J87 -> 44900
B88: SM-S938BZBCTHL | C88: BLUE | D88: 52900 | E88: {=_xlfn.XLOOKUP(B88,Stock1!F:F,Stock1!J:J,"")} | F88: {=_xlfn.XLOOKUP(B88,Stock2!F:F,Stock2!J:J,"")} | G88: 6000 | H88: =D88-G88 -> 46900 | J88: 8000 | K88: =D88-J88 -> 44900
B89: SM-S938BZTCTHL | C89: GRAY | D89: 52900 | E89: {=_xlfn.XLOOKUP(B89,Stock1!F:F,Stock1!J:J,"")} | F89: {=_xlfn.XLOOKUP(B89,Stock2!F:F,Stock2!J:J,"")} | G89: 6000 | H89: =D89-G89 -> 46900 | J89: 8000 | K89: =D89-J89 -> 44900
B90: SM-S938BZSCTHL | C90: SILVER | D90: 52900 | E90: {=_xlfn.XLOOKUP(B90,Stock1!F:F,Stock1!J:J,"")} | F90: {=_xlfn.XLOOKUP(B90,Stock2!F:F,Stock2!J:J,"")} | G90: 6000 | H90: =D90-G90 -> 46900 | J90: 8000 | K90: =D90-J90 -> 44900
A91: Galaxy S25 Ultra 5G 12/1TB | B91: SM-S938BZKQTHL | C91: BLACK | D91: 62900 | E91: {=_xlfn.XLOOKUP(B91,Stock1!F:F,Stock1!J:J,"")} | F91: {=_xlfn.XLOOKUP(B91,Stock2!F:F,Stock2!J:J,"")} | G91: 6000 | H91: =D91-G91 -> 56900 | J91: 8000 | K91: =D91-J91 -> 54900
B92: SM-S938BZBQTHL | C92: BLUE | D92: 62900 | E92: {=_xlfn.XLOOKUP(B92,Stock1!F:F,Stock1!J:J,"")} | F92: {=_xlfn.XLOOKUP(B92,Stock2!F:F,Stock2!J:J,"")} | G92: 6000 | H92: =D92-G92 -> 56900 | J92: 8000 | K92: =D92-J92 -> 54900
B93: SM-S938BZTQTHL | C93: GRAY | D93: 62900 | E93: {=_xlfn.XLOOKUP(B93,Stock1!F:F,Stock1!J:J,"")} | F93: {=_xlfn.XLOOKUP(B93,Stock2!F:F,Stock2!J:J,"")} | G93: 6000 | H93: =D93-G93 -> 56900 | J93: 8000 | K93: =D93-J93 -> 54900
B94: SM-S938BZSQTHL | C94: SILVER | D94: 62900 | E94: {=_xlfn.XLOOKUP(B94,Stock1!F:F,Stock1!J:J,"")} | F94: {=_xlfn.XLOOKUP(B94,Stock2!F:F,Stock2!J:J,"")} | G94: 6000 | H94: =D94-G94 -> 56900 | J94: 8000 | K94: =D94-J94 -> 54900
A95: Galaxy Z Flip7 FE 8/128GB | B95: SM-F761BZKATHL | C95: Black | D95: 25900 | E95: {=_xlfn.XLOOKUP(B95,Stock1!F:F,Stock1!J:J,"")} | F95: {=_xlfn.XLOOKUP(B95,Stock2!F:F,Stock2!J:J,"")}
B96: SM-F761BZWATHL | C96: White | D96: 25900 | E96: {=_xlfn.XLOOKUP(B96,Stock1!F:F,Stock1!J:J,"")} | F96: {=_xlfn.XLOOKUP(B96,Stock2!F:F,Stock2!J:J,"")}
A97: Galxy Z Flip7 FE 8/256GB | B97: F-NFLIP4FESET2 | C97: Black | D97: 27900 | E97: {=_xlfn.XLOOKUP(B97,Stock1!F:F,Stock1!J:J,"")} | F97: {=_xlfn.XLOOKUP(B97,Stock2!F:F,Stock2!J:J,"")}
B98: SM-F761BZWETHL | C98: White | D98: 27900 | E98: {=_xlfn.XLOOKUP(B98,Stock1!F:F,Stock1!J:J,"")} | F98: {=_xlfn.XLOOKUP(B98,Stock2!F:F,Stock2!J:J,"")}
A99: Galaxy Z Flip7 12/256GB | B99: SM-F766BZRATHL | C99: Coralred | D99: 40900 | E99: {=_xlfn.XLOOKUP(B99,Stock1!F:F,Stock1!J:J,"")} | F99: {=_xlfn.XLOOKUP(B99,Stock2!F:F,Stock2!J:J,"")} | G99: 3000 | H99: =D99-G99 -> 37900 | M99: Discount 3,000 + Trade-Up 5,000 ประกันจอ 2 ปี+SF+ Capped DP 20%
B100: SM-F766BZKATHL | C100: Jet Black | D100: 40900 | E100: {=_xlfn.XLOOKUP(B100,Stock1!F:F,Stock1!J:J,"")} | F100: {=_xlfn.XLOOKUP(B100,Stock2!F:F,Stock2!J:J,"")} | G100: 3000 | H100: =D100-G100 -> 37900
...

Sheet ชีต61

Sheet SES Student Campaign
A2: Student Promotion model list for SES & SPS
A3: Period: 01 Jun - 05 Jul 2026
A4: Model Name | B4: ราคาเต็ม | C4: ราคา Student | D4: % ส่วนลด | E4: ราคาโปรกลาง | F4: ส่วนต่าง STD VS NTW | G4: Remarks
A5: Mobile: A-Series
A6: Galaxy A07 LTE (4/64) | B6: 3299 | C6: 2969 | D6: 0.1 | E6: 3299 | F6: 330
A7: Galaxy A07 LTE (4/128) | B7: 3999 | C7: 3599 | D7: 0.1 | E7: 3999 | F7: 400
A8: Galaxy A07 5G (6/128) | B8: 5999 | C8: 5399 | D8: 0.1 | E8: 5999 | F8: 600 | G8: ใช้ร่วมกับ SF+ ดาวน์ไม่เกิน 20% ได้เฉพาะ UPC เท่านั้น
A9: Galaxy A17 5G (8/128) | B9: 7499 | C9: 6749 | D9: 0.1 | E9: 7499 | F9: 750
A10: Galaxy A17 5G (8/256) | B10: 8999 | C10: 8099 | D10: 0.1 | E10: 8999 | F10: 900
A11: Galaxy A37 5G (8/256) | B11: 13999 | C11: 12599 | D11: 0.1 | E11: 13999 | F11: 1400 | G11: ใช้ร่วม SF+ ดาวน์ไม่เกิน 10% ได้
A12: Galaxy A57 5G (8/256) | B12: 16999 | C12: 15299 | D12: 0.1 | E12: 15999 | F12: 700
A13: Galaxy A57 5G (12/256) | B13: 17999 | C13: 16199 | D13: 0.1 | E13: 16999 | F13: 800
A14: Galaxy A57 5G (12/512) | B14: 20999 | C14: 18899 | D14: 0.1 | E14: 19999 | F14: 1100
A15: Mobile: S-Series
A16: Galaxy S25 FE (12/128) | B16: 22900 | C16: 19465 | D16: 0.15 | E16: 21900 | F16: 2435 | G16: ใช้ร่วม SF+ ดาวน์ไม่เกิน 10% ได้
A17: Galaxy S25 FE (12/256) | B17: 26900 | C17: 22865 | D17: 0.15 | E17: 24900 | F17: 2035
A18: Galaxy S26 Ultra (12/256) | B18: 46900 | C18: 42210 | D18: 0.1 | E18: 44900 | F18: 2690 | G18: ใช้ร่วม SF+ ดาวน์ไม่เกิน 20% ได้
A19: Galaxy S26+ (12/256) | B19: 40900 | C19: 36810 | D19: 0.1 | E19: 38900 | F19: 2090 | G19: ใช้ร่วม SF+ ดาวน์ไม่เกิน 10% ได้
A20: Galaxy S26 (12/256) | B20: 33900 | C20: 30510 | D20: 0.1 | E20: 31900 | F20: 1390
A21: Mobile: Z-Series
A22: Galaxy Z Flip7 (12/256) | B22: 40900 | C22: 34765 | D22: 0.15 | E22: 36900 | F22: 2135 | G22: ใช้ร่วม SF+ ดาวน์ไม่เกิน 10% ได้
A23: Galaxy Z Flip7 (12/512) | B23: 48900 | C23: 41565 | D23: 0.15 | E23: 44900 | F23: 3335
A24: Tablet: A
A25: Galaxy Tab A11 LTE (8/128) | B25: 7490 | C25: 6367 | D25: 0.15 | E25: 6990 | F25: 624 | G25: ไม่สามารถใช้ร่วมกับ SF+ ดาวน์ไม่เกิน 10% ได้ แลกซื้อ Keyboard / Book Cover ลด 50%
A26: Galaxy Tab A11+ Wifi (6/128) | B26: 8490 | C26: 7217 | D26: 0.15 | E26: 7990 | F26: 774
A27: Galaxy Tab A11+ 5G (6/128) | B27: 10490 | C27: 8917 | D27: 0.15 | E27: 9990 | F27: 1074
A28: Tablet: Lite
A29: Galaxy Tab S10 Lite Wi-Fi | B29: 12990 | C29: 11691 | D29: 0.1 | E29: 12990 | F29: 1299 | G29: ฟรี Keyboard Cover (1,990) GP-FCX400RLABH
A30: Galaxy Tab S10 Lite 5G | B30: 16990 | C30: 15291 | D30: 0.1 | E30: 16990 | F30: 1699
A31: Tablet: FE
A32: Galaxy Tab S10 FE Wi-Fi | B32: 19900 | C32: 16915 | D32: 0.15 | E32: 17900 | F32: 985 | G32: แลกซื้อ Keyboard / Book Cover ลด 50%
A33: Galaxy Tab S10 FE 5G | B33: 22900 | C33: 19465 | D33: 0.15 | E33: 20900 | F33: 1435
A34: Galaxy Tab S10 FE+ WiFi | B34: 27900 | C34: 23715 | D34: 0.15 | E34: 23900 | F34: 185
A35: Galaxy Tab S10 FE+ 5G | B35: 30900 | C35: 26265 | D35: 0.15 | E35: 26900 | F35: 635
A36: Tablet: S
A37: Galaxy Tab S11 Wi-Fi | B37: 28900 | C37: 24565 | D37: 0.15 | E37: 26900 | F37: 2335 | G37: แลกซื้อ Keyboard / Book Cover ลด 50%
A38: Galaxy Tab S11 5G | B38: 33900 | C38: 28815 | D38: 0.15 | E38: 31900 | F38: 3085
A39: Galaxy Tab S11 Ultra 5G | B39: 48900 | C39: 41565 | D39: 0.15 | E39: 45900 | F39: 4335

Sheet ของแถม
A1: SM88592896555607 | B1: Model Code | D1: "RRP In.vat" | E1: Stock ชั้น1 | F1: Stock จริง | M1: หมายเหตุ | N1: จำนวน | O1: ขาด/เกิน | X1: {=_xlfn.XLOOKUP("Other",Stock1!A1,Stock1!I1,"")} | Y1: {=_xlfn.XLOOKUP(X1,Stock1!I1,Stock1!F1,"")} | Z1: {=_xlfn.XLOOKUP(X1,Stock1!I1,Stock1!J1,"")} | AA1: {=_xlfn.XLOOKUP(Y1,DATAPremium!A:A,DATAPremium!C:C,"")}
A2: =UNIQUE(X:X) | B2: =UNIQUE(Y:Y) | X2: {=_xlfn.XLOOKUP("Other",Stock1!A2,Stock1!I2,"")} | Y2: {=_xlfn.XLOOKUP(X2,Stock1!I2,Stock1!F2,"")} | Z2: {=_xlfn.XLOOKUP(X2,Stock1!I2,Stock1!J2,"")} | AA2: {=_xlfn.XLOOKUP(Y2,DATAPremium!A:A,DATAPremium!C:C,"")}
A3: [PM] Double Wall Stainless Steel 600ml | B3: 6931481215710 | C3: {=_xlfn.XLOOKUP(B3,DATAPremium!A:A,DATAPremium!C:C,"")} -> Tablet | D3: {=_xlfn.XLOOKUP(B3,Stock1!F:F,Stock1!E:E,"")} -> 299 | E3: {=_xlfn.XLOOKUP(B3,Stock1!F:F,Stock1!J:J,"")} -> 16 | F3: 15 | N3: =F3-E3 -> -1 | X3: {=_xlfn.XLOOKUP("Other",Stock1!A3,Stock1!I3,"")} | Y3: {=_xlfn.XLOOKUP(X3,Stock1!I3,Stock1!F3,"")} | Z3: {=_xlfn.XLOOKUP(X3,Stock1!I3,Stock1!J3,"")} | AA3: {=_xlfn.XLOOKUP(Y3,DATAPremium!A:A,DATAPremium!C:C,"")}
A4: Premium D-Power M22 Speaker Bluetooth | B4: 8859289657762 | C4: {=_xlfn.XLOOKUP(B4,DATAPremium!A:A,DATAPremium!C:C,"")} -> Smartphone 10,000 up | D4: {=_xlfn.XLOOKUP(B4,Stock1!F:F,Stock1!E:E,"")} -> 599 | E4: {=_xlfn.XLOOKUP(B4,Stock1!F:F,Stock1!J:J,"")} -> 19 | F4: 19 | N4: =F4-E4 -> 0 | X4: {=_xlfn.XLOOKUP("Other",Stock1!A4,Stock1!I4,"")} | Y4: {=_xlfn.XLOOKUP(X4,Stock1!I4,Stock1!F4,"")} | Z4: {=_xlfn.XLOOKUP(X4,Stock1!I4,Stock1!J4,"")} | AA4: {=_xlfn.XLOOKUP(Y4,DATAPremium!A:A,DATAPremium!C:C,"")}
A5: Premium SAMSUNG TC-04 (Type-C) | B5: 8859289665477 | C5: {=_xlfn.XLOOKUP(B5,DATAPremium!A:A,DATAPremium!C:C,"")} -> Smartphone | D5: {=_xlfn.XLOOKUP(B5,Stock1!F:F,Stock1!E:E,"")} -> 399 | E5: {=_xlfn.XLOOKUP(B5,Stock1!F:F,Stock1!J:J,"")} -> 18 | F5: 19 | N5: =F5-E5 -> 1 | X5: {=_xlfn.XLOOKUP("Other",Stock1!A5,Stock1!I5,"")} | Y5: {=_xlfn.XLOOKUP(X5,Stock1!I5,Stock1!F5,"")} | Z5: {=_xlfn.XLOOKUP(X5,Stock1!I5,Stock1!J5,"")} | AA5: {=_xlfn.XLOOKUP(Y5,DATAPremium!A:A,DATAPremium!C:C,"")}
A6: [PM] Phone Stand First class NO V168 Phoenix | B6: 8859763200989 | C6: {=_xlfn.XLOOKUP(B6,DATAPremium!A:A,DATAPremium!C:C,"")} -> Tablet | D6: {=_xlfn.XLOOKUP(B6,Stock1!F:F,Stock1!E:E,"")} -> 199 | E6: {=_xlfn.XLOOKUP(B6,Stock1!F:F,Stock1!J:J,"")} -> 20 | F6: 20 | N6: =F6-E6 -> 0 | X6: {=_xlfn.XLOOKUP("Other",Stock1!A6,Stock1!I6,"")} | Y6: {=_xlfn.XLOOKUP(X6,Stock1!I6,Stock1!F6,"")} | Z6: {=_xlfn.XLOOKUP(X6,Stock1!I6,Stock1!J6,"")} | AA6: {=_xlfn.XLOOKUP(Y6,DATAPremium!A:A,DATAPremium!C:C,"")}
A7: [Premium] Gaabor weighing scale GWS-M01A - Black | B7: PM4897121002558 | C7: {=_xlfn.XLOOKUP(B7,DATAPremium!A:A,DATAPremium!C:C,"")} | D7: {=_xlfn.XLOOKUP(B7,Stock1!F:F,Stock1!E:E,"")} -> 599 | E7: {=_xlfn.XLOOKUP(B7,Stock1!F:F,Stock1!J:J,"")} -> 3 | F7: 5 | N7: =F7-E7 -> 2 | X7: {=_xlfn.XLOOKUP("Other",Stock1!A7,Stock1!I7,"")} | Y7: {=_xlfn.XLOOKUP(X7,Stock1!I7,Stock1!F7,"")} | Z7: {=_xlfn.XLOOKUP(X7,Stock1!I7,Stock1!J7,"")} | AA7: {=_xlfn.XLOOKUP(Y7,DATAPremium!A:A,DATAPremium!C:C,"")}
A8: [Premium] Gaabor Air Fryer 4L AF-40M01A | B8: PM4897121009793 | C8: {=_xlfn.XLOOKUP(B8,DATAPremium!A:A,DATAPremium!C:C,"")} -> Smartphone 20,000 up | D8: {=_xlfn.XLOOKUP(B8,Stock1!F:F,Stock1!E:E,"")} -> 999 | E8: {=_xlfn.XLOOKUP(B8,Stock1!F:F,Stock1!J:J,"")} -> 27 | F8: 30 | N8: =F8-E8 -> 3 | X8: {=_xlfn.XLOOKUP("Other",Stock1!A8,Stock1!I8,"")} | Y8: {=_xlfn.XLOOKUP(X8,Stock1!I8,Stock1!F8,"")} | Z8: {=_xlfn.XLOOKUP(X8,Stock1!I8,Stock1!J8,"")} | AA8: {=_xlfn.XLOOKUP(Y8,DATAPremium!A:A,DATAPremium!C:C,"")}
A9: Premiun ����Ѻ�� Mini YOUMI-SAMSUNG | B9: PM6931481215697 | C9: {=_xlfn.XLOOKUP(B9,DATAPremium!A:A,DATAPremium!C:C,"")} -> Smartphone 10,000 up | D9: {=_xlfn.XLOOKUP(B9,Stock1!F:F,Stock1!E:E,"")} -> 359 | E9: {=_xlfn.XLOOKUP(B9,Stock1!F:F,Stock1!J:J,"")} -> 51 | F9: 51 | N9: =F9-E9 -> 0 | X9: {=_xlfn.XLOOKUP("Other",Stock1!A9,Stock1!I9,"")} | Y9: {=_xlfn.XLOOKUP(X9,Stock1!I9,Stock1!F9,"")} | Z9: {=_xlfn.XLOOKUP(X9,Stock1!I9,Stock1!J9,"")} | AA9: {=_xlfn.XLOOKUP(Y9,DATAPremium!A:A,DATAPremium!C:C,"")}
A10: Premium Robot Portable handheld fan RT-HF01 - White | B10: PM6936678491526 | C10: {=_xlfn.XLOOKUP(B10,DATAPremium!A:A,DATAPremium!C:C,"")} -> Smartphone 5,000 up | D10: {=_xlfn.XLOOKUP(B10,Stock1!F:F,Stock1!E:E,"")} -> 399 | E10: {=_xlfn.XLOOKUP(B10,Stock1!F:F,Stock1!J:J,"")} -> 6 | F10: 6 | N10: =F10-E10 -> 0 | X10: {=_xlfn.XLOOKUP("Other",Stock1!A10,Stock1!I10,"")} | Y10: {=_xlfn.XLOOKUP(X10,Stock1!I10,Stock1!F10,"")} | Z10: {=_xlfn.XLOOKUP(X10,Stock1!I10,Stock1!J10,"")} | AA10: {=_xlfn.XLOOKUP(Y10,DATAPremium!A:A,DATAPremium!C:C,"")}
A11: Premium D-Power Blackpack-SAMSUNG | B11: PM8859289684768 | C11: {=_xlfn.XLOOKUP(B11,DATAPremium!A:A,DATAPremium!C:C,"")} -> Smartphone 8,000 up | D11: {=_xlfn.XLOOKUP(B11,Stock1!F:F,Stock1!E:E,"")} -> 599 | E11: {=_xlfn.XLOOKUP(B11,Stock1!F:F,Stock1!J:J,"")} -> 2 | F11: 2 | N11: =F11-E11 -> 0 | X11: {=_xlfn.XLOOKUP("Other",Stock1!A11,Stock1!I11,"")} | Y11: {=_xlfn.XLOOKUP(X11,Stock1!I11,Stock1!F11,"")} | Z11: {=_xlfn.XLOOKUP(X11,Stock1!I11,Stock1!J11,"")} | AA11: {=_xlfn.XLOOKUP(Y11,DATAPremium!A:A,DATAPremium!C:C,"")}
A12: [PM] Backpack Fashion Phoenix | B12: PREMIUM0017044 | C12: {=_xlfn.XLOOKUP(B12,DATAPremium!A:A,DATAPremium!C:C,"")} -> Tablet | D12: {=_xlfn.XLOOKUP(B12,Stock1!F:F,Stock1!E:E,"")} -> 199 | E12: {=_xlfn.XLOOKUP(B12,Stock1!F:F,Stock1!J:J,"")} -> 27 | F12: 27 | N12: =F12-E12 -> 0 | X12: {=_xlfn.XLOOKUP("Other",Stock1!A12,Stock1!I12,"")} | Y12: {=_xlfn.XLOOKUP(X12,Stock1!I12,Stock1!F12,"")} | Z12: {=_xlfn.XLOOKUP(X12,Stock1!I12,Stock1!J12,"")} | AA12: {=_xlfn.XLOOKUP(Y12,DATAPremium!A:A,DATAPremium!C:C,"")}
A13: [PM] Sling Bag Phoenix | B13: PREMIUM0017046 | C13: {=_xlfn.XLOOKUP(B13,DATAPremium!A:A,DATAPremium!C:C,"")} | D13: {=_xlfn.XLOOKUP(B13,Stock1!F:F,Stock1!E:E,"")} -> 199 | E13: {=_xlfn.XLOOKUP(B13,Stock1!F:F,Stock1!J:J,"")} -> 20 | F13: 20 | N13: =F13-E13 -> 0 | X13: {=_xlfn.XLOOKUP("Other",Stock1!A13,Stock1!I13,"")} | Y13: {=_xlfn.XLOOKUP(X13,Stock1!I13,Stock1!F13,"")} | Z13: {=_xlfn.XLOOKUP(X13,Stock1!I13,Stock1!J13,"")} | AA13: {=_xlfn.XLOOKUP(Y13,DATAPremium!A:A,DATAPremium!C:C,"")}
A14: [PM] Small Talk TC-04 TypeC Tablet | B14: PREMIUM-665477 | C14: {=_xlfn.XLOOKUP(B14,DATAPremium!A:A,DATAPremium!C:C,"")} -> Tablet | D14: {=_xlfn.XLOOKUP(B14,Stock1!F:F,Stock1!E:E,"")} -> 199 | E14: {=_xlfn.XLOOKUP(B14,Stock1!F:F,Stock1!J:J,"")} -> 27 | F14: 28 | N14: =F14-E14 -> 1 | X14: {=_xlfn.XLOOKUP("Other",Stock1!A14,Stock1!I14,"")} | Y14: {=_xlfn.XLOOKUP(X14,Stock1!I14,Stock1!F14,"")} | Z14: {=_xlfn.XLOOKUP(X14,Stock1!I14,Stock1!J14,"")} | AA14: {=_xlfn.XLOOKUP(Y14,DATAPremium!A:A,DATAPremium!C:C,"")}
... A28: Premium Samsung SmartTag2 - S26 Series | B28: Z-SMARTTAG2WMR | C28: {=_xlfn.XLOOKUP(B28,DATAPremium!A:A,DATAPremium!C:C,"")} -> Smartphone S26 Ultra | D28: {=_xlfn.XLOOKUP(B28,Stock1!F:F,Stock1!E:E,"")} -> 1090 | E28: {=_xlfn.XLOOKUP(B28,Stock1!F:F,Stock1!J:J,"")} -> 7 | F28: 7 | N28: =F28-E28 -> 0 | X28: {=_xlfn.XLOOKUP("Other",Stock1!A28,Stock1!I28,"")} | Y28: {=_xlfn.XLOOKUP(X28,Stock1!I28,Stock1!F28,"")} | Z28: {=_xlfn.XLOOKUP(X28,Stock1!I28,Stock1!J28,"")} | AA28: {=_xlfn.XLOOKUP(Y28,DATAPremium!A:A,DATAPremium!C:C,"")}
C29: {=_xlfn.XLOOKUP(B29,DATAPremium!A:A,DATAPremium!C:C,"")} | D29: {=_xlfn.XLOOKUP(B29,Stock1!F:F,Stock1!E:E,"")} | E29: {=_xlfn.XLOOKUP(B29,Stock1!F:F,Stock1!J:J,"")} | N29: =F29-E29 -> 0 | X29: {=_xlfn.XLOOKUP("Other",Stock1!A29,Stock1!I29,"")} | Y29: {=_xlfn.XLOOKUP(X29,Stock1!I29,Stock1!F29,"")} | Z29: {=_xlfn.XLOOKUP(X29,Stock1!I29,Stock1!J29,"")} | AA29: {=_xlfn.XLOOKUP(Y29,DATAPremium!A:A,DATAPremium!C:C,"")}
C30: {=_xlfn.XLOOKUP(B30,DATAPremium!A:A,DATAPremium!C:C,"")} | D30: {=_xlfn.XLOOKUP(B30,Stock1!F:F,Stock1!E:E,"")} | E30: {=_xlfn.XLOOKUP(B30,Stock1!F:F,Stock1!J:J,"")} | N30: =F30-E30 -> 0 | X30: {=_xlfn.XLOOKUP("Other",Stock1!A30,Stock1!I30,"")} | Y30: {=_xlfn.XLOOKUP(X30,Stock1!I30,Stock1!F30,"")} | Z30: {=_xlfn.XLOOKUP(X30,Stock1!I30,Stock1!J30,"")} | AA30: {=_xlfn.XLOOKUP(Y30,DATAPremium!A:A,DATAPremium!C:C,"")}
C31: {=_xlfn.XLOOKUP(B31,DATAPremium!A:A,DATAPremium!C:C,"")} | D31: {=_xlfn.XLOOKUP(B31,Stock1!F:F,Stock1!E:E,"")} | E31: {=_xlfn.XLOOKUP(B31,Stock1!F:F,Stock1!J:J,"")} | N31: =F31-E31 -> 0 | X31: {=_xlfn.XLOOKUP("Other",Stock1!A31,Stock1!I31,"")} | Y31: {=_xlfn.XLOOKUP(X31,Stock1!I31,Stock1!F31,"")} | Z31: {=_xlfn.XLOOKUP(X31,Stock1!I31,Stock1!J31,"")} | AA31: {=_xlfn.XLOOKUP(Y31,DATAPremium!A:A,DATAPremium!C:C,"")}
C32: {=_xlfn.XLOOKUP(B32,DATAPremium!A:A,DATAPremium!C:C,"")} | D32: {=_xlfn.XLOOKUP(B32,Stock1!F:F,Stock1!E:E,"")} | E32: {=_xlfn.XLOOKUP(B32,Stock1!F:F,Stock1!J:J,"")} | N32: =F32-E32 -> 0 | X32: {=_xlfn.XLOOKUP("Other",Stock1!A32,Stock1!I32,"")} | Y32: {=_xlfn.XLOOKUP(X32,Stock1!I32,Stock1!F32,"")} | Z32: {=_xlfn.XLOOKUP(X32,Stock1!I32,Stock1!J32,"")} | AA32: {=_xlfn.XLOOKUP(Y32,DATAPremium!A:A,DATAPremium!C:C,"")}
C33: {=_xlfn.XLOOKUP(B33,DATAPremium!A:A,DATAPremium!C:C,"")} | D33: {=_xlfn.XLOOKUP(B33,Stock1!F:F,Stock1!E:E,"")} | E33: {=_xlfn.XLOOKUP(B33,Stock1!F:F,Stock1!J:J,"")} | N33: =F33-E33 -> 0 | X33: {=_xlfn.XLOOKUP("Other",Stock1!A33,Stock1!I33,"")} | Y33: {=_xlfn.XLOOKUP(X33,Stock1!I33,Stock1!F33,"")} | Z33: {=_xlfn.XLOOKUP(X33,Stock1!I33,Stock1!J33,"")} | AA33: {=_xlfn.XLOOKUP(Y33,DATAPremium!A:A,DATAPremium!C:C,"")}
C34: {=_xlfn.XLOOKUP(B34,DATAPremium!A:A,DATAPremium!C:C,"")} | D34: {=_xlfn.XLOOKUP(B34,Stock1!F:F,Stock1!E:E,"")} | E34: {=_xlfn.XLOOKUP(B34,Stock1!F:F,Stock1!J:J,"")} | N34: =F34-E34 -> 0 | X34: {=_xlfn.XLOOKUP("Other",Stock1!A34,Stock1!I34,"")} | Y34: {=_xlfn.XLOOKUP(X34,Stock1!I34,Stock1!F34,"")} | Z34: {=_xlfn.XLOOKUP(X34,Stock1!I34,Stock1!J34,"")} | AA34: {=_xlfn.XLOOKUP(Y34,DATAPremium!A:A,DATAPremium!C:C,"")}
C35: {=_xlfn.XLOOKUP(B35,DATAPremium!A:A,DATAPremium!C:C,"")} | D35: {=_xlfn.XLOOKUP(B35,Stock1!F:F,Stock1!E:E,"")} | E35: {=_xlfn.XLOOKUP(B35,Stock1!F:F,Stock1!J:J,"")} | N35: =F35-E35 -> 0 | X35: {=_xlfn.XLOOKUP("Other",Stock1!A35,Stock1!I35,"")} | Y35: {=_xlfn.XLOOKUP(X35,Stock1!I35,Stock1!F35,"")} | Z35: {=_xlfn.XLOOKUP(X35,Stock1!I35,Stock1!J35,"")} | AA35: {=_xlfn.XLOOKUP(Y35,DATAPremium!A:A,DATAPremium!C:C,"")}
C36: {=_xlfn.XLOOKUP(B36,DATAPremium!A:A,DATAPremium!C:C,"")} | D36: {=_xlfn.XLOOKUP(B36,Stock1!F:F,Stock1!E:E,"")} | E36: {=_xlfn.XLOOKUP(B36,Stock1!F:F,Stock1!J:J,"")} | N36: =F36-E36 -> 0 | X36: {=_xlfn.XLOOKUP("Other",Stock1!A36,Stock1!I36,"")} | Y36: {=_xlfn.XLOOKUP(X36,Stock1!I36,Stock1!F36,"")} | Z36: {=_xlfn.XLOOKUP(X36,Stock1!I36,Stock1!J36,"")} | AA36: {=_xlfn.XLOOKUP(Y36,DATAPremium!A:A,DATAPremium!C:C,"")}
C37: {=_xlfn.XLOOKUP(B37,DATAPremium!A:A,DATAPremium!C:C,"")} | D37: {=_xlfn.XLOOKUP(B37,Stock1!F:F,Stock1!E:E,"")} | E37: {=_xlfn.XLOOKUP(B37,Stock1!F:F,Stock1!J:J,"")} | N37: =F37-E37 -> 0 | X37: {=_xlfn.XLOOKUP("Other",Stock1!A37,Stock1!I37,"")} | Y37: {=_xlfn.XLOOKUP(X37,Stock1!I37,Stock1!F37,"")} | Z37: {=_xlfn.XLOOKUP(X37,Stock1!I37,Stock1!J37,"")} | AA37: {=_xlfn.XLOOKUP(Y37,DATAPremium!A:A,DATAPremium!C:C,"")}
C38: {=_xlfn.XLOOKUP(B38,DATAPremium!A:A,DATAPremium!C:C,"")} | D38: {=_xlfn.XLOOKUP(B38,Stock1!F:F,Stock1!E:E,"")} | E38: {=_xlfn.XLOOKUP(B38,Stock1!F:F,Stock1!J:J,"")} | N38: =F38-E38 -> 0 | X38: {=_xlfn.XLOOKUP("Other",Stock1!A38,Stock1!I38,"")} | Y38: {=_xlfn.XLOOKUP(X38,Stock1!I38,Stock1!F38,"")} | Z38: {=_xlfn.XLOOKUP(X38,Stock1!I38,Stock1!J38,"")} | AA38: {=_xlfn.XLOOKUP(Y38,DATAPremium!A:A,DATAPremium!C:C,"")}
C39: {=_xlfn.XLOOKUP(B39,DATAPremium!A:A,DATAPremium!C:C,"")} | D39: {=_xlfn.XLOOKUP(B39,Stock1!F:F,Stock1!E:E,"")} | E39: =_xlfn.XLOOKUP(A39,X:X,Z:Z,"") | N39: =F39-E39 -> 0 | X39: {=_xlfn.XLOOKUP("Other",Stock1!A39,Stock1!I39,"")} | Y39: {=_xlfn.XLOOKUP(X39,Stock1!I39,Stock1!F39,"")} | Z39: {=_xlfn.XLOOKUP(X39,Stock1!I39,Stock1!J39,"")} | AA39: {=_xlfn.XLOOKUP(Y39,DATAPremium!A:A,DATAPremium!C:C,"")}
C40: {=_xlfn.XLOOKUP(B40,DATAPremium!A:A,DATAPremium!C:C,"")} | D40: {=_xlfn.XLOOKUP(B40,Stock1!F:F,Stock1!E:E,"")} | E40: =_xlfn.XLOOKUP(A40,X:X,Z:Z,"") | N40: =F40-E40 -> 0 | X40: {=_xlfn.XLOOKUP("Other",Stock1!A40,Stock1!I40,"")} | Y40: {=_xlfn.XLOOKUP(X40,Stock1!I40,Stock1!F40,"")} | Z40: {=_xlfn.XLOOKUP(X40,Stock1!I40,Stock1!J40,"")} | AA40: {=_xlfn.XLOOKUP(Y40,DATAPremium!A:A,DATAPremium!C:C,"")}
C41: {=_xlfn.XLOOKUP(B41,DATAPremium!A:A,DATAPremium!C:C,"")} | E41: =_xlfn.XLOOKUP(A41,X:X,Z:Z,"") | N41: =F41-E41 -> 0 | X41: {=_xlfn.XLOOKUP("Other",Stock1!A41,Stock1!I41,"")} | Y41: {=_xlfn.XLOOKUP(X41,Stock1!I41,Stock1!F41,"")} | Z41: {=_xlfn.XLOOKUP(X41,Stock1!I41,Stock1!J41,"")} | AA41: {=_xlfn.XLOOKUP(Y41,DATAPremium!A:A,DATAPremium!C:C,"")}
C42: {=_xlfn.XLOOKUP(B42,DATAPremium!A:A,DATAPremium!C:C,"")} | E42: =_xlfn.XLOOKUP(A42,X:X,Z:Z,"") | N42: =F42-E42 -> 0 | X42: {=_xlfn.XLOOKUP("Other",Stock1!A42,Stock1!I42,"")} | Y42: {=_xlfn.XLOOKUP(X42,Stock1!I42,Stock1!F42,"")} | Z42: {=_xlfn.XLOOKUP(X42,Stock1!I42,Stock1!J42,"")} | AA42: {=_xlfn.XLOOKUP(Y42,DATAPremium!A:A,DATAPremium!C:C,"")}
A43: , | C43: {=_xlfn.XLOOKUP(B43,DATAPremium!A:A,DATAPremium!C:C,"")} | E43: =_xlfn.XLOOKUP(A43,X:X,Z:Z,"") | N43: =F43-E43 -> 0 | X43: {=_xlfn.XLOOKUP("Other",Stock1!A43,Stock1!I43,"")} | Y43: {=_xlfn.XLOOKUP(X43,Stock1!I43,Stock1!F43,"")} | Z43: {=_xlfn.XLOOKUP(X43,Stock1!I43,Stock1!J43,"")} | AA43: {=_xlfn.XLOOKUP(Y43,DATAPremium!A:A,DATAPremium!C:C,"")}
C44: {=_xlfn.XLOOKUP(B44,DATAPremium!A:A,DATAPremium!C:C,"")} | E44: =_xlfn.XLOOKUP(A44,X:X,Z:Z,"") | N44: =F44-E44 -> 0 | X44: {=_xlfn.XLOOKUP("Other",Stock1!A44,Stock1!I44,"")} | Y44: {=_xlfn.XLOOKUP(X44,Stock1!I44,Stock1!F44,"")} | Z44: {=_xlfn.XLOOKUP(X44,Stock1!I44,Stock1!J44,"")} | AA44: {=_xlfn.XLOOKUP(Y44,DATAPremium!A:A,DATAPremium!C:C,"")}
C45: {=_xlfn.XLOOKUP(B45,DATAPremium!A:A,DATAPremium!C:C,"")} | E45: =_xlfn.XLOOKUP(A45,X:X,Z:Z,"") | N45: =F45-E45 -> 0 | X45: {=_xlfn.XLOOKUP("Other",Stock1!A45,Stock1!I45,"")} | Y45: {=_xlfn.XLOOKUP(X45,Stock1!I45,Stock1!F45,"")} | Z45: {=_xlfn.XLOOKUP(X45,Stock1!I45,Stock1!J45,"")} | AA45: {=_xlfn.XLOOKUP(Y45,DATAPremium!A:A,DATAPremium!C:C,"")}
C46: {=_xlfn.XLOOKUP(B46,DATAPremium!A:A,DATAPremium!C:C,"")} | E46: =_xlfn.XLOOKUP(A46,X:X,Z:Z,"") | N46: =F46-E46 -> 0 | X46: {=_xlfn.XLOOKUP("Other",Stock1!A46,Stock1!I46,"")} | Y46: {=_xlfn.XLOOKUP(X46,Stock1!I46,Stock1!F46,"")} | Z46: {=_xlfn.XLOOKUP(X46,Stock1!I46,Stock1!J46,"")} | AA46: {=_xlfn.XLOOKUP(Y46,DATAPremium!A:A,DATAPremium!C:C,"")}
C47: {=_xlfn.XLOOKUP(B47,DATAPremium!A:A,DATAPremium!C:C,"")} | E47: =_xlfn.XLOOKUP(A47,X:X,Z:Z,"") | N47: =F47-E47 -> 0 | X47: {=_xlfn.XLOOKUP("Other",Stock1!A47,Stock1!I47,"")} | Y47: {=_xlfn.XLOOKUP(X47,Stock1!I47,Stock1!F47,"")} | Z47: {=_xlfn.XLOOKUP(X47,Stock1!I47,Stock1!J47,"")} | AA47: {=_xlfn.XLOOKUP(Y47,DATAPremium!A:A,DATAPremium!C:C,"")}
X48: {=_xlfn.XLOOKUP("Other",Stock1!A48,Stock1!I48,"")} | Y48: {=_xlfn.XLOOKUP(X48,Stock1!I48,Stock1!F48,"")} | Z48: {=_xlfn.XLOOKUP(X48,Stock1!I48,Stock1!J48,"")} | AA48: {=_xlfn.XLOOKUP(Y48,DATAPremium!A:A,DATAPremium!C:C,"")}
X49: {=_xlfn.XLOOKUP("Other",Stock1!A49,Stock1!I49,"")} | Y49: {=_xlfn.XLOOKUP(X49,Stock1!I49,Stock1!F49,"")} | Z49: {=_xlfn.XLOOKUP(X49,Stock1!I49,Stock1!J49,"")} | AA49: {=_xlfn.XLOOKUP(Y49,DATAPremium!A:A,DATAPremium!C:C,"")}
X50: {=_xlfn.XLOOKUP("Other",Stock1!A50,Stock1!I50,"")} | Y50: {=_xlfn.XLOOKUP(X50,Stock1!I50,Stock1!F50,"")} | Z50: {=_xlfn.XLOOKUP(X50,Stock1!I50,Stock1!J50,"")} | AA50: {=_xlfn.XLOOKUP(Y50,DATAPremium!A:A,DATAPremium!C:C,"")}
X51: {=_xlfn.XLOOKUP("Other",Stock1!A51,Stock1!I51,"")} | Y51: {=_xlfn.XLOOKUP(X51,Stock1!I51,Stock1!F51,"")} | Z51: {=_xlfn.XLOOKUP(X51,Stock1!I51,Stock1!J51,"")} | AA51: {=_xlfn.XLOOKUP(Y51,DATAPremium!A:A,DATAPremium!C:C,"")}
X52: {=_xlfn.XLOOKUP("Other",Stock1!A52,Stock1!I52,"")} | Y52: {=_xlfn.XLOOKUP(X52,Stock1!I52,Stock1!F52,"")} | Z52: {=_xlfn.XLOOKUP(X52,Stock1!I52,Stock1!J52,"")} | AA52: {=_xlfn.XLOOKUP(Y52,DATAPremium!A:A,DATAPremium!C:C,"")}
X53: {=_xlfn.XLOOKUP("Other",Stock1!A53,Stock1!I53,"")} | Y53: {=_xlfn.XLOOKUP(X53,Stock1!I53,Stock1!F53,"")} | Z53: {=_xlfn.XLOOKUP(X53,Stock1!I53,Stock1!J53,"")} | AA53: {=_xlfn.XLOOKUP(Y53,DATAPremium!A:A,DATAPremium!C:C,"")}
X54: {=_xlfn.XLOOKUP("Other",Stock1!A54,Stock1!I54,"")} | Y54: {=_xlfn.XLOOKUP(X54,Stock1!I54,Stock1!F54,"")} | Z54: {=_xlfn.XLOOKUP(X54,Stock1!I54,Stock1!J54,"")} | AA54: {=_xlfn.XLOOKUP(Y54,DATAPremium!A:A,DATAPremium!C:C,"")}
X55: {=_xlfn.XLOOKUP("Other",Stock1!A55,Stock1!I55,"")} | Y55: {=_xlfn.XLOOKUP(X55,Stock1!I55,Stock1!F55,"")} | Z55: {=_xlfn.XLOOKUP(X55,Stock1!I55,Stock1!J55,"")} | AA55: {=_xlfn.XLOOKUP(Y55,DATAPremium!A:A,DATAPremium!C:C,"")}
X56: {=_xlfn.XLOOKUP("Other",Stock1!A56,Stock1!I56,"")} | Y56: {=_xlfn.XLOOKUP(X56,Stock1!I56,Stock1!F56,"")} | Z56: {=_xlfn.XLOOKUP(X56,Stock1!I56,Stock1!J56,"")} | AA56: {=_xlfn.XLOOKUP(Y56,DATAPremium!A:A,DATAPremium!C:C,"")}
X57: {=_xlfn.XLOOKUP("Other",Stock1!A57,Stock1!I57,"")} | Y57: {=_xlfn.XLOOKUP(X57,Stock1!I57,Stock1!F57,"")} | Z57: {=_xlfn.XLOOKUP(X57,Stock1!I57,Stock1!J57,"")} | AA57: {=_xlfn.XLOOKUP(Y57,DATAPremium!A:A,DATAPremium!C:C,"")}
X58: {=_xlfn.XLOOKUP("Other",Stock1!A58,Stock1!I58,"")} | Y58: {=_xlfn.XLOOKUP(X58,Stock1!I58,Stock1!F58,"")} | Z58: {=_xlfn.XLOOKUP(X58,Stock1!I58,Stock1!J58,"")} | AA58: {=_xlfn.XLOOKUP(Y58,DATAPremium!A:A,DATAPremium!C:C,"")}
X59: {=_xlfn.XLOOKUP("Other",Stock1!A59,Stock1!I59,"")} | Y59: {=_xlfn.XLOOKUP(X59,Stock1!I59,Stock1!F59,"")} | Z59: {=_xlfn.XLOOKUP(X59,Stock1!I59,Stock1!J59,"")} | AA59: {=_xlfn.XLOOKUP(Y59,DATAPremium!A:A,DATAPremium!C:C,"")}
... X1000: {=_xlfn.XLOOKUP("Other",Stock1!A1000,Stock1!I1000,"")} | Y1000: {=_xlfn.XLOOKUP(X1000,Stock1!I1000,Stock1!F1000,"")} | Z1000: {=_xlfn.XLOOKUP(X1000,Stock1!I1000,Stock1!J1000,"")} | AA1000: {=_xlfn.XLOOKUP(Y1000,DATAPremium!A:A,DATAPremium!C:C,"")}

Sheet ชีต66

Sheet Incentive
A3: Brand | B3: Part Number | C3: Model | D3: SRP | E3: Sales Staff | F3: Stock ชั้น1 | G3: Stock ชั้น2 | H3: Incentive Details
A4: PAPERLIKE | B4: 4260470099102 | C4: PAPERLIKE 2-Pack Screen Protector for iPad Pro 12.9 [2018-2022] | D4: 1390 | E4: 30 | F4: =IFERROR(VLOOKUP(B4,Stock1!F:J,5,False),"") | G4: {=_xlfn.XLOOKUP(B4,Stock2!F:F,Stock2!J:J,"")} | H4: ให้ตั้งแต่ชิ้นแรก All Channel (1-31 Aug 2025)
A5: PAPERLIKE | B5: 4260470099126 | C5: PAPERLIKE 2-Pack Screen Protector for iPad 10.2 Gen7/8/9 | D5: 1390 | E5: 30 | F5: =IFERROR(VLOOKUP(B5,Stock1!F:J,5,False),"") | G5: {=_xlfn.XLOOKUP(B5,Stock2!F:F,Stock2!J:J,"")} | H5: ให้ตั้งแต่ชิ้นแรก All Channel (1-31 Aug 2025)
A6: PAPERLIKE | B6: 4260470099300 | C6: PAPERLIKE 2-Pack Screen Protector for iPad mini G6 | D6: 1390 | E6: 30 | F6: =IFERROR(VLOOKUP(B6,Stock1!F:J,5,False),"") | G6: {=_xlfn.XLOOKUP(B6,Stock2!F:F,Stock2!J:J,"")} | H6: ให้ตั้งแต่ชิ้นแรก All Channel (1-31 Aug 2025)
F7: =IFERROR(VLOOKUP(B7,Stock1!F:J,5,False),"") | G7: {=_xlfn.XLOOKUP(B7,Stock2!F:F,Stock2!J:J,"")} | H7: ให้ตั้งแต่ชิ้นแรก All Channel (1-31 July 2025)
A8: ZAGG | B8: 840056173507 | C8: ZAGG Bundle Set for iPhone 14 Pro | D8: 2670 | E8: 70 | F8: =IFERROR(VLOOKUP(B8,Stock1!F:J,5,False),"") | G8: {=_xlfn.XLOOKUP(B8,Stock2!F:F,Stock2!J:J,"")} | H8: ให้ตั้งแต่ชิ้นแรก All Channel (1-31 Aug 2025)
A9: ZAGG | B9: 840056173514 | C9: ZAGG Bundle Set for iPhone 14 Plus | D9: 2670 | E9: 70 | F9: =IFERROR(VLOOKUP(B9,Stock1!F:J,5,False),"") | G9: {=_xlfn.XLOOKUP(B9,Stock2!F:F,Stock2!J:J,"")} | H9: ให้ตั้งแต่ชิ้นแรก All Channel (1-31 Aug 2025)
A10: ZAGG | B10: 840056173521 | C10: ZAGG Bundle Set for iPhone 14 Pro Max | D10: 2670 | E10: 70 | F10: =IFERROR(VLOOKUP(B10,Stock1!F:J,5,False),"") | G10: {=_xlfn.XLOOKUP(B10,Stock2!F:F,Stock2!J:J,"")} | H10: ให้ตั้งแต่ชิ้นแรก All Channel (1-31 Aug 2025)
A11: ZAGG | B11: 840056198531 | C11: ZAGG Bundle Set for iPhone 15 | D11: 2670 | E11: 70 | F11: =IFERROR(VLOOKUP(B11,Stock1!F:J,5,False),"") | G11: {=_xlfn.XLOOKUP(B11,Stock2!F:F,Stock2!J:J,"")} | H11: ให้ตั้งแต่ชิ้นแรก All Channel (1-31 Aug 2025)
A12: ZAGG | B12: 840056198548 | C12: ZAGG Bundle Set for iPhone 15 Plus | D12: 2670 | E12: 70 | F12: =IFERROR(VLOOKUP(B12,Stock1!F:J,5,False),"") | G12: {=_xlfn.XLOOKUP(B12,Stock2!F:F,Stock2!J:J,"")} | H12: ให้ตั้งแต่ชิ้นแรก All Channel (1-31 Aug 2025)
A13: ZAGG | B13: 840056198555 | C13: ZAGG Bundle Set for iPhone 15 Pro | D13: 2670 | E13: 70 | F13: =IFERROR(VLOOKUP(B13,Stock1!F:J,5,False),"") | G13: {=_xlfn.XLOOKUP(B13,Stock2!F:F,Stock2!J:J,"")} | H13: ให้ตั้งแต่ชิ้นแรก All Channel (1-31 Aug 2025)
A14: ZAGG | B14: 840056198562 | C14: ZAGG Bundle Set for iPhone 15 Pro Max | D14: 2670 | E14: 70 | F14: =IFERROR(VLOOKUP(B14,Stock1!F:J,5,False),"") | G14: {=_xlfn.XLOOKUP(B14,Stock2!F:F,Stock2!J:J,"")} | H14: ให้ตั้งแต่ชิ้นแรก All Channel (1-31 Aug 2025)
F15: =IFERROR(VLOOKUP(B15,Stock1!F:J,5,False),"") | G15: {=_xlfn.XLOOKUP(B15,Stock2!F:F,Stock2!J:J,"")}
A16: ZAGG | B16: 840390300744 | C16: ZAGG Pro Keys [TH] for iPad Pro 11 [2018-2022] / Air 10.9 Gen4/5 - Black/Gray | D16: 4290 | E16: 70 | F16: =IFERROR(VLOOKUP(B16,Stock1!F:J,5,False),"") | G16: {=_xlfn.XLOOKUP(B16,Stock2!F:F,Stock2!J:J,"")} | H16: ให้ตั้งแต่ชิ้นแรก All Channel (1-31 Aug 2025)
F17: =IFERROR(VLOOKUP(B17,Stock1!F:J,5,False),"") | G17: {=_xlfn.XLOOKUP(B17,Stock2!F:F,Stock2!J:J,"")}
A18: SPIGEN | B18: 8800283301953 | C18: SPIGEN Nintendo Switch 2 Slim HD - Tray X | D18: 990 | E18: 50 | F18: =IFERROR(VLOOKUP(B18,Stock1!F:J,5,False),"") | G18: {=_xlfn.XLOOKUP(B18,Stock2!F:F,Stock2!J:J,"")} | H18: ให้ตั้งแต่ชิ้นแรก All Channel (1-31 Aug 2025)
F19: =IFERROR(VLOOKUP(B19,Stock1!F:J,5,False),"") | G19: {=_xlfn.XLOOKUP(B19,Stock2!F:F,Stock2!J:J,"")}
C20: เคสและฟิล์ม iPhone16 series | F20: =IFERROR(VLOOKUP(B20,Stock1!F:J,5,False),"") | G20: {=_xlfn.XLOOKUP(B20,Stock2!F:F,Stock2!J:J,"")}
A21: ZAGG | B21: 100616206 | C21: ZAGG Bundle Set for iPhone 16 | D21: 1990 | E21: 70 | F21: =IFERROR(VLOOKUP(B21,Stock1!F:J,5,False),"") | G21: {=_xlfn.XLOOKUP(B21,Stock2!F:F,Stock2!J:J,"")} | H21: ให้ตั้งแต่ชิ้นแรก All Channel (1-31 Aug 2025)
A22: ZAGG | B22: 100616207 | C22: ZAGG Bundle Set for iPhone 16 Plus | D22: 1990 | E22: 70 | F22: =IFERROR(VLOOKUP(B22,Stock1!F:J,5,False),"") | G22: {=_xlfn.XLOOKUP(B22,Stock2!F:F,Stock2!J:J,"")} | H22: ให้ตั้งแต่ชิ้นแรก All Channel (1-31 Aug 2025)
A23: ZAGG | B23: 100616208 | C23: ZAGG Bundle Set for iPhone 16 Pro | D23: 1990 | E23: 70 | F23: =IFERROR(VLOOKUP(B23,Stock1!F:J,5,False),"") | G23: {=_xlfn.XLOOKUP(B23,Stock2!F:F,Stock2!J:J,"")} | H23: ให้ตั้งแต่ชิ้นแรก All Channel (1-31 Aug 2025)
A24: ZAGG | B24: 100616209 | C24: ZAGG Bundle Set for iPhone 16 Pro Max | D24: 1990 | E24: 70 | F24: =IFERROR(VLOOKUP(B24,Stock1!F:J,5,False),"") | G24: {=_xlfn.XLOOKUP(B24,Stock2!F:F,Stock2!J:J,"")} | H24: ให้ตั้งแต่ชิ้นแรก All Channel (1-31 Aug 2025)
F25: =IFERROR(VLOOKUP(B25,Stock1!F:J,5,False),"") | G25: {=_xlfn.XLOOKUP(B25,Stock2!F:F,Stock2!J:J,"")}
A26: PANZERGLASS | B26: S31786 | C26: PANZERGLASS Bundle Set for iPhone 16 | D26: 2490 | E26: 70 | F26: =IFERROR(VLOOKUP(B26,Stock1!F:J,5,False),"") | G26: {=_xlfn.XLOOKUP(B26,Stock2!F:F,Stock2!J:J,"")} | H26: ให้ตั้งแต่ชิ้นแรก All Channel (1-31 Aug 2025)
A27: PANZERGLASS | B27: S31788 | C27: PANZERGLASS Bundle Set for iPhone 16 Plus | D27: 2490 | E27: 70 | F27: =IFERROR(VLOOKUP(B27,Stock1!F:J,5,False),"") | G27: {=_xlfn.XLOOKUP(B27,Stock2!F:F,Stock2!J:J,"")} | H27: ให้ตั้งแต่ชิ้นแรก All Channel (1-31 Aug 2025)
A28: PANZERGLASS | B28: S31787 | C28: PANZERGLASS Bundle Set for iPhone 16 Pro | D28: 2490 | E28: 70 | F28: =IFERROR(VLOOKUP(B28,Stock1!F:J,5,False),"") | G28: {=_xlfn.XLOOKUP(B28,Stock2!F:F,Stock2!J:J,"")} | H28: ให้ตั้งแต่ชิ้นแรก All Channel (1-31 Aug 2025)
A29: PANZERGLASS | B29: S31789 | C29: PANZERGLASS Bundle Set for iPhone 16 Pro Max | D29: 2490 | E29: 70 | F29: =IFERROR(VLOOKUP(B29,Stock1!F:J,5,False),"") | G29: {=_xlfn.XLOOKUP(B29,Stock2!F:F,Stock2!J:J,"")} | H29: ให้ตั้งแต่ชิ้นแรก All Channel (1-31 Aug 2025)
F30: =IFERROR(VLOOKUP(B30,Stock1!F:J,5,False),"") | G30: {=_xlfn.XLOOKUP(B30,Stock2!F:F,Stock2!J:J,"")}
A31: BODYGUARDZ | B31: 846237082385 | C31: BODYGUARDZ APEX for iPhone 16 Pro - Black Border | D31: 2790 | E31: 70 | F31: =IFERROR(VLOOKUP(B31,Stock1!F:J,5,False),"") | G31: {=_xlfn.XLOOKUP(B31,Stock2!F:F,Stock2!J:J,"")} | H31: ให้ตั้งแต่ชิ้นแรก All Channel (1-31 Aug 2025)
A32: BODYGUARDZ | B32: 846237082408 | C32: BODYGUARDZ APEX for iPhone 16 Pro Max - Black Border | D32: 2790 | E32: 70 | F32: =IFERROR(VLOOKUP(B32,Stock1!F:J,5,False),"") | G32: {=_xlfn.XLOOKUP(B32,Stock2!F:F,Stock2!J:J,"")} | H32: ให้ตั้งแต่ชิ้นแรก All Channel (1-31 Aug 2025)
F33: =IFERROR(VLOOKUP(B33,Stock1!F:J,5,False),"") | G33: {=_xlfn.XLOOKUP(B33,Stock2!F:F,Stock2!J:J,"")}
A34: PANZERGLASS | B34: 5715685002335 | C34: PANZERGLASS Ultra Wide Fit Matte Gaming for iPhone 16 | D34: 1590 | E34: 20 | F34: =IFERROR(VLOOKUP(B34,Stock1!F:J,5,False),"") | G34: {=_xlfn.XLOOKUP(B34,Stock2!F:F,Stock2!J:J,"")} | H34: ให้ตั้งแต่ชิ้นแรก All channel | 1-31 Aug 2025 (ไม่คู่เครื่อง)
A35: PANZERGLASS | B35: 5715685002373 | C35: PANZERGLASS Ultra Wide Fit for iPhone 16 | D35: 1490 | E35: 20 | F35: =IFERROR(VLOOKUP(B35,Stock1!F:J,5,False),"") | G35: {=_xlfn.XLOOKUP(B35,Stock2!F:F,Stock2!J:J,"")} | H35: ให้ตั้งแต่ชิ้นแรก All channel | 1-30 June 2025 (ไม่คู่เครื่อง)
A36: PANZERGLASS | B36: 5715685002458 | C36: PANZERGLASS Ultra Wide Fit Privacy for iPhone 16 | D36: 1590 | E36: 20 | F36: =IFERROR(VLOOKUP(B36,Stock1!F:J,5,False),"") | G36: {=_xlfn.XLOOKUP(B36,Stock2!F:F,Stock2!J:J,"")} | H36: ให้ตั้งแต่ชิ้นแรก All channel | 1-31 Aug 2025 (ไม่คู่เครื่อง)
A37: PANZERGLASS | B37: 5715685002359 | C37: PANZERGLASS Ultra Wide Fit Matte Gaming for iPhone 16 Plus | D37: 1590 | E37: 20 | F37: =IFERROR(VLOOKUP(B37,Stock1!F:J,5,False),"") | G37: {=_xlfn.XLOOKUP(B37,Stock2!F:F,Stock2!J:J,"")} | H37: ให้ตั้งแต่ชิ้นแรก All channel | 1-31 Aug 2025 (ไม่คู่เครื่อง)
A38: PANZERGLASS | B38: 5715685002397 | C38: PANZERGLASS Ultra Wide Fit for iPhone 16 Plus | D38: 1490 | E38: 20 | F38: =IFERROR(VLOOKUP(B38,Stock1!F:J,5,False),"") | G38: {=_xlfn.XLOOKUP(B38,Stock2!F:F,Stock2!J:J,"")} | H38: ให้ตั้งแต่ชิ้นแรก All channel | 1-31 Aug 2025 (ไม่คู่เครื่อง)
A39: PANZERGLASS | B39: 5715685002472 | C39: PANZERGLASS Ultra Wide Fit Privacy for iPhone 16 Plus | D39: 1590 | E39: 20 | F39: =IFERROR(VLOOKUP(B39,Stock1!F:J,5,False),"") | G39: {=_xlfn.XLOOKUP(B39,Stock2!F:F,Stock2!J:J,"")} | H39: ให้ตั้งแต่ชิ้นแรก All channel | 1-31 Aug 2025 (ไม่คู่เครื่อง)
A40: PANZERGLASS | B40: 5715685002304 | C40: PANZERGLASS Ultra Wide Fit Ceramic for iPhone 16 Pro | D40: 2590 | E40: 20 | F40: =IFERROR(VLOOKUP(B40,Stock1!F:J,5,False),"") | G40: {=_xlfn.XLOOKUP(B40,Stock2!F:F,Stock2!J:J,"")} | H40: ให้ตั้งแต่ชิ้นแรก All channel | 1-31 Aug 2025 (ไม่คู่เครื่อง)
A41: PANZERGLASS | B41: 5715685002342 | C41: PANZERGLASS Ultra Wide Fit Matte Gaming for iPhone 16 Pro | D41: 1590 | E41: 20 | F41: =IFERROR(VLOOKUP(B41,Stock1!F:J,5,False),"") | G41: {=_xlfn.XLOOKUP(B41,Stock2!F:F,Stock2!J:J,"")} | H41: ให้ตั้งแต่ชิ้นแรก All channel | 1-31 Aug 2025 (ไม่คู่เครื่อง)
A42: PANZERGLASS | B42: 5715685002380 | C42: PANZERGLASS Ultra Wide Fit for iPhone 16 Pro | D42: 1490 | E42: 20 | F42: =IFERROR(VLOOKUP(B42,Stock1!F:J,5,False),"") | G42: {=_xlfn.XLOOKUP(B42,Stock2!F:F,Stock2!J:J,"")} | H42: ให้ตั้งแต่ชิ้นแรก All channel | 1-31 Aug 2025 (ไม่คู่เครื่อง)
A43: PANZERGLASS | B43: 5715685002465 | C43: PANZERGLASS Ultra Wide Fit Privacy for iPhone 16 Pro | D43: 1590 | E43: 20 | F43: =IFERROR(VLOOKUP(B43,Stock1!F:J,5,False),"") | G43: {=_xlfn.XLOOKUP(B43,Stock2!F:F,Stock2!J:J,"")} | H43: ให้ตั้งแต่ชิ้นแรก All channel | 1-31 Aug 2025 (ไม่คู่เครื่อง)
A44: PANZERGLASS | B44: 5715685002328 | C44: PANZERGLASS Ultra Wide Fit Ceramic for iPhone 16 Pro Max | D44: 2590 | E44: 20 | F44: =IFERROR(VLOOKUP(B44,Stock1!F:J,5,False),"") | G44: {=_xlfn.XLOOKUP(B44,Stock2!F:F,Stock2!J:J,"")} | H44: ให้ตั้งแต่ชิ้นแรก All channel | 1-31 Aug 2025 (ไม่คู่เครื่อง)
A45: PANZERGLASS | B45: 5715685002366 | C45: PANZERGLASS Ultra Wide Fit Matte Gaming for iPhone 16 Pro Max | D45: 1590 | E45: 20 | F45: =IFERROR(VLOOKUP(B45,Stock1!F:J,5,False),"") | G45: {=_xlfn.XLOOKUP(B45,Stock2!F:F,Stock2!J:J,"")} | H45: ให้ตั้งแต่ชิ้นแรก All channel | 1-31 Aug 2025 (ไม่คู่เครื่อง)
... A52: PANZERGLASS | B52: 5711724028359 | C52: PANZERGLASS Glass for iPad Air 13 G6 /Pro 13 G7 | D52: 1590 | E52: 20 | F52: =IFERROR(VLOOKUP(B52,Stock1!F:J,5,False),"") | G52: {=_xlfn.XLOOKUP(B52,Stock2!F:F,Stock2!J:J,"")} | H52: ให้ตั้งแต่ชิ้นแรก All channel | 1-31 Aug 2025 (ไม่คู่เครื่อง)
F53: =IFERROR(VLOOKUP(B53,Stock1!F:J,5,False),"") | G53: {=_xlfn.XLOOKUP(B53,Stock2!F:F,Stock2!J:J,"")}
A54: PANZERGLASS | B54: 5715685002335 | C54: PANZERGLASS Ultra Wide Fit Matte Gaming for iPhone 16 | D54: 1590 | E54: 40 | F54: =IFERROR(VLOOKUP(B54,Stock1!F:J,5,False),"") | G54: {=_xlfn.XLOOKUP(B54,Stock2!F:F,Stock2!J:J,"")} | H54: ให้ตั้งแต่ชิ้นแรก All channel | 1-31 Aug 2025 ( ซื้อคู่เครื่อง)
A55: PANZERGLASS | B55: 5715685002373 | C55: PANZERGLASS Ultra Wide Fit for iPhone 16 | D55: 1490 | E55: 40 | F55: =IFERROR(VLOOKUP(B55,Stock1!F:J,5,False),"") | G55: {=_xlfn.XLOOKUP(B55,Stock2!F:F,Stock2!J:J,"")} | H55: ให้ตั้งแต่ชิ้นแรก All channel | 1-31 Aug 2025 ( ซื้อคู่เครื่อง)
A56: PANZERGLASS | B56: 5715685002458 | C56: PANZERGLASS Ultra Wide Fit Privacy for iPhone 16 | D56: 1590 | E56: 40 | F56: =IFERROR(VLOOKUP(B56,Stock1!F:J,5,False),"") | G56: {=_xlfn.XLOOKUP(B56,Stock2!F:F,Stock2!J:J,"")} | H56: ให้ตั้งแต่ชิ้นแรก All channel | 1-31 Aug 2025 ( ซื้อคู่เครื่อง)
A57: PANZERGLASS | B57: 5715685002359 | C57: PANZERGLASS Ultra Wide Fit Matte Gaming for iPhone 16 Plus | D57: 1590 | E57: 40 | F57: =IFERROR(VLOOKUP(B57,Stock1!F:J,5,False),"") | G57: {=_xlfn.XLOOKUP(B57,Stock2!F:F,Stock2!J:J,"")} | H57: ให้ตั้งแต่ชิ้นแรก All channel | 1-31 Aug 2025 ( ซื้อคู่เครื่อง)
A58: PANZERGLASS | B58: 5715685002397 | C58: PANZERGLASS Ultra Wide Fit for iPhone 16 Plus | D58: 1490 | E58: 40 | F58: =IFERROR(VLOOKUP(B58,Stock1!F:J,5,False),"") | G58: {=_xlfn.XLOOKUP(B58,Stock2!F:F,Stock2!J:J,"")} | H58: ให้ตั้งแต่ชิ้นแรก All channel | 1-31 Aug 2025 ( ซื้อคู่เครื่อง)
A59: PANZERGLASS | B59: 5715685002472 | C59: PANZERGLASS Ultra Wide Fit Privacy for iPhone 16 Plus | D59: 1590 | E59: 40 | F59: =IFERROR(VLOOKUP(B59,Stock1!F:J,5,False),"") | G59: {=_xlfn.XLOOKUP(B59,Stock2!F:F,Stock2!J:J,"")} | H59: ให้ตั้งแต่ชิ้นแรก All channel | 1-31 Aug 2025 ( ซื้อคู่เครื่อง)
A60: PANZERGLASS | B60: 5715685002304 | C60: PANZERGLASS Ultra Wide Fit Ceramic for iPhone 16 Pro | D60: 2590 | E60: 40 | F60: =IFERROR(VLOOKUP(B60,Stock1!F:J,5,False),"") | G60: {=_xlfn.XLOOKUP(B60,Stock2!F:F,Stock2!J:J,"")} | H60: ให้ตั้งแต่ชิ้นแรก All channel | 1-31 Aug 2025 ( ซื้อคู่เครื่อง)
A61: PANZERGLASS | B61: 5715685002342 | C61: PANZERGLASS Ultra Wide Fit Matte Gaming for iPhone 16 Pro | D61: 1590 | E61: 40 | F61: =IFERROR(VLOOKUP(B61,Stock1!F:J,5,False),"") | G61: {=_xlfn.XLOOKUP(B61,Stock2!F:F,Stock2!J:J,"")} | H61: ให้ตั้งแต่ชิ้นแรก All channel | 1-31 Aug 2025 ( ซื้อคู่เครื่อง)
A62: PANZERGLASS | B62: 5715685002380 | C62: PANZERGLASS Ultra Wide Fit for iPhone 16 Pro | D62: 1490 | E62: 40 | F62: =IFERROR(VLOOKUP(B62,Stock1!F:J,5,False),"") | G62: {=_xlfn.XLOOKUP(B62,Stock2!F:F,Stock2!J:J,"")} | H62: ให้ตั้งแต่ชิ้นแรก All channel | 1-31 Aug 2025 ( ซื้อคู่เครื่อง)
A63: PANZERGLASS | B63: 5715685002465 | C63: PANZERGLASS Ultra Wide Fit Privacy for iPhone 16 Pro | D63: 1590 | E63: 40 | F63: =IFERROR(VLOOKUP(B63,Stock1!F:J,5,False),"") | G63: {=_xlfn.XLOOKUP(B63,Stock2!F:F,Stock2!J:J,"")} | H63: ให้ตั้งแต่ชิ้นแรก All channel | 1-31 Aug 2025 ( ซื้อคู่เครื่อง)
A64: PANZERGLASS | B64: 5715685002328 | C64: PANZERGLASS Ultra Wide Fit Ceramic for iPhone 16 Pro Max | D64: 2590 | E64: 40 | F64: =IFERROR(VLOOKUP(B64,Stock1!F:J,5,False),"") | G64: {=_xlfn.XLOOKUP(B64,Stock2!F:F,Stock2!J:J,"")} | H64: ให้ตั้งแต่ชิ้นแรก All channel | 1-31 Aug 2025 ( ซื้อคู่เครื่อง)
A65: PANZERGLASS | B65: 5715685002366 | C65: PANZERGLASS Ultra Wide Fit Matte Gaming for iPhone 16 Pro Max | D65: 1590 | E65: 40 | F65: =IFERROR(VLOOKUP(B65,Stock1!F:J,5,False),"") | G65: {=_xlfn.XLOOKUP(B65,Stock2!F:F,Stock2!J:J,"")} | H65: ให้ตั้งแต่ชิ้นแรก All channel | 1-31 Aug 2025 ( ซื้อคู่เครื่อง)
... A72: PANZERGLASS | B72: 5711724028359 | C72: PANZERGLASS Glass for iPad Air 13 G6 /Pro 13 G7 | D72: 1590 | E72: 40 | F72: =IFERROR(VLOOKUP(B72,Stock1!F:J,5,False),"") | G72: {=_xlfn.XLOOKUP(B72,Stock2!F:F,Stock2!J:J,"")} | H72: ให้ตั้งแต่ชิ้นแรก All channel | 1-31 Aug 2025 ( ซื้อคู่เครื่อง)
C73: ฟิล์ม Samsung S25, S25+, S25 Ultra | F73: =IFERROR(VLOOKUP(B73,Stock1!F:J,5,False),"") | G73: {=_xlfn.XLOOKUP(B73,Stock2!F:F,Stock2!J:J,"")}
A74: SAFE | B74: 5715685017605 | C74: SAFE Ultra Wide Fit for Samsung S25 Plus | D74: 490 | E74: 20 | F74: =IFERROR(VLOOKUP(B74,Stock1!F:J,5,False),"") | G74: {=_xlfn.XLOOKUP(B74,Stock2!F:F,Stock2!J:J,"")} | H74: ให้ตั้งแต่ชิ้นแรก All Channel (1-31 Aug 2025)
A75: SAFE | B75: 5715685017636 | C75: SAFE Ultra Wide Fit for Samsung S25 | D75: 490 | E75: 20 | F75: =IFERROR(VLOOKUP(B75,Stock1!F:J,5,False),"") | G75: {=_xlfn.XLOOKUP(B75,Stock2!F:F,Stock2!J:J,"")} | H75: ให้ตั้งแต่ชิ้นแรก All Channel (1-31 Aug 2025)
A76: SAFE | B76: 5715685017643 | C76: SAFE Ultra Wide Fit for Samsung S25 Ultra | D76: 490 | E76: 20 | F76: =IFERROR(VLOOKUP(B76,Stock1!F:J,5,False),"") | G76: {=_xlfn.XLOOKUP(B76,Stock2!F:F,Stock2!J:J,"")} | H76: ให้ตั้งแต่ชิ้นแรก All Channel (1-31 Aug 2025)
A77: SAFE | B77: 5715685017643 | C77: SAFE Ultra Wide Fit Privacy for Samsung S25 Ultra | D77: 490 | E77: 20 | F77: =IFERROR(VLOOKUP(B77,Stock1!F:J,5,False),"") | G77: {=_xlfn.XLOOKUP(B77,Stock2!F:F,Stock2!J:J,"")} | H77: ให้ตั้งแต่ชิ้นแรก All Channel (1-31 Aug 2025)
A78: SAFE | B78: 5715685017766 | C78: SAFE Camera Lens Protector for Samsung S25 Ultra | D78: 490 | E78: 20 | F78: =IFERROR(VLOOKUP(B78,Stock1!F:J,5,False),"") | G78: {=_xlfn.XLOOKUP(B78,Stock2!F:F,Stock2!J:J,"")} | H78: ให้ตั้งแต่ชิ้นแรก All Channel (1-31 Aug 2025)
C79: ฟิล์ม Samsung Galaxy Flip/Fold 7 | F79: =IFERROR(VLOOKUP(B79,Stock1!F:J,5,False),"") | G79: {=_xlfn.XLOOKUP(B79,Stock2!F:F,Stock2!J:J,"")}
A80: PANZERGLASS | B80: 5715685026492 | C80: PANZERGLASS Ultra Wide Fit for Samsung Galaxy Z Fold 7 | D80: 990 | E80: 70 | F80: =IFERROR(VLOOKUP(B80,Stock1!F:J,5,False),"") | G80: {=_xlfn.XLOOKUP(B80,Stock2!F:F,Stock2!J:J,"")} | H80: ให้ตั้งแต่ชิ้นแรก All Channel (1-31 Aug 2025)
A81: PANZERGLASS | B81: 5715685026478 | C81: PANZERGLASS Ultra Wide Fit for Samsung Galaxy Z Flip 7 | D81: 990 | E81: 70 | F81: =IFERROR(VLOOKUP(B81,Stock1!F:J,5,False),"") | G81: {=_xlfn.XLOOKUP(B81,Stock2!F:F,Stock2!J:J,"")} | H81: ให้ตั้งแต่ชิ้นแรก All Channel (1-31 Aug 2025)
F82: =IFERROR(VLOOKUP(B82,Stock1!F:J,5,False),"") | G82: {=_xlfn.XLOOKUP(B82,Stock2!F:F,Stock2!J:J,"")}
C83: Lens iPhone 16 | F83: =IFERROR(VLOOKUP(B83,Stock1!F:J,5,False),"") | G83: {=_xlfn.XLOOKUP(B83,Stock2!F:F,Stock2!J:J,"")}
A84: Ablemen | B84: 8859703428381 | C84: Ablemen Lens Full Glass Apple iPhone 16/16 Plus | E84: 10 | F84: =IFERROR(VLOOKUP(B84,Stock1!F:J,5,False),"") | G84: {=_xlfn.XLOOKUP(B84,Stock2!F:F,Stock2!J:J,"")} | H84: ให้ตั้งแต่ชิ้นแรก All Channel (1-31 Aug 2025)
A85: Ablemen | B85: 8859703428398 | C85: Ablemen Lens Full Glass Apple iPhone 16 Pro/16 Pro Max | E85: 10 | F85: =IFERROR(VLOOKUP(B85,Stock1!F:J,5,False),"") | G85: {=_xlfn.XLOOKUP(B85,Stock2!F:F,Stock2!J:J,"")} | H85: ให้ตั้งแต่ชิ้นแรก All Channel (1-31 Aug 2025)
C86: Film iPhone 16 | F86: =IFERROR(VLOOKUP(B86,Stock1!F:J,5,False),"") | G86: {=_xlfn.XLOOKUP(B86,Stock2!F:F,Stock2!J:J,"")}
A87: Ablemen | B87: 8859703427896 | C87: Ablemen FF 2X PV Apple iPhone 16 | E87: 50 | F87: =IFERROR(VLOOKUP(B87,Stock1!F:J,5,False),"") | G87: {=_xlfn.XLOOKUP(B87,Stock2!F:F,Stock2!J:J,"")} | H87: ให้ตั้งแต่ชิ้นแรก All Channel (1-31 Aug 2025)
A88: Ablemen | B88: 8859703427919 | C88: Ablemen FF 2X PV Apple iPhone 16 Pro | E88: 50 | F88: =IFERROR(VLOOKUP(B88,Stock1!F:J,5,False),"") | G88: {=_xlfn.XLOOKUP(B88,Stock2!F:F,Stock2!J:J,"")} | H88: ให้ตั้งแต่ชิ้นแรก All Channel (1-31 Aug 2025)
A89: Ablemen | B89: 8859703427926 | C89: Ablemen FF 2X PV Apple iPhone 16 Pro Max | E89: 50 | F89: =IFERROR(VLOOKUP(B89,Stock1!F:J,5,False),"") | G89: {=_xlfn.XLOOKUP(B89,Stock2!F:F,Stock2!J:J,"")} | H89: ให้ตั้งแต่ชิ้นแรก All Channel (1-31 Aug 2025)
A90: Ablemen | B90: 8859703427933 | C90: Ablemen FF 2X MT Apple iPhone 16 | E90: 50 | F90: =IFERROR(VLOOKUP(B90,Stock1!F:J,5,False),"") | G90: {=_xlfn.XLOOKUP(B90,Stock2!F:F,Stock2!J:J,"")} | H90: ให้ตั้งแต่ชิ้นแรก All Channel (1-31 Aug 2025)
A91: Ablemen | B91: 8859703427957 | C91: Ablemen FF 2X MT Apple iPhone 16 Pro | E91: 50 | F91: =IFERROR(VLOOKUP(B91,Stock1!F:J,5,False),"") | G91: {=_xlfn.XLOOKUP(B91,Stock2!F:F,Stock2!J:J,"")} | H91: ให้ตั้งแต่ชิ้นแรก All Channel (1-31 Aug 2025)
A92: Ablemen | B92: 8859703427964 | C92: Ablemen FF 2X MT Apple iPhone 16 Pro Max | E92: 50 | F92: =IFERROR(VLOOKUP(B92,Stock1!F:J,5,False),"") | G92: {=_xlfn.XLOOKUP(B92,Stock2!F:F,Stock2!J:J,"")} | H92: ให้ตั้งแต่ชิ้นแรก All Channel (1-31 Aug 2025)
A93: Ablemen | B93: 8859703427971 | C93: Ablemen FF 2X BLC Apple iPhone 16 | E93: 50 | F93: =IFERROR(VLOOKUP(B93,Stock1!F:J,5,False),"") | G93: {=_xlfn.XLOOKUP(B93,Stock2!F:F,Stock2!J:J,"")} | H93: ให้ตั้งแต่ชิ้นแรก All Channel (1-31 Aug 2025)
A94: Ablemen | B94: 8859703427995 | C94: Ablemen FF 2X BLC Apple iPhone 16 Pro | E94: 50 | F94: =IFERROR(VLOOKUP(B94,Stock1!F:J,5,False),"") | G94: {=_xlfn.XLOOKUP(B94,Stock2!F:F,Stock2!J:J,"")} | H94: ให้ตั้งแต่ชิ้นแรก All Channel (1-31 Aug 2025)
A95: Ablemen | B95: 8859703428008 | C95: Ablemen FF 2X BLC Apple iPhone 16 Pro Max | E95: 50 | F95: =IFERROR(VLOOKUP(B95,Stock1!F:J,5,False),"") | G95: {=_xlfn.XLOOKUP(B95,Stock2!F:F,Stock2!J:J,"")} | H95: ให้ตั้งแต่ชิ้นแรก All Channel (1-31 Aug 2025)
C96: Film Samsung S25 | F96: =IFERROR(VLOOKUP(B96,Stock1!F:J,5,False),"") | G96: {=_xlfn.XLOOKUP(B96,Stock2!F:F,Stock2!J:J,"")}
A97: Ablemen | B97: 8859703428466 | C97: Ablemen FF 2X SL PV Samsung Galaxy S25 Ultra | E97: 60 | F97: =IFERROR(VLOOKUP(B97,Stock1!F:J,5,False),"") | G97: {=_xlfn.XLOOKUP(B97,Stock2!F:F,Stock2!J:J,"")} | H97: ให้ตั้งแต่ชิ้นแรก All Channel (1-31 Aug 2025)
A98: Ablemen | B98: 8859703428473 | C98: Ablemen FF 2X SL MT Samsung Galaxy S25 Ultra | E98: 60 | F98: =IFERROR(VLOOKUP(B98,Stock1!F:J,5,False),"") | G98: {=_xlfn.XLOOKUP(B98,Stock2!F:F,Stock2!J:J,"")} | H98: ให้ตั้งแต่ชิ้นแรก All Channel (1-31 Aug 2025)
A99: Ablemen | B99: 8859703428497 | C99: Ablemen FF 5XC SL BLC Samsung Galaxy S25 Ultra | E99: 60 | F99: =IFERROR(VLOOKUP(B99,Stock1!F:J,5,False),"") | G99: {=_xlfn.XLOOKUP(B99,Stock2!F:F,Stock2!J:J,"")} | H99: ให้ตั้งแต่ชิ้นแรก All Channel (1-31 Aug 2025)
C100: Box Set Samsung | F100: =IFERROR(VLOOKUP(B100,Stock1!F:J,5,False),"") | G100: {=_xlfn.XLOOKUP(B100,Stock2!F:F,Stock2!J:J,"")}
A101: Focus | B101: 8859703426301 | C101: Focus Premium Gift Set Samsung Galaxy S24 Ultra (FF-SL) for Trade | E101: 200 | F101: =IFERROR(VLOOKUP(B101,Stock1!F:J,5,False),"") | G101: {=_xlfn.XLOOKUP(B101,Stock2!F:F,Stock2!J:J,"")} | H101: ให้ตั้งแต่ชิ้นแรก All Channel (1-31 Aug 2025)
A102: Focus | B102: 8859703433729 | C102: Focus Premium Gift Set Samsung Galaxy S25 Ultra (UG-FF-SL) Pro Magsafe for Trade | E102: 200 | F102: =IFERROR(VLOOKUP(B102,Stock1!F:J,5,False),"") | G102: {=_xlfn.XLOOKUP(B102,Stock2!F:F,Stock2!J:J,"")} | H102: ให้ตั้งแต่ชิ้นแรก All Channel (1-31 Aug 2025)
A103: Focus | B103: 8859703431336 | C103: Focus Premium Gift Set Samsung Galaxy Z Flip 6 (TG-UC) | E103: 150 | F103: =IFERROR(VLOOKUP(B103,Stock1!F:J,5,False),"") | G103: {=_xlfn.XLOOKUP(B103,Stock2!F:F,Stock2!J:J,"")} | H103: ให้ตั้งแต่ชิ้นแรก All Channel (1-31 Aug 2025)
A104: Focus | B104: 8859703431367 | C104: Focus Premium Gift Set Samsung Galaxy Z Fold 6 (TG-UC) | E104: 150 | F104: =IFERROR(VLOOKUP(B104,Stock1!F:J,5,False),"") | G104: {=_xlfn.XLOOKUP(B104,Stock2!F:F,Stock2!J:J,"")} | H104: ให้ตั้งแต่ชิ้นแรก All Channel (1-31 Aug 2025)
C105: Hydro Film | F105: =IFERROR(VLOOKUP(B105,Stock1!F:J,5,False),"") | G105: {=_xlfn.XLOOKUP(B105,Stock2!F:F,Stock2!J:J,"")}
A106: Focus | B106: 8859095890766 | C106: Focus Hydroplus Film Ultra Clear | E106: 60 | F106: =IFERROR(VLOOKUP(B106,Stock1!F:J,5,False),"") | G106: {=_xlfn.XLOOKUP(B106,Stock2!F:F,Stock2!J:J,"")} -> 19 | H106: ให้ตั้งแต่ชิ้นแรก All Channel (1-31 Aug 2025)
A107: Focus | B107: 8859095890773 | C107: Focus Hydroplus Film Antifinger Print | E107: 60 | F107: =IFERROR(VLOOKUP(B107,Stock1!F:J,5,False),"") | G107: {=_xlfn.XLOOKUP(B107,Stock2!F:F,Stock2!J:J,"")} -> 4 | H107: ให้ตั้งแต่ชิ้นแรก All Channel (1-31 Aug 2025)
A108: Focus | B108: 8859703400875 | C108: Focus Hydroplus Film Tablet Ultra Clear | E108: 60 | F108: =IFERROR(VLOOKUP(B108,Stock1!F:J,5,False),"") | G108: {=_xlfn.XLOOKUP(B108,Stock2!F:F,Stock2!J:J,"")} | H108: ให้ตั้งแต่ชิ้นแรก All Channel (1-31 Aug 2025)
A109: Focus | B109: 8859703408253 | C109: Focus Hydroplus Film Privacy Matte | E109: 60 | F109: =IFERROR(VLOOKUP(B109,Stock1!F:J,5,False),"") | G109: {=_xlfn.XLOOKUP(B109,Stock2!F:F,Stock2!J:J,"")} | H109: ให้ตั้งแต่ชิ้นแรก All Channel (1-31 Aug 2025)
C110: Lens and film | F110: =IFERROR(VLOOKUP(B110,Stock1!F:J,5,False),"") | G110: {=_xlfn.XLOOKUP(B110,Stock2!F:F,Stock2!J:J,"")}
A111: Focus | B111: 8859703426387 | C111: Focus Perfect Clear Ring Samsung Galaxy S24 Ultra | E111: 50 | F111: =IFERROR(VLOOKUP(B111,Stock1!F:J,5,False),"") | G111: {=_xlfn.XLOOKUP(B111,Stock2!F:F,Stock2!J:J,"")} | H111: ให้ตั้งแต่ชิ้นแรก All Channel (1-31 Aug 2025)
A112: Focus | B112: 8859703426431 | C112: Focus Iron Ring Samsung Galaxy S24 Ultra Black | E112: 50 | F112: =IFERROR(VLOOKUP(B112,Stock1!F:J,5,False),"") | G112: {=_xlfn.XLOOKUP(B112,Stock2!F:F,Stock2!J:J,"")} | H112: ให้ตั้งแต่ชิ้นแรก All Channel (1-31 Aug 2025)
A113: Focus | B113: 8859703426516 | C113: Focus TG FF SL Samsung Galaxy S24 Black | E113: 50 | F113: =IFERROR(VLOOKUP(B113,Stock1!F:J,5,False),"") | G113: {=_xlfn.XLOOKUP(B113,Stock2!F:F,Stock2!J:J,"")} | H113: ให้ตั้งแต่ชิ้นแรก All Channel (1-31 Aug 2025)
A114: Focus | B114: 8859703426523 | C114: Focus TG FF SL Samsung Galaxy S24 Plus Black | E114: 50 | F114: =IFERROR(VLOOKUP(B114,Stock1!F:J,5,False),"") | G114: {=_xlfn.XLOOKUP(B114,Stock2!F:F,Stock2!J:J,"")} | H114: ให้ตั้งแต่ชิ้นแรก All Channel (1-31 Aug 2025)
...

Sheet DATAPremium
A4: P/N | B4: Description | C4: Premium
A5: 2064925400008 | B5: [PM] Umbrella UV Mini Youmi Black | C5: Smartphone 10,000 up
A6: 4897121000134 | B6: [PM] Stand Tablet 360 Rotation | C6: Tablet
A7: 8859289659292 | B7: [PM] Multifunction Metal Holder desktop PH-02 Dpower | C7: Smartphone
A8: 8859289665477 | B8: Premium SAMSUNG TC-04 (Type-C) | C8: Smartphone
A9: 8859289682399 | B9: Premium D-Power Phone Holder PH-03 | C9: Smartphone
A10: 8859289650411 | B10: Premium Bluetooth Speaker PARCO | C10: Smartphone
A11: 8859289657762 | B11: Premium D-Power M22 Speaker Bluetooth | C11: Smartphone 10,000 up
A12: 8859289682863 | B12: [PM] Bluetooth speaker Z2 Dpower | C12: Tablet
A13: PREMIUM0017044 | B13: [PM] Blackpack Fashion Phoenix | C13: Tablet
A14: PREMIUM0017045 | B14: [PM] Blackpack Colorful Phoenix | C14: Tablet
A15: PREMIUM-2025112 | B15: [PM] Wireless Speaker EP Poppy | C15: Tablet
... A81: PM6936678491526 | B81: Premium Robot Portable handheld fan RT-HF01 - White | C81: Smartphone 5,000 up

Sheet Adapter&สาย&Flim
A1: Marketing Name | B1: Model Code | C1: RRP In.vat | D1: Stock ชั้น1 | E1: Stock ชั้น2 | H1: Marketing Name | I1: Model Code | J1: RRP In.vat | K1: Incentive | L1: Stock ชั้น1 | M1: Stock ชั้น2 | P1: Marketing Name | Q1: Model Code | R1: RRP In.vat | S1: Stock ชั้น1 | T1: Stock ชั้น2 | V1: {=_xlfn.XLOOKUP("Charger",Stock1!B1,Stock1!I1,"")} | W1: {=_xlfn.XLOOKUP(V1,Stock1!I1,Stock1!F1,"")} | X1: {=_xlfn.XLOOKUP(V1,Stock1!I1,Stock1!J1,"")} | Y1: {=_xlfn.XLOOKUP("Screen Protector for Android Phone and Other",Stock1!B1,Stock1!I1,"")} | Z1: {=_xlfn.XLOOKUP("Screen Protector for Galaxy Phone",Stock1!B1,Stock1!I1,"")} | AA1: {=_xlfn.XLOOKUP("Screen Protector for Galaxy Tab",Stock1!B1,Stock1!I1,"")} | AB1: =TEXTJOIN(,,Y1,Z1,AA1) | AC1: {=_xlfn.XLOOKUP(AB1,Stock1!I1,Stock1!F1,"")} | AD1: {=_xlfn.XLOOKUP(AB1,Stock1!I1,Stock1!J1,"")} | AE1: {=_xlfn.XLOOKUP("Storage",Stock1!B1,Stock1!I1,"")} | AF1: {=_xlfn.XLOOKUP(AE1,Stock1!I1,Stock1!F1,"")} | AG1: {=_xlfn.XLOOKUP(AE1,Stock1!I1,Stock1!J1,"")}
A2: =UNIQUE(V:V) | B2: =UNIQUE(W:W) | D2: =IFERROR(VLOOKUP(B2,Stock1!F:J,5,False),"") | E2: =IFERROR(VLOOKUP(B2,Stock2!F:J,5,False),"") | H2: =UNIQUE(AB:AB) | I2: =UNIQUE(AC:AC) | L2: =IFERROR(VLOOKUP(I2,Stock1!F:J,5,False),"") | M2: =IFERROR(VLOOKUP(I2,Stock2!F:J,5,False),"") | P2: =UNIQUE(AE:AE) | Q2: =UNIQUE(AF:AF) | S2: =IFERROR(VLOOKUP(Q2,Stock1!F:J,5,False),"") | T2: =IFERROR(VLOOKUP(Q2,Stock2!F:J,5,False),"") | V2: {=_xlfn.XLOOKUP("Charger",Stock1!B2,Stock1!I2,"")} | W2: {=_xlfn.XLOOKUP(V2,Stock1!I2,Stock1!F2,"")} | X2: {=_xlfn.XLOOKUP(V2,Stock1!I2,Stock1!J2,"")} | Y2: {=_xlfn.XLOOKUP("Screen Protector for Android Phone and Other",Stock1!B2,Stock1!I2,"")} | Z2: {=_xlfn.XLOOKUP("Screen Protector for Galaxy Phone",Stock1!B2,Stock1!I2,"")} | AA2: {=_xlfn.XLOOKUP("Screen Protector for Galaxy Tab",Stock1!B2,Stock1!I2,"")} | AB2: =TEXTJOIN(,,Y2,Z2,AA2) | AC2: {=_xlfn.XLOOKUP(AB2,Stock1!I2,Stock1!F2,"")} | AD2: {=_xlfn.XLOOKUP(AB2,Stock1!I2,Stock1!J2,"")} | AE2: {=_xlfn.XLOOKUP("Storage",Stock1!B2,Stock1!I2,"")} | AF2: {=_xlfn.XLOOKUP(AE2,Stock1!I2,Stock1!F2,"")} | AG2: {=_xlfn.XLOOKUP(AE2,Stock1!I2,Stock1!J2,"")}
A3: [CS]UGREEN UNO RG 65W USB A*1 + USB C*2 GaN Fast Charger THAI PLUG - Gray | B3: 6941876238958 | C3: {=IFERROR(_xlfn.XLOOKUP(B3,Stock1!F:F,Stock1!E:E,""),"")} -> 999 | D3: =IFERROR(VLOOKUP(B3,Stock1!F:J,5,False),"") -> 8 | E3: =IFERROR(VLOOKUP(B3,Stock2!F:J,5,False),"") -> 2 | H3: [CS]Focus TG FF Samsung Galaxy A07 Black | I3: 8859703436409 | J3: {=IFERROR(_xlfn.XLOOKUP(I3,Stock1!F:F,Stock1!E:E,""),"")} -> 249 | K3: {=IFERROR(_xlfn.XLOOKUP(I3,Incentive!B:B,Incentive!E:E,""),"")} | L3: =IFERROR(VLOOKUP(I3,Stock1!F:J,5,False),"") -> 10 | M3: =IFERROR(VLOOKUP(I3,Stock2!F:J,5,False),"") -> 10 | P3: #REF! | Q3: #REF! | R3: {=IFERROR(_xlfn.XLOOKUP(Q3,Stock1!F:F,Stock1!E:E,""),"")} | S3: =IFERROR(VLOOKUP(Q3,Stock1!F:J,5,False),"") | T3: =IFERROR(VLOOKUP(Q3,Stock2!F:J,5,False),"") | V3: {=_xlfn.XLOOKUP("Charger",Stock1!B3,Stock1!I3,"")} | W3: {=_xlfn.XLOOKUP(V3,Stock1!I3,Stock1!F3,"")} | X3: {=_xlfn.XLOOKUP(V3,Stock1!I3,Stock1!J3,"")} | Y3: {=_xlfn.XLOOKUP("Screen Protector for Android Phone and Other",Stock1!B3,Stock1!I3,"")} | Z3: {=_xlfn.XLOOKUP("Screen Protector for Galaxy Phone",Stock1!B3,Stock1!I3,"")} | AA3: {=_xlfn.XLOOKUP("Screen Protector for Galaxy Tab",Stock1!B3,Stock1!I3,"")} | AB3: =TEXTJOIN(,,Y3,Z3,AA3) | AC3: {=_xlfn.XLOOKUP(AB3,Stock1!I3,Stock1!F3,"")} | AD3: {=_xlfn.XLOOKUP(AB3,Stock1!I3,Stock1!J3,"")} | AE3: {=_xlfn.XLOOKUP("Storage",Stock1!B3,Stock1!I3,"")} | AF3: {=_xlfn.XLOOKUP(AE3,Stock1!I3,Stock1!F3,"")} | AG3: {=_xlfn.XLOOKUP(AE3,Stock1!I3,Stock1!J3,"")}
A4: [CS]UGREEN Wall Charer 30W USB Port*1 + PD*2 Fast Charger Thai plug - Grey | B4: 6941876265732 | C4: {=IFERROR(_xlfn.XLOOKUP(B4,Stock1!F:F,Stock1!E:E,""),"")} -> 399 | D4: =IFERROR(VLOOKUP(B4,Stock1!F:J,5,False),"") -> 48 | E4: =IFERROR(VLOOKUP(B4,Stock2!F:J,5,False),"") -> 9 | H4: [CS]HISHIELD TemperedGlass FC 2.5D Samsung A07 | I4: 8859216804023 | J4: {=IFERROR(_xlfn.XLOOKUP(I4,Stock1!F:F,Stock1!E:E,""),"")} -> 299 | K4: {=IFERROR(_xlfn.XLOOKUP(I4,Incentive!B:B,Incentive!E:E,""),"")} | L4: =IFERROR(VLOOKUP(I4,Stock1!F:J,5,False),"") -> 7 | M4: =IFERROR(VLOOKUP(I4,Stock2!F:J,5,False),"") -> 15 | R4: {=IFERROR(_xlfn.XLOOKUP(Q4,Stock1!F:F,Stock1!E:E,""),"")} | S4: =IFERROR(VLOOKUP(Q4,Stock1!F:J,5,False),"") | T4: =IFERROR(VLOOKUP(Q4,Stock2!F:J,5,False),"") | V4: {=_xlfn.XLOOKUP("Charger",Stock1!B4,Stock1!I4,"")} | W4: {=_xlfn.XLOOKUP(V4,Stock1!I4,Stock1!F4,"")} | X4: {=_xlfn.XLOOKUP(V4,Stock1!I4,Stock1!J4,"")} | Y4: {=_xlfn.XLOOKUP("Screen Protector for Android Phone and Other",Stock1!B4,Stock1!I4,"")} | Z4: {=_xlfn.XLOOKUP("Screen Protector for Galaxy Phone",Stock1!B4,Stock1!I4,"")} | AA4: {=_xlfn.XLOOKUP("Screen Protector for Galaxy Tab",Stock1!B4,Stock1!I4,"")} | AB4: =TEXTJOIN(,,Y4,Z4,AA4) | AC4: {=_xlfn.XLOOKUP(AB4,Stock1!I4,Stock1!F4,"")} | AD4: {=_xlfn.XLOOKUP(AB4,Stock1!I4,Stock1!J4,"")} | AE4: {=_xlfn.XLOOKUP("Storage",Stock1!B4,Stock1!I4,"")} | AF4: {=_xlfn.XLOOKUP(AE4,Stock1!I4,Stock1!F4,"")} | AG4: {=_xlfn.XLOOKUP(AE4,Stock1!I4,Stock1!J4,"")}
A5: [CS]UGREEN Wall Charger 45W USB Port*1 + PD*2 Fast Charger Thai plug - Grey | B5: 6941876265749 | C5: {=IFERROR(_xlfn.XLOOKUP(B5,Stock1!F:F,Stock1!E:E,""),"")} -> 599 | D5: =IFERROR(VLOOKUP(B5,Stock1!F:J,5,False),"") -> 9 | E5: =IFERROR(VLOOKUP(B5,Stock2!F:J,5,False),"") -> 10 | H5: [CS]HISHIELD TemperedGlass FC 2.5D Samsung A17 | I5: 8859216803910 | J5: {=IFERROR(_xlfn.XLOOKUP(I5,Stock1!F:F,Stock1!E:E,""),"")} -> 299 | K5: {=IFERROR(_xlfn.XLOOKUP(I5,Incentive!B:B,Incentive!E:E,""),"")} | L5: =IFERROR(VLOOKUP(I5,Stock1!F:J,5,False),"") -> 17 | M5: =IFERROR(VLOOKUP(I5,Stock2!F:J,5,False),"") -> 33 | R5: {=IFERROR(_xlfn.XLOOKUP(Q5,Stock1!F:F,Stock1!E:E,""),"")} | S5: =IFERROR(VLOOKUP(Q5,Stock1!F:J,5,False),"") | T5: =IFERROR(VLOOKUP(Q5,Stock2!F:J,5,False),"") | V5: {=_xlfn.XLOOKUP("Charger",Stock1!B5,Stock1!I5,"")} | W5: {=_xlfn.XLOOKUP(V5,Stock1!I5,Stock1!F5,"")} | X5: {=_xlfn.XLOOKUP(V5,Stock1!I5,Stock1!J5,"")} | Y5: {=_xlfn.XLOOKUP("Screen Protector for Android Phone and Other",Stock1!B5,Stock1!I5,"")} | Z5: {=_xlfn.XLOOKUP("Screen Protector for Galaxy Phone",Stock1!B5,Stock1!I5,"")} | AA5: {=_xlfn.XLOOKUP("Screen Protector for Galaxy Tab",Stock1!B5,Stock1!I5,"")} | AB5: =TEXTJOIN(,,Y5,Z5,AA5) | AC5: {=_xlfn.XLOOKUP(AB5,Stock1!I5,Stock1!F5,"")} | AD5: {=_xlfn.XLOOKUP(AB5,Stock1!I5,Stock1!J5,"")} | AE5: {=_xlfn.XLOOKUP("Storage",Stock1!B5,Stock1!I5,"")} | AF5: {=_xlfn.XLOOKUP(AE5,Stock1!I5,Stock1!F5,"")} | AG5: {=_xlfn.XLOOKUP(AE5,Stock1!I5,Stock1!J5,"")}
A6: Samsung Adapter 25W No Cable-Black | B6: EP-T2510NBEGTH | C6: {=IFERROR(_xlfn.XLOOKUP(B6,Stock1!F:F,Stock1!E:E,""),"")} -> 690 | D6: =IFERROR(VLOOKUP(B6,Stock1!F:J,5,False),"") -> 52 | E6: =IFERROR(VLOOKUP(B6,Stock2!F:J,5,False),"") -> 36 | H6: [CS]Focus TG FF Samsung Galaxy A26 5G/A17 5G Black | I6: 8859703433569 | J6: {=IFERROR(_xlfn.XLOOKUP(I6,Stock1!F:F,Stock1!E:E,""),"")} -> 249 | K6: {=IFERROR(_xlfn.XLOOKUP(I6,Incentive!B:B,Incentive!E:E,""),"")} -> 10 | L6: =IFERROR(VLOOKUP(I6,Stock1!F:J,5,False),"") -> 4 | M6: =IFERROR(VLOOKUP(I6,Stock2!F:J,5,False),"") -> 13 | R6: {=IFERROR(_xlfn.XLOOKUP(Q6,Stock1!F:F,Stock1!E:E,""),"")} | S6: =IFERROR(VLOOKUP(Q6,Stock1!F:J,5,False),"") | T6: =IFERROR(VLOOKUP(Q6,Stock2!F:J,5,False),"") | V6: {=_xlfn.XLOOKUP("Charger",Stock1!B6,Stock1!I6,"")} | W6: {=_xlfn.XLOOKUP(V6,Stock1!I6,Stock1!F6,"")} | X6: {=_xlfn.XLOOKUP(V6,Stock1!I6,Stock1!J6,"")} | Y6: {=_xlfn.XLOOKUP("Screen Protector for Android Phone and Other",Stock1!B6,Stock1!I6,"")} | Z6: {=_xlfn.XLOOKUP("Screen Protector for Galaxy Phone",Stock1!B6,Stock1!I6,"")} | AA6: {=_xlfn.XLOOKUP("Screen Protector for Galaxy Tab",Stock1!B6,Stock1!I6,"")} | AB6: =TEXTJOIN(,,Y6,Z6,AA6) | AC6: {=_xlfn.XLOOKUP(AB6,Stock1!I6,Stock1!F6,"")} | AD6: {=_xlfn.XLOOKUP(AB6,Stock1!I6,Stock1!J6,"")} | AE6: {=_xlfn.XLOOKUP("Storage",Stock1!B6,Stock1!I6,"")} | AF6: {=_xlfn.XLOOKUP(AE6,Stock1!I6,Stock1!F6,"")} | AG6: {=_xlfn.XLOOKUP(AE6,Stock1!I6,Stock1!J6,"")}
A7: Samsung Adapter 25W No Cable-White | B7: EP-T2510NWEGTH | C7: {=IFERROR(_xlfn.XLOOKUP(B7,Stock1!F:F,Stock1!E:E,""),"")} -> 690 | D7: =IFERROR(VLOOKUP(B7,Stock1!F:J,5,False),"") -> 42 | E7: =IFERROR(VLOOKUP(B7,Stock2!F:J,5,False),"") -> 31 | H7: [CS]Focus TG FF Samsung Galaxy A27 5G Black | I7: 8859703443339 | J7: {=IFERROR(_xlfn.XLOOKUP(I7,Stock1!F:F,Stock1!E:E,""),"")} -> 249 | K7: {=IFERROR(_xlfn.XLOOKUP(I7,Incentive!B:B,Incentive!E:E,""),"")} | L7: =IFERROR(VLOOKUP(I7,Stock1!F:J,5,False),"") -> 12 | M7: =IFERROR(VLOOKUP(I7,Stock2!F:J,5,False),"") | R7: {=IFERROR(_xlfn.XLOOKUP(Q7,Stock1!F:F,Stock1!E:E,""),"")} | S7: =IFERROR(VLOOKUP(Q7,Stock1!F:J,5,False),"") | T7: =IFERROR(VLOOKUP(Q7,Stock2!F:J,5,False),"") | V7: {=_xlfn.XLOOKUP("Charger",Stock1!B7,Stock1!I7,"")} | W7: {=_xlfn.XLOOKUP(V7,Stock1!I7,Stock1!F7,"")} | X7: {=_xlfn.XLOOKUP(V7,Stock1!I7,Stock1!J7,"")} | Y7: {=_xlfn.XLOOKUP("Screen Protector for Android Phone and Other",Stock1!B7,Stock1!I7,"")} | Z7: {=_xlfn.XLOOKUP("Screen Protector for Galaxy Phone",Stock1!B7,Stock1!I7,"")} | AA7: {=_xlfn.XLOOKUP("Screen Protector for Galaxy Tab",Stock1!B7,Stock1!I7,"")} | AB7: =TEXTJOIN(,,Y7,Z7,AA7) | AC7: {=_xlfn.XLOOKUP(AB7,Stock1!I7,Stock1!F7,"")} | AD7: {=_xlfn.XLOOKUP(AB7,Stock1!I7,Stock1!J7,"")} | AE7: {=_xlfn.XLOOKUP("Storage",Stock1!B7,Stock1!I7,"")} | AF7: {=_xlfn.XLOOKUP(AE7,Stock1!I7,Stock1!F7,"")} | AG7: {=_xlfn.XLOOKUP(AE7,Stock1!I7,Stock1!J7,"")}
A8: Samsung Adapter 45W Fastcharge with Cable - Black | B8: EP-T4511XBEGTH | C8: {=IFERROR(_xlfn.XLOOKUP(B8,Stock1!F:F,Stock1!E:E,""),"")} -> 1290 | D8: =IFERROR(VLOOKUP(B8,Stock1!F:J,5,False),"") -> 7 | E8: =IFERROR(VLOOKUP(B8,Stock2!F:J,5,False),"") -> 1 | H8: [CS]Hishield Tempered Glass FC 2.5D for Samsung A37 | I8: 8859216846719 | J8: {=IFERROR(_xlfn.XLOOKUP(I8,Stock1!F:F,Stock1!E:E,""),"")} -> 299 | K8: {=IFERROR(_xlfn.XLOOKUP(I8,Incentive!B:B,Incentive!E:E,""),"")} | L8: =IFERROR(VLOOKUP(I8,Stock1!F:J,5,False),"") -> 35 | M8: =IFERROR(VLOOKUP(I8,Stock2!F:J,5,False),"") -> 18 | R8: {=IFERROR(_xlfn.XLOOKUP(Q8,Stock1!F:F,Stock1!E:E,""),"")} | S8: =IFERROR(VLOOKUP(Q8,Stock1!F:J,5,False),"") | T8: =IFERROR(VLOOKUP(Q8,Stock2!F:J,5,False),"") | V8: {=_xlfn.XLOOKUP("Charger",Stock1!B8,Stock1!I8,"")} | W8: {=_xlfn.XLOOKUP(V8,Stock1!I8,Stock1!F8,"")} | X8: {=_xlfn.XLOOKUP(V8,Stock1!I8,Stock1!J8,"")} | Y8: {=_xlfn.XLOOKUP("Screen Protector for Android Phone and Other",Stock1!B8,Stock1!I8,"")} | Z8: {=_xlfn.XLOOKUP("Screen Protector for Galaxy Phone",Stock1!B8,Stock1!I8,"")} | AA8: {=_xlfn.XLOOKUP("Screen Protector for Galaxy Tab",Stock1!B8,Stock1!I8,"")} | AB8: =TEXTJOIN(,,Y8,Z8,AA8) | AC8: {=_xlfn.XLOOKUP(AB8,Stock1!I8,Stock1!F8,"")} | AD8: {=_xlfn.XLOOKUP(AB8,Stock1!I8,Stock1!J8,"")} | AE8: {=_xlfn.XLOOKUP("Storage",Stock1!B8,Stock1!I8,"")} | AF8: {=_xlfn.XLOOKUP(AE8,Stock1!I8,Stock1!F8,"")} | AG8: {=_xlfn.XLOOKUP(AE8,Stock1!I8,Stock1!J8,"")}
A9: Samsung Adapter 45W Fastcharge with Cable (SIS) - Black | B9: SSG-EP-T4511XBEGTH | C9: {=IFERROR(_xlfn.XLOOKUP(B9,Stock1!F:F,Stock1!E:E,""),"")} -> 1290 | D9: =IFERROR(VLOOKUP(B9,Stock1!F:J,5,False),"") -> 43 | E9: =IFERROR(VLOOKUP(B9,Stock2!F:J,5,False),"") -> 25 | H9: [CS]Hishield Tempered Glass FC 2.5D for Samsung A57 | I9: 8859216846726 | J9: {=IFERROR(_xlfn.XLOOKUP(I9,Stock1!F:F,Stock1!E:E,""),"")} -> 299 | K9: {=IFERROR(_xlfn.XLOOKUP(I9,Incentive!B:B,Incentive!E:E,""),"")} | L9: =IFERROR(VLOOKUP(I9,Stock1!F:J,5,False),"") -> 10 | M9: =IFERROR(VLOOKUP(I9,Stock2!F:J,5,False),"") -> 29 | R9: {=IFERROR(_xlfn.XLOOKUP(Q9,Stock1!F:F,Stock1!E:E,""),"")} | S9: =IFERROR(VLOOKUP(Q9,Stock1!F:J,5,False),"") | T9: =IFERROR(VLOOKUP(Q9,Stock2!F:J,5,False),"") | V9: {=_xlfn.XLOOKUP("Charger",Stock1!B9,Stock1!I9,"")} | W9: {=_xlfn.XLOOKUP(V9,Stock1!I9,Stock1!F9,"")} | X9: {=_xlfn.XLOOKUP(V9,Stock1!I9,Stock1!J9,"")} | Y9: {=_xlfn.XLOOKUP("Screen Protector for Android Phone and Other",Stock1!B9,Stock1!I9,"")} | Z9: {=_xlfn.XLOOKUP("Screen Protector for Galaxy Phone",Stock1!B9,Stock1!I9,"")} | AA9: {=_xlfn.XLOOKUP("Screen Protector for Galaxy Tab",Stock1!B9,Stock1!I9,"")} | AB9: =TEXTJOIN(,,Y9,Z9,AA9) | AC9: {=_xlfn.XLOOKUP(AB9,Stock1!I9,Stock1!F9,"")} | AD9: {=_xlfn.XLOOKUP(AB9,Stock1!I9,Stock1!J9,"")} | AE9: {=_xlfn.XLOOKUP("Storage",Stock1!B9,Stock1!I9,"")} | AF9: {=_xlfn.XLOOKUP(AE9,Stock1!I9,Stock1!F9,"")} | AG9: {=_xlfn.XLOOKUP(AE9,Stock1!I9,Stock1!J9,"")}
A10: Samsung Adapter 45W without cable - Black | B10: EP-T4511NBEGTH | C10: {=IFERROR(_xlfn.XLOOKUP(B10,Stock1!F:F,Stock1!E:E,""),"")} -> 1090 | D10: =IFERROR(VLOOKUP(B10,Stock1!F:J,5,False),"") -> 19 | E10: =IFERROR(VLOOKUP(B10,Stock2!F:J,5,False),"") -> 21 | H10: [CS]Focus TG FF Samsung Galaxy A36 5G/A56 5G Black | I10: 8859703433828 | J10: {=IFERROR(_xlfn.XLOOKUP(I10,Stock1!F:F,Stock1!E:E,""),"")} -> 249 | K10: {=IFERROR(_xlfn.XLOOKUP(I10,Incentive!B:B,Incentive!E:E,""),"")} -> 10 | L10: =IFERROR(VLOOKUP(I10,Stock1!F:J,5,False),"") -> 9 | M10: =IFERROR(VLOOKUP(I10,Stock2!F:J,5,False),"") -> 12 | R10: {=IFERROR(_xlfn.XLOOKUP(Q10,Stock1!F:F,Stock1!E:E,""),"")} | S10: =IFERROR(VLOOKUP(Q10,Stock1!F:J,5,False),"") | T10: =IFERROR(VLOOKUP(Q10,Stock2!F:J,5,False),"") | V10: {=_xlfn.XLOOKUP("Charger",Stock1!B10,Stock1!I10,"")} | W10: {=_xlfn.XLOOKUP(V10,Stock1!I10,Stock1!F10,"")} | X10: {=_xlfn.XLOOKUP(V10,Stock1!I10,Stock1!J10,"")} | Y10: {=_xlfn.XLOOKUP("Screen Protector for Android Phone and Other",Stock1!B10,Stock1!I10,"")} | Z10: {=_xlfn.XLOOKUP("Screen Protector for Galaxy Phone",Stock1!B10,Stock1!I10,"")} | AA10: {=_xlfn.XLOOKUP("Screen Protector for Galaxy Tab",Stock1!B10,Stock1!I10,"")} | AB10: =TEXTJOIN(,,Y10,Z10,AA10) | AC10: {=_xlfn.XLOOKUP(AB10,Stock1!I10,Stock1!F10,"")} | AD10: {=_xlfn.XLOOKUP(AB10,Stock1!I10,Stock1!J10,"")} | AE10: {=_xlfn.XLOOKUP("Storage",Stock1!B10,Stock1!I10,"")} | AF10: {=_xlfn.XLOOKUP(AE10,Stock1!I10,Stock1!F10,"")} | AG10: {=_xlfn.XLOOKUP(AE10,Stock1!I10,Stock1!J10,"")}
A11: Samsung Adapter 60W without cable - Black | B11: EP-T6010NBEGTH | C11: {=IFERROR(_xlfn.XLOOKUP(B11,Stock1!F:F,Stock1!E:E,""),"")} -> 1490 | D11: =IFERROR(VLOOKUP(B11,Stock1!F:J,5,False),"") -> 26 | E11: =IFERROR(VLOOKUP(B11,Stock2!F:J,5,False),"") -> 9 | H11: [CS]Focus TG FF Samsung Galaxy A57 5G Black | I11: 8859703437345 | J11: {=IFERROR(_xlfn.XLOOKUP(I11,Stock1!F:F,Stock1!E:E,""),"")} -> 249 | K11: {=IFERROR(_xlfn.XLOOKUP(I11,Incentive!B:B,Incentive!E:E,""),"")} | L11: =IFERROR(VLOOKUP(I11,Stock1!F:J,5,False),"") -> 36 | M11: =IFERROR(VLOOKUP(I11,Stock2!F:J,5,False),"") -> 17 | R11: {=IFERROR(_xlfn.XLOOKUP(Q11,Stock1!F:F,Stock1!E:E,""),"")} | S11: =IFERROR(VLOOKUP(Q11,Stock1!F:J,5,False),"") | T11: =IFERROR(VLOOKUP(Q11,Stock2!F:J,5,False),"") | V11: {=_xlfn.XLOOKUP("Charger",Stock1!B11,Stock1!I11,"")} | W11: {=_xlfn.XLOOKUP(V11,Stock1!I11,Stock1!F11,"")} | X11: {=_xlfn.XLOOKUP(V11,Stock1!I11,Stock1!J11,"")} | Y11: {=_xlfn.XLOOKUP("Screen Protector for Android Phone and Other",Stock1!B11,Stock1!I11,"")} | Z11: {=_xlfn.XLOOKUP("Screen Protector for Galaxy Phone",Stock1!B11,Stock1!I11,"")} | AA11: {=_xlfn.XLOOKUP("Screen Protector for Galaxy Tab",Stock1!B11,Stock1!I11,"")} | AB11: =TEXTJOIN(,,Y11,Z11,AA11) | AC11: {=_xlfn.XLOOKUP(AB11,Stock1!I11,Stock1!F11,"")} | AD11: {=_xlfn.XLOOKUP(AB11,Stock1!I11,Stock1!J11,"")} | AE11: {=_xlfn.XLOOKUP("Storage",Stock1!B11,Stock1!I11,"")} | AF11: {=_xlfn.XLOOKUP(AE11,Stock1!I11,Stock1!F11,"")} | AG11: {=_xlfn.XLOOKUP(AE11,Stock1!I11,Stock1!J11,"")}
A12: #REF! | B12: #REF! | C12: {=IFERROR(_xlfn.XLOOKUP(B12,Stock1!F:F,Stock1!E:E,""),"")} | D12: =IFERROR(VLOOKUP(B12,Stock1!F:J,5,False),"") | E12: =IFERROR(VLOOKUP(B12,Stock2!F:J,5,False),"") | H12: Samsung Galaxy Fold8 Anti-reflecting Film - Transparent | I12: EF-UF971CTEGWW | J12: {=IFERROR(_xlfn.XLOOKUP(I12,Stock1!F:F,Stock1!E:E,""),"")} -> 590 | K12: {=IFERROR(_xlfn.XLOOKUP(I12,Incentive!B:B,Incentive!E:E,""),"")} | L12: =IFERROR(VLOOKUP(I12,Stock1!F:J,5,False),"") -> 1 | M12: =IFERROR(VLOOKUP(I12,Stock2!F:J,5,False),"") -> 1 | R12: {=IFERROR(_xlfn.XLOOKUP(Q12,Stock1!F:F,Stock1!E:E,""),"")} | S12: =IFERROR(VLOOKUP(Q12,Stock1!F:J,5,False),"") | T12: =IFERROR(VLOOKUP(Q12,Stock2!F:J,5,False),"") | V12: {=_xlfn.XLOOKUP("Charger",Stock1!B12,Stock1!I12,"")} | W12: {=_xlfn.XLOOKUP(V12,Stock1!I12,Stock1!F12,"")} | X12: {=_xlfn.XLOOKUP(V12,Stock1!I12,Stock1!J12,"")} | Y12: {=_xlfn.XLOOKUP("Screen Protector for Android Phone and Other",Stock1!B12,Stock1!I12,"")} | Z12: {=_xlfn.XLOOKUP("Screen Protector for Galaxy Phone",Stock1!B12,Stock1!I12,"")} | AA12: {=_xlfn.XLOOKUP("Screen Protector for Galaxy Tab",Stock1!B12,Stock1!I12,"")} | AB12: =TEXTJOIN(,,Y12,Z12,AA12) | AC12: {=_xlfn.XLOOKUP(AB12,Stock1!I12,Stock1!F12,"")} | AD12: {=_xlfn.XLOOKUP(AB12,Stock1!I12,Stock1!J12,"")} | AE12: {=_xlfn.XLOOKUP("Storage",Stock1!B12,Stock1!I12,"")} | AF12: {=_xlfn.XLOOKUP(AE12,Stock1!I12,Stock1!F12,"")} | AG12: {=_xlfn.XLOOKUP(AE12,Stock1!I12,Stock1!J12,"")}
C13: {=IFERROR(_xlfn.XLOOKUP(B13,Stock1!F:F,Stock1!E:E,""),"")} | D13: =IFERROR(VLOOKUP(B13,Stock1!F:J,5,False),"") | E13: =IFERROR(VLOOKUP(B13,Stock2!F:J,5,False),"") | H13: [CS]Focus TG FF Samsung Galaxy S25 FE Black | I13: 8859703436560 | J13: {=IFERROR(_xlfn.XLOOKUP(I13,Stock1!F:F,Stock1!E:E,""),"")} -> 249 | K13: {=IFERROR(_xlfn.XLOOKUP(I13,Incentive!B:B,Incentive!E:E,""),"")} | L13: =IFERROR(VLOOKUP(I13,Stock1!F:J,5,False),"") -> 19 | M13: =IFERROR(VLOOKUP(I13,Stock2!F:J,5,False),"") -> 8 | R13: {=IFERROR(_xlfn.XLOOKUP(Q13,Stock1!F:F,Stock1!E:E,""),"")} | S13: =IFERROR(VLOOKUP(Q13,Stock1!F:J,5,False),"") | T13: =IFERROR(VLOOKUP(Q13,Stock2!F:J,5,False),"") | V13: {=_xlfn.XLOOKUP("Charger",Stock1!B13,Stock1!I13,"")} | W13: {=_xlfn.XLOOKUP(V13,Stock1!I13,Stock1!F13,"")} | X13: {=_xlfn.XLOOKUP(V13,Stock1!I13,Stock1!J13,"")} | Y13: {=_xlfn.XLOOKUP("Screen Protector for Android Phone and Other",Stock1!B13,Stock1!I13,"")} | Z13: {=_xlfn.XLOOKUP("Screen Protector for Galaxy Phone",Stock1!B13,Stock1!I13,"")} | AA13: {=_xlfn.XLOOKUP("Screen Protector for Galaxy Tab",Stock1!B13,Stock1!I13,"")} | AB13: =TEXTJOIN(,,Y13,Z13,AA13) | AC13: {=_xlfn.XLOOKUP(AB13,Stock1!I13,Stock1!F13,"")} | AD13: {=_xlfn.XLOOKUP(AB13,Stock1!I13,Stock1!J13,"")} | AE13: {=_xlfn.XLOOKUP("Storage",Stock1!B13,Stock1!I13,"")} | AF13: {=_xlfn.XLOOKUP(AE13,Stock1!I13,Stock1!F13,"")} | AG13: {=_xlfn.XLOOKUP(AE13,Stock1!I13,Stock1!J13,"")}
C14: {=IFERROR(_xlfn.XLOOKUP(B14,Stock1!F:F,Stock1!E:E,""),"")} | D14: =IFERROR(VLOOKUP(B14,Stock1!F:J,5,False),"") | E14: =IFERROR(VLOOKUP(B14,Stock2!F:J,5,False),"") | H14: [CS]HISHIELD TemperedGlass FC 2.5D Samsung S25 FE | I14: 8859216804030 | J14: {=IFERROR(_xlfn.XLOOKUP(I14,Stock1!F:F,Stock1!E:E,""),"")} -> 299 | K14: {=IFERROR(_xlfn.XLOOKUP(I14,Incentive!B:B,Incentive!E:E,""),"")} | L14: =IFERROR(VLOOKUP(I14,Stock1!F:J,5,False),"") -> 11 | M14: =IFERROR(VLOOKUP(I14,Stock2!F:J,5,False),"") -> 20 | R14: {=IFERROR(_xlfn.XLOOKUP(Q14,Stock1!F:F,Stock1!E:E,""),"")} | S14: =IFERROR(VLOOKUP(Q14,Stock1!F:J,5,False),"") | T14: =IFERROR(VLOOKUP(Q14,Stock2!F:J,5,False),"") | V14: {=_xlfn.XLOOKUP("Charger",Stock1!B14,Stock1!I14,"")} | W14: {=_xlfn.XLOOKUP(V14,Stock1!I14,Stock1!F14,"")} | X14: {=_xlfn.XLOOKUP(V14,Stock1!I14,Stock1!J14,"")} | Y14: {=_xlfn.XLOOKUP("Screen Protector for Android Phone and Other",Stock1!B14,Stock1!I14,"")} | Z14: {=_xlfn.XLOOKUP("Screen Protector for Galaxy Phone",Stock1!B14,Stock1!I14,"")} | AA14: {=_xlfn.XLOOKUP("Screen Protector for Galaxy Tab",Stock1!B14,Stock1!I14,"")} | AB14: =TEXTJOIN(,,Y14,Z14,AA14) | AC14: {=_xlfn.XLOOKUP(AB14,Stock1!I14,Stock1!F14,"")} | AD14: {=_xlfn.XLOOKUP(AB14,Stock1!I14,Stock1!J14,"")} | AE14: {=_xlfn.XLOOKUP("Storage",Stock1!B14,Stock1!I14,"")} | AF14: {=_xlfn.XLOOKUP(AE14,Stock1!I14,Stock1!F14,"")} | AG14: {=_xlfn.XLOOKUP(AE14,Stock1!I14,Stock1!J14,"")}
C15: {=IFERROR(_xlfn.XLOOKUP(B15,Stock1!F:F,Stock1!E:E,""),"")} | D15: =IFERROR(VLOOKUP(B15,Stock1!F:J,5,False),"") | E15: =IFERROR(VLOOKUP(B15,Stock2!F:J,5,False),"") | H15: Samsung Galaxy S26FE Anti-reflecting Film - Transparency | I15: EF-US741CTEGWW | J15: {=IFERROR(_xlfn.XLOOKUP(I15,Stock1!F:F,Stock1!E:E,""),"")} -> 590 | K15: {=IFERROR(_xlfn.XLOOKUP(I15,Incentive!B:B,Incentive!E:E,""),"")} | L15: =IFERROR(VLOOKUP(I15,Stock1!F:J,5,False),"") -> 2 | M15: =IFERROR(VLOOKUP(I15,Stock2!F:J,5,False),"") -> 2 | R15: {=IFERROR(_xlfn.XLOOKUP(Q15,Stock1!F:F,Stock1!E:E,""),"")} | S15: =IFERROR(VLOOKUP(Q15,Stock1!F:J,5,False),"") | T15: =IFERROR(VLOOKUP(Q15,Stock2!F:J,5,False),"") | V15: {=_xlfn.XLOOKUP("Charger",Stock1!B15,Stock1!I15,"")} | W15: {=_xlfn.XLOOKUP(V15,Stock1!I15,Stock1!F15,"")} | X15: {=_xlfn.XLOOKUP(V15,Stock1!I15,Stock1!J15,"")} | Y15: {=_xlfn.XLOOKUP("Screen Protector for Android Phone and Other",Stock1!B15,Stock1!I15,"")} | Z15: {=_xlfn.XLOOKUP("Screen Protector for Galaxy Phone",Stock1!B15,Stock1!I15,"")} | AA15: {=_xlfn.XLOOKUP("Screen Protector for Galaxy Tab",Stock1!B15,Stock1!I15,"")} | AB15: =TEXTJOIN(,,Y15,Z15,AA15) | AC15: {=_xlfn.XLOOKUP(AB15,Stock1!I15,Stock1!F15,"")} | AD15: {=_xlfn.XLOOKUP(AB15,Stock1!I15,Stock1!J15,"")} | AE15: {=_xlfn.XLOOKUP("Storage",Stock1!B15,Stock1!I15,"")} | AF15: {=_xlfn.XLOOKUP(AE15,Stock1!I15,Stock1!F15,"")} | AG15: {=_xlfn.XLOOKUP(AE15,Stock1!I15,Stock1!J15,"")}
C16: {=IFERROR(_xlfn.XLOOKUP(B16,Stock1!F:F,Stock1!E:E,""),"")} | D16: =IFERROR(VLOOKUP(B16,Stock1!F:J,5,False),"") | E16: =IFERROR(VLOOKUP(B16,Stock2!F:J,5,False),"") | H16: [CS]Hishield Hydrogel Film/Size S(18x12cm) - Ultra Clear | I16: 8859216623860 | J16: {=IFERROR(_xlfn.XLOOKUP(I16,Stock1!F:F,Stock1!E:E,""),"")} -> 290 | K16: {=IFERROR(_xlfn.XLOOKUP(I16,Incentive!B:B,Incentive!E:E,""),"")} -> 50 | L16: =IFERROR(VLOOKUP(I16,Stock1!F:J,5,False),"") -> 32 | M16: =IFERROR(VLOOKUP(I16,Stock2!F:J,5,False),"") | R16: {=IFERROR(_xlfn.XLOOKUP(Q16,Stock1!F:F,Stock1!E:E,""),"")} | S16: =IFERROR(VLOOKUP(Q16,Stock1!F:J,5,False),"") | T16: =IFERROR(VLOOKUP(Q16,Stock2!F:J,5,False),"") | V16: {=_xlfn.XLOOKUP("Charger",Stock1!B16,Stock1!I16,"")} | W16: {=_xlfn.XLOOKUP(V16,Stock1!I16,Stock1!F16,"")} | X16: {=_xlfn.XLOOKUP(V16,Stock1!I16,Stock1!J16,"")} | Y16: {=_xlfn.XLOOKUP("Screen Protector for Android Phone and Other",Stock1!B16,Stock1!I16,"")} | Z16: {=_xlfn.XLOOKUP("Screen Protector for Galaxy Phone",Stock1!B16,Stock1!I16,"")} | AA16: {=_xlfn.XLOOKUP("Screen Protector for Galaxy Tab",Stock1!B16,Stock1!I16,"")} | AB16: =TEXTJOIN(,,Y16,Z16,AA16) | AC16: {=_xlfn.XLOOKUP(AB16,Stock1!I16,Stock1!F16,"")} | AD16: {=_xlfn.XLOOKUP(AB16,Stock1!I16,Stock1!J16,"")} | AE16: {=_xlfn.XLOOKUP("Storage",Stock1!B16,Stock1!I16,"")} | AF16: {=_xlfn.XLOOKUP(AE16,Stock1!I16,Stock1!F16,"")} | AG16: {=_xlfn.XLOOKUP(AE16,Stock1!I16,Stock1!J16,"")}
C17: {=IFERROR(_xlfn.XLOOKUP(B17,Stock1!F:F,Stock1!E:E,""),"")} | D17: =IFERROR(VLOOKUP(B17,Stock1!F:J,5,False),"") | E17: =IFERROR(VLOOKUP(B17,Stock2!F:J,5,False),"") | H17: [CS]Hishield Hydrogel Film/Size S(18x12cm) - Anti Glare Gray | I17: 8859216623877 | J17: {=IFERROR(_xlfn.XLOOKUP(I17,Stock1!F:F,Stock1!E:E,""),"")} -> 290 | K17: {=IFERROR(_xlfn.XLOOKUP(I17,Incentive!B:B,Incentive!E:E,""),"")} -> 50 | L17: =IFERROR(VLOOKUP(I17,Stock1!F:J,5,False),"") -> 32 | M17: =IFERROR(VLOOKUP(I17,Stock2!F:J,5,False),"") | R17: {=IFERROR(_xlfn.XLOOKUP(Q17,Stock1!F:F,Stock1!E:E,""),"")} | S17: =IFERROR(VLOOKUP(Q17,Stock1!F:J,5,False),"") | T17: =IFERROR(VLOOKUP(Q17,Stock2!F:J,5,False),"") | V17: {=_xlfn.XLOOKUP("Charger",Stock1!B17,Stock1!I17,"")} | W17: {=_xlfn.XLOOKUP(V17,Stock1!I17,Stock1!F17,"")} | X17: {=_xlfn.XLOOKUP(V17,Stock1!I17,Stock1!J17,"")} | Y17: {=_xlfn.XLOOKUP("Screen Protector for Android Phone and Other",Stock1!B17,Stock1!I17,"")} | Z17: {=_xlfn.XLOOKUP("Screen Protector for Galaxy Phone",Stock1!B17,Stock1!I17,"")} | AA17: {=_xlfn.XLOOKUP("Screen Protector for Galaxy Tab",Stock1!B17,Stock1!I17,"")} | AB17: =TEXTJOIN(,,Y17,Z17,AA17) | AC17: {=_xlfn.XLOOKUP(AB17,Stock1!I17,Stock1!F17,"")} | AD17: {=_xlfn.XLOOKUP(AB17,Stock1!I17,Stock1!J17,"")} | AE17: {=_xlfn.XLOOKUP("Storage",Stock1!B17,Stock1!I17,"")} | AF17: {=_xlfn.XLOOKUP(AE17,Stock1!I17,Stock1!F17,"")} | AG17: {=_xlfn.XLOOKUP(AE17,Stock1!I17,Stock1!J17,"")}
C18: {=IFERROR(_xlfn.XLOOKUP(B18,Stock1!F:F,Stock1!E:E,""),"")} | D18: =IFERROR(VLOOKUP(B18,Stock1!F:J,5,False),"") | E18: =IFERROR(VLOOKUP(B18,Stock2!F:J,5,False),"") | H18: [CS]Focus TG FF SL Samsung S25 Black | I18: 8859703433576 | J18: {=IFERROR(_xlfn.XLOOKUP(I18,Stock1!F:F,Stock1!E:E,""),"")} -> 490 | K18: {=IFERROR(_xlfn.XLOOKUP(I18,Incentive!B:B,Incentive!E:E,""),"")} -> 50 | L18: =IFERROR(VLOOKUP(I18,Stock1!F:J,5,False),"") -> 1 | M18: =IFERROR(VLOOKUP(I18,Stock2!F:J,5,False),"") -> 2 | R18: {=IFERROR(_xlfn.XLOOKUP(Q18,Stock1!F:F,Stock1!E:E,""),"")} | S18: =IFERROR(VLOOKUP(Q18,Stock1!F:J,5,False),"") | T18: =IFERROR(VLOOKUP(Q18,Stock2!F:J,5,False),"") | V18: {=_xlfn.XLOOKUP("Charger",Stock1!B18,Stock1!I18,"")} | W18: {=_xlfn.XLOOKUP(V18,Stock1!I18,Stock1!F18,"")} | X18: {=_xlfn.XLOOKUP(V18,Stock1!I18,Stock1!J18,"")} | Y18: {=_xlfn.XLOOKUP("Screen Protector for Android Phone and Other",Stock1!B18,Stock1!I18,"")} | Z18: {=_xlfn.XLOOKUP("Screen Protector for Galaxy Phone",Stock1!B18,Stock1!I18,"")} | AA18: {=_xlfn.XLOOKUP("Screen Protector for Galaxy Tab",Stock1!B18,Stock1!I18,"")} | AB18: =TEXTJOIN(,,Y18,Z18,AA18) | AC18: {=_xlfn.XLOOKUP(AB18,Stock1!I18,Stock1!F18,"")} | AD18: {=_xlfn.XLOOKUP(AB18,Stock1!I18,Stock1!J18,"")} | AE18: {=_xlfn.XLOOKUP("Storage",Stock1!B18,Stock1!I18,"")} | AF18: {=_xlfn.XLOOKUP(AE18,Stock1!I18,Stock1!F18,"")} | AG18: {=_xlfn.XLOOKUP(AE18,Stock1!I18,Stock1!J18,"")}
C19: {=IFERROR(_xlfn.XLOOKUP(B19,Stock1!F:F,Stock1!E:E,""),"")} | D19: =IFERROR(VLOOKUP(B19,Stock1!F:J,5,False),"") | E19: =IFERROR(VLOOKUP(B19,Stock2!F:J,5,False),"") | H19: [CS]Focus TG FF SL Samsung S25 Ultra Black | I19: 8859703433590 | J19: {=IFERROR(_xlfn.XLOOKUP(I19,Stock1!F:F,Stock1!E:E,""),"")} -> 490 | K19: {=IFERROR(_xlfn.XLOOKUP(I19,Incentive!B:B,Incentive!E:E,""),"")} -> 50 | L19: =IFERROR(VLOOKUP(I19,Stock1!F:J,5,False),"") -> 10 | M19: =IFERROR(VLOOKUP(I19,Stock2!F:J,5,False),"") -> 16 | R19: {=IFERROR(_xlfn.XLOOKUP(Q19,Stock1!F:F,Stock1!E:E,""),"")} | S19: =IFERROR(VLOOKUP(Q19,Stock1!F:J,5,False),"") | T19: =IFERROR(VLOOKUP(Q19,Stock2!F:J,5,False),"") | V19: {=_xlfn.XLOOKUP("Charger",Stock1!B19,Stock1!I19,"")} | W19: {=_xlfn.XLOOKUP(V19,Stock1!I19,Stock1!F19,"")} | X19: {=_xlfn.XLOOKUP(V19,Stock1!I19,Stock1!J19,"")} | Y19: {=_xlfn.XLOOKUP("Screen Protector for Android Phone and Other",Stock1!B19,Stock1!I19,"")} | Z19: {=_xlfn.XLOOKUP("Screen Protector for Galaxy Phone",Stock1!B19,Stock1!I19,"")} | AA19: {=_xlfn.XLOOKUP("Screen Protector for Galaxy Tab",Stock1!B19,Stock1!I19,"")} | AB19: =TEXTJOIN(,,Y19,Z19,AA19) | AC19: {=_xlfn.XLOOKUP(AB19,Stock1!I19,Stock1!F19,"")} | AD19: {=_xlfn.XLOOKUP(AB19,Stock1!I19,Stock1!J19,"")} | AE19: {=_xlfn.XLOOKUP("Storage",Stock1!B19,Stock1!I19,"")} | AF19: {=_xlfn.XLOOKUP(AE19,Stock1!I19,Stock1!F19,"")} | AG19: {=_xlfn.XLOOKUP(AE19,Stock1!I19,Stock1!J19,"")}
H20: [CS]Focus TG FF SL PV Samsung S25 Ultra Black | I20: 8859703433606 | J20: {=IFERROR(_xlfn.XLOOKUP(I20,Stock1!F:F,Stock1!E:E,""),"")} -> 690 | K20: {=IFERROR(_xlfn.XLOOKUP(I20,Incentive!B:B,Incentive!E:E,""),"")} -> 50 | L20: =IFERROR(VLOOKUP(I20,Stock1!F:J,5,False),"") -> 3 | M20: =IFERROR(VLOOKUP(I20,Stock2!F:J,5,False),"") -> 5 | R20: {=IFERROR(_xlfn.XLOOKUP(Q20,Stock1!F:F,Stock1!E:E,""),"")} | S20: =IFERROR(VLOOKUP(Q20,Stock1!F:J,5,False),"") | T20: =IFERROR(VLOOKUP(Q20,Stock2!F:J,5,False),"") | V20: {=_xlfn.XLOOKUP("Charger",Stock1!B20,Stock1!I20,"")} | W20: {=_xlfn.XLOOKUP(V20,Stock1!I20,Stock1!F20,"")} | X20: {=_xlfn.XLOOKUP(V20,Stock1!I20,Stock1!J20,"")} | Y20: {=_xlfn.XLOOKUP("Screen Protector for Android Phone and Other",Stock1!B20,Stock1!I20,"")} | Z20: {=_xlfn.XLOOKUP("Screen Protector for Galaxy Phone",Stock1!B20,Stock1!I20,"")} | AA20: {=_xlfn.XLOOKUP("Screen Protector for Galaxy Tab",Stock1!B20,Stock1!I20,"")} | AB20: =TEXTJOIN(,,Y20,Z20,AA20) | AC20: {=_xlfn.XLOOKUP(AB20,Stock1!I20,Stock1!F20,"")} | AD20: {=_xlfn.XLOOKUP(AB20,Stock1!I20,Stock1!J20,"")} | AE20: {=_xlfn.XLOOKUP("Storage",Stock1!B20,Stock1!I20,"")} | AF20: {=_xlfn.XLOOKUP(AE20,Stock1!I20,Stock1!F20,"")} | AG20: {=_xlfn.XLOOKUP(AE20,Stock1!I20,Stock1!J20,"")}
H21: [CS]Hishield Tempered Glass FC 2.5D Samsung S25Ultra - Black | I21: 8859216739264 | J21: {=IFERROR(_xlfn.XLOOKUP(I21,Stock1!F:F,Stock1!E:E,""),"")} -> 590 | K21: {=IFERROR(_xlfn.XLOOKUP(I21,Incentive!B:B,Incentive!E:E,""),"")} -> 50 | L21: =IFERROR(VLOOKUP(I21,Stock1!F:J,5,False),"") -> 4 | M21: =IFERROR(VLOOKUP(I21,Stock2!F:J,5,False),"") -> 5 | R21: {=IFERROR(_xlfn.XLOOKUP(Q21,Stock1!F:F,Stock1!E:E,""),"")} | S21: =IFERROR(VLOOKUP(Q21,Stock1!F:J,5,False),"") | T21: =IFERROR(VLOOKUP(Q21,Stock2!F:J,5,False),"") | V21: {=_xlfn.XLOOKUP("Charger",Stock1!B21,Stock1!I21,"")} | W21: {=_xlfn.XLOOKUP(V21,Stock1!I21,Stock1!F21,"")} | X21: {=_xlfn.XLOOKUP(V21,Stock1!I21,Stock1!J21,"")} | Y21: {=_xlfn.XLOOKUP("Screen Protector for Android Phone and Other",Stock1!B21,Stock1!I21,"")} | Z21: {=_xlfn.XLOOKUP("Screen Protector for Galaxy Phone",Stock1!B21,Stock1!I21,"")} | AA21: {=_xlfn.XLOOKUP("Screen Protector for Galaxy Tab",Stock1!B21,Stock1!I21,"")} | AB21: =TEXTJOIN(,,Y21,Z21,AA21) | AC21: {=_xlfn.XLOOKUP(AB21,Stock1!I21,Stock1!F21,"")} | AD21: {=_xlfn.XLOOKUP(AB21,Stock1!I21,Stock1!J21,"")} | AE21: {=_xlfn.XLOOKUP("Storage",Stock1!B21,Stock1!I21,"")} | AF21: {=_xlfn.XLOOKUP(AE21,Stock1!I21,Stock1!F21,"")} | AG21: {=_xlfn.XLOOKUP(AE21,Stock1!I21,Stock1!J21,"")}
H22: Samsung Galaxy S25Plus Screen Protector - Transparent | I22: EF-US936CTEGWW | J22: {=IFERROR(_xlfn.XLOOKUP(I22,Stock1!F:F,Stock1!E:E,""),"")} -> 590 | K22: {=IFERROR(_xlfn.XLOOKUP(I22,Incentive!B:B,Incentive!E:E,""),"")} | L22: =IFERROR(VLOOKUP(I22,Stock1!F:J,5,False),"") -> 1 | M22: =IFERROR(VLOOKUP(I22,Stock2!F:J,5,False),"") | R22: {=IFERROR(_xlfn.XLOOKUP(Q22,Stock1!F:F,Stock1!E:E,""),"")} | S22: =IFERROR(VLOOKUP(Q22,Stock1!F:J,5,False),"") | T22: =IFERROR(VLOOKUP(Q22,Stock2!F:J,5,False),"") | V22: {=_xlfn.XLOOKUP("Charger",Stock1!B22,Stock1!I22,"")} | W22: {=_xlfn.XLOOKUP(V22,Stock1!I22,Stock1!F22,"")} | X22: {=_xlfn.XLOOKUP(V22,Stock1!I22,Stock1!J22,"")} | Y22: {=_xlfn.XLOOKUP("Screen Protector for Android Phone and Other",Stock1!B22,Stock1!I22,"")} | Z22: {=_xlfn.XLOOKUP("Screen Protector for Galaxy Phone",Stock1!B22,Stock1!I22,"")} | AA22: {=_xlfn.XLOOKUP("Screen Protector for Galaxy Tab",Stock1!B22,Stock1!I22,"")} | AB22: =TEXTJOIN(,,Y22,Z22,AA22) | AC22: {=_xlfn.XLOOKUP(AB22,Stock1!I22,Stock1!F22,"")} | AD22: {=_xlfn.XLOOKUP(AB22,Stock1!I22,Stock1!J22,"")} | AE22: {=_xlfn.XLOOKUP("Storage",Stock1!B22,Stock1!I22,"")} | AF22: {=_xlfn.XLOOKUP(AE22,Stock1!I22,Stock1!F22,"")} | AG22: {=_xlfn.XLOOKUP(AE22,Stock1!I22,Stock1!J22,"")}
H23: [CS]Focus TG FF SL Samsung Galaxy S26 | I23: 8859703437451 | J23: {=IFERROR(_xlfn.XLOOKUP(I23,Stock1!F:F,Stock1!E:E,""),"")} -> 490 | K23: {=IFERROR(_xlfn.XLOOKUP(I23,Incentive!B:B,Incentive!E:E,""),"")} | L23: =IFERROR(VLOOKUP(I23,Stock1!F:J,5,False),"") -> 2 | M23: =IFERROR(VLOOKUP(I23,Stock2!F:J,5,False),"") -> 4 | R23: {=IFERROR(_xlfn.XLOOKUP(Q23,Stock1!F:F,Stock1!E:E,""),"")} | S23: =IFERROR(VLOOKUP(Q23,Stock1!F:J,5,False),"") | T23: =IFERROR(VLOOKUP(Q23,Stock2!F:J,5,False),"") | V23: {=_xlfn.XLOOKUP("Charger",Stock1!B23,Stock1!I23,"")} | W23: {=_xlfn.XLOOKUP(V23,Stock1!I23,Stock1!F23,"")} | X23: {=_xlfn.XLOOKUP(V23,Stock1!I23,Stock1!J23,"")} | Y23: {=_xlfn.XLOOKUP("Screen Protector for Android Phone and Other",Stock1!B23,Stock1!I23,"")} | Z23: {=_xlfn.XLOOKUP("Screen Protector for Galaxy Phone",Stock1!B23,Stock1!I23,"")} | AA23: {=_xlfn.XLOOKUP("Screen Protector for Galaxy Tab",Stock1!B23,Stock1!I23,"")} | AB23: =TEXTJOIN(,,Y23,Z23,AA23) | AC23: {=_xlfn.XLOOKUP(AB23,Stock1!I23,Stock1!F23,"")} | AD23: {=_xlfn.XLOOKUP(AB23,Stock1!I23,Stock1!J23,"")} | AE23: {=_xlfn.XLOOKUP("Storage",Stock1!B23,Stock1!I23,"")} | AF23: {=_xlfn.XLOOKUP(AE23,Stock1!I23,Stock1!F23,"")} | AG23: {=_xlfn.XLOOKUP(AE23,Stock1!I23,Stock1!J23,"")}
H24: [CS]Focus TG FF SL Samsung Galaxy S26 Plus | I24: 8859703437468 | J24: {=IFERROR(_xlfn.XLOOKUP(I24,Stock1!F:F,Stock1!E:E,""),"")} -> 490 | K24: {=IFERROR(_xlfn.XLOOKUP(I24,Incentive!B:B,Incentive!E:E,""),"")} | L24: =IFERROR(VLOOKUP(I24,Stock1!F:J,5,False),"") -> 3 | M24: =IFERROR(VLOOKUP(I24,Stock2!F:J,5,False),"") -> 10 | R24: {=IFERROR(_xlfn.XLOOKUP(Q24,Stock1!F:F,Stock1!E:E,""),"")} | S24: =IFERROR(VLOOKUP(Q24,Stock1!F:J,5,False),"") | T24: =IFERROR(VLOOKUP(Q24,Stock2!F:J,5,False),"") | V24: {=_xlfn.XLOOKUP("Charger",Stock1!B24,Stock1!I24,"")} | W24: {=_xlfn.XLOOKUP(V24,Stock1!I24,Stock1!F24,"")} | X24: {=_xlfn.XLOOKUP(V24,Stock1!I24,Stock1!J24,"")} | Y24: {=_xlfn.XLOOKUP("Screen Protector for Android Phone and Other",Stock1!B24,Stock1!I24,"")} | Z24: {=_xlfn.XLOOKUP("Screen Protector for Galaxy Phone",Stock1!B24,Stock1!I24,"")} | AA24: {=_xlfn.XLOOKUP("Screen Protector for Galaxy Tab",Stock1!B24,Stock1!I24,"")} | AB24: =TEXTJOIN(,,Y24,Z24,AA24) | AC24: {=_xlfn.XLOOKUP(AB24,Stock1!I24,Stock1!F24,"")} | AD24: {=_xlfn.XLOOKUP(AB24,Stock1!I24,Stock1!J24,"")} | AE24: {=_xlfn.XLOOKUP("Storage",Stock1!B24,Stock1!I24,"")} | AF24: {=_xlfn.XLOOKUP(AE24,Stock1!I24,Stock1!F24,"")} | AG24: {=_xlfn.XLOOKUP(AE24,Stock1!I24,Stock1!J24,"")}
H25: [CS]Focus TG FF SL Samsung Galaxy S26 Ultra | I25: 8859703437475 | J25: {=IFERROR(_xlfn.XLOOKUP(I25,Stock1!F:F,Stock1!E:E,""),"")} -> 490 | K25: {=IFERROR(_xlfn.XLOOKUP(I25,Incentive!B:B,Incentive!E:E,""),"")} | L25: =IFERROR(VLOOKUP(I25,Stock1!F:J,5,False),"") -> 15 | M25: =IFERROR(VLOOKUP(I25,Stock2!F:J,5,False),"") -> 33 | R25: {=IFERROR(_xlfn.XLOOKUP(Q25,Stock1!F:F,Stock1!E:E,""),"")} | S25: =IFERROR(VLOOKUP(Q25,Stock1!F:J,5,False),"") | T25: =IFERROR(VLOOKUP(Q25,Stock2!F:J,5,False),"") | V25: {=_xlfn.XLOOKUP("Charger",Stock1!B25,Stock1!I25,"")} | W25: {=_xlfn.XLOOKUP(V25,Stock1!I25,Stock1!F25,"")} | X25: {=_xlfn.XLOOKUP(V25,Stock1!I25,Stock1!J25,"")} | Y25: {=_xlfn.XLOOKUP("Screen Protector for Android Phone and Other",Stock1!B25,Stock1!I25,"")} | Z25: {=_xlfn.XLOOKUP("Screen Protector for Galaxy Phone",Stock1!B25,Stock1!I25,"")} | AA25: {=_xlfn.XLOOKUP("Screen Protector for Galaxy Tab",Stock1!B25,Stock1!I25,"")} | AB25: =TEXTJOIN(,,Y25,Z25,AA25) | AC25: {=_xlfn.XLOOKUP(AB25,Stock1!I25,Stock1!F25,"")} | AD25: {=_xlfn.XLOOKUP(AB25,Stock1!I25,Stock1!J25,"")} | AE25: {=_xlfn.XLOOKUP("Storage",Stock1!B25,Stock1!I25,"")} | AF25: {=_xlfn.XLOOKUP(AE25,Stock1!I25,Stock1!F25,"")} | AG25: {=_xlfn.XLOOKUP(AE25,Stock1!I25,Stock1!J25,"")}
H26: [CS]Focus TG FF SL PV Samsung Galaxy S26 Ultra | I26: 8859703437482 | J26: {=IFERROR(_xlfn.XLOOKUP(I26,Stock1!F:F,Stock1!E:E,""),"")} -> 690 | K26: {=IFERROR(_xlfn.XLOOKUP(I26,Incentive!B:B,Incentive!E:E,""),"")} | L26: =IFERROR(VLOOKUP(I26,Stock1!F:J,5,False),"") -> 5 | M26: =IFERROR(VLOOKUP(I26,Stock2!F:J,5,False),"") -> 10 | R26: {=IFERROR(_xlfn.XLOOKUP(Q26,Stock1!F:F,Stock1!E:E,""),"")} | S26: =IFERROR(VLOOKUP(Q26,Stock1!F:J,5,False),"") | T26: =IFERROR(VLOOKUP(Q26,Stock2!F:J,5,False),"") | V26: {=_xlfn.XLOOKUP("Charger",Stock1!B26,Stock1!I26,"")} | W26: {=_xlfn.XLOOKUP(V26,Stock1!I26,Stock1!F26,"")} | X26: {=_xlfn.XLOOKUP(V26,Stock1!I26,Stock1!J26,"")} | Y26: {=_xlfn.XLOOKUP("Screen Protector for Android Phone and Other",Stock1!B26,Stock1!I26,"")} | Z26: {=_xlfn.XLOOKUP("Screen Protector for Galaxy Phone",Stock1!B26,Stock1!I26,"")} | AA26: {=_xlfn.XLOOKUP("Screen Protector for Galaxy Tab",Stock1!B26,Stock1!I26,"")} | AB26: =TEXTJOIN(,,Y26,Z26,AA26) | AC26: {=_xlfn.XLOOKUP(AB26,Stock1!I26,Stock1!F26,"")} | AD26: {=_xlfn.XLOOKUP(AB26,Stock1!I26,Stock1!J26,"")} | AE26: {=_xlfn.XLOOKUP("Storage",Stock1!B26,Stock1!I26,"")} | AF26: {=_xlfn.XLOOKUP(AE26,Stock1!I26,Stock1!F26,"")} | AG26: {=_xlfn.XLOOKUP(AE26,Stock1!I26,Stock1!J26,"")}
H27: [CS]Focus TG FF SL MT Samsung Galaxy S26 Ultra | I27: 8859703437499 | J27: {=IFERROR(_xlfn.XLOOKUP(I27,Stock1!F:F,Stock1!E:E,""),"")} -> 690 | K27: {=IFERROR(_xlfn.XLOOKUP(I27,Incentive!B:B,Incentive!E:E,""),"")} | L27: =IFERROR(VLOOKUP(I27,Stock1!F:J,5,False),"") -> 6 | M27: =IFERROR(VLOOKUP(I27,Stock2!F:J,5,False),"") -> 5 | R27: {=IFERROR(_xlfn.XLOOKUP(Q27,Stock1!F:F,Stock1!E:E,""),"")} | S27: =IFERROR(VLOOKUP(Q27,Stock1!F:J,5,False),"") | T27: =IFERROR(VLOOKUP(Q27,Stock2!F:J,5,False),"") | V27: {=_xlfn.XLOOKUP("Charger",Stock1!B27,Stock1!I27,"")} | W27: {=_xlfn.XLOOKUP(V27,Stock1!I27,Stock1!F27,"")} | X27: {=_xlfn.XLOOKUP(V27,Stock1!I27,Stock1!J27,"")} | Y27: {=_xlfn.XLOOKUP("Screen Protector for Android Phone and Other",Stock1!B27,Stock1!I27,"")} | Z27: {=_xlfn.XLOOKUP("Screen Protector for Galaxy Phone",Stock1!B27,Stock1!I27,"")} | AA27: {=_xlfn.XLOOKUP("Screen Protector for Galaxy Tab",Stock1!B27,Stock1!I27,"")} | AB27: =TEXTJOIN(,,Y27,Z27,AA27) | AC27: {=_xlfn.XLOOKUP(AB27,Stock1!I27,Stock1!F27,"")} | AD27: {=_xlfn.XLOOKUP(AB27,Stock1!I27,Stock1!J27,"")} | AE27: {=_xlfn.XLOOKUP("Storage",Stock1!B27,Stock1!I27,"")} | AF27: {=_xlfn.XLOOKUP(AE27,Stock1!I27,Stock1!F27,"")} | AG27: {=_xlfn.XLOOKUP(AE27,Stock1!I27,Stock1!J27,"")}
H28: [CS]Focus TG FF UG SL Samsung Galaxy S26 Ultra | I28: 8859703437581 | J28: {=IFERROR(_xlfn.XLOOKUP(I28,Stock1!F:F,Stock1!E:E,""),"")} -> 890 | K28: {=IFERROR(_xlfn.XLOOKUP(I28,Incentive!B:B,Incentive!E:E,""),"")} | L28: =IFERROR(VLOOKUP(I28,Stock1!F:J,5,False),"") -> 2 | M28: =IFERROR(VLOOKUP(I28,Stock2!F:J,5,False),"") -> 8 | R28: {=IFERROR(_xlfn.XLOOKUP(Q28,Stock1!F:F,Stock1!E:E,""),"")} | S28: =IFERROR(VLOOKUP(Q28,Stock1!F:J,5,False),"") | T28: =IFERROR(VLOOKUP(Q28,Stock2!F:J,5,False),"") | V28: {=_xlfn.XLOOKUP("Charger",Stock1!B28,Stock1!I28,"")} | W28: {=_xlfn.XLOOKUP(V28,Stock1!I28,Stock1!F28,"")} | X28: {=_xlfn.XLOOKUP(V28,Stock1!I28,Stock1!J28,"")} | Y28: {=_xlfn.XLOOKUP("Screen Protector for Android Phone and Other",Stock1!B28,Stock1!I28,"")} | Z28: {=_xlfn.XLOOKUP("Screen Protector for Galaxy Phone",Stock1!B28,Stock1!I28,"")} | AA28: {=_xlfn.XLOOKUP("Screen Protector for Galaxy Tab",Stock1!B28,Stock1!I28,"")} | AB28: =TEXTJOIN(,,Y28,Z28,AA28) | AC28: {=_xlfn.XLOOKUP(AB28,Stock1!I28,Stock1!F28,"")} | AD28: {=_xlfn.XLOOKUP(AB28,Stock1!I28,Stock1!J28,"")} | AE28: {=_xlfn.XLOOKUP("Storage",Stock1!B28,Stock1!I28,"")} | AF28: {=_xlfn.XLOOKUP(AE28,Stock1!I28,Stock1!F28,"")} | AG28: {=_xlfn.XLOOKUP(AE28,Stock1!I28,Stock1!J28,"")}
H29: [CS]Focus TG FF Samsung Galaxy S26 FE Black | I29: 8859703446620 | J29: {=IFERROR(_xlfn.XLOOKUP(I29,Stock1!F:F,Stock1!E:E,""),"")} -> 249 | K29: {=IFERROR(_xlfn.XLOOKUP(I29,Incentive!B:B,Incentive!E:E,""),"")} | L29: =IFERROR(VLOOKUP(I29,Stock1!F:J,5,False),"") -> 5 | M29: =IFERROR(VLOOKUP(I29,Stock2!F:J,5,False),"") -> 4 | R29: {=IFERROR(_xlfn.XLOOKUP(Q29,Stock1!F:F,Stock1!E:E,""),"")} | S29: =IFERROR(VLOOKUP(Q29,Stock1!F:J,5,False),"") | T29: =IFERROR(VLOOKUP(Q29,Stock2!F:J,5,False),"") | V29: {=_xlfn.XLOOKUP("Charger",Stock1!B29,Stock1!I29,"")} | W29: {=_xlfn.XLOOKUP(V29,Stock1!I29,Stock1!F29,"")} | X29: {=_xlfn.XLOOKUP(V29,Stock1!I29,Stock1!J29,"")} | Y29: {=_xlfn.XLOOKUP("Screen Protector for Android Phone and Other",Stock1!B29,Stock1!I29,"")} | Z29: {=_xlfn.XLOOKUP("Screen Protector for Galaxy Phone",Stock1!B29,Stock1!I29,"")} | AA29: {=_xlfn.XLOOKUP("Screen Protector for Galaxy Tab",Stock1!B29,Stock1!I29,"")} | AB29: =TEXTJOIN(,,Y29,Z29,AA29) | AC29: {=_xlfn.XLOOKUP(AB29,Stock1!I29,Stock1!F29,"")} | AD29: {=_xlfn.XLOOKUP(AB29,Stock1!I29,Stock1!J29,"")} | AE29: {=_xlfn.XLOOKUP("Storage",Stock1!B29,Stock1!I29,"")} | AF29: {=_xlfn.XLOOKUP(AE29,Stock1!I29,Stock1!F29,"")} | AG29: {=_xlfn.XLOOKUP(AE29,Stock1!I29,Stock1!J29,"")}
H30: [CS]Hishield Tempered Glass FC 2.5D Samsung S26 | I30: 8859216829019 | J30: {=IFERROR(_xlfn.XLOOKUP(I30,Stock1!F:F,Stock1!E:E,""),"")} -> 490 | K30: {=IFERROR(_xlfn.XLOOKUP(I30,Incentive!B:B,Incentive!E:E,""),"")} | L30: =IFERROR(VLOOKUP(I30,Stock1!F:J,5,False),"") -> 2 | M30: =IFERROR(VLOOKUP(I30,Stock2!F:J,5,False),"") -> 8 | R30: {=IFERROR(_xlfn.XLOOKUP(Q30,Stock1!F:F,Stock1!E:E,""),"")} | S30: =IFERROR(VLOOKUP(Q30,Stock1!F:J,5,False),"") | T30: =IFERROR(VLOOKUP(Q30,Stock2!F:J,5,False),"") | V30: {=_xlfn.XLOOKUP("Charger",Stock1!B30,Stock1!I30,"")} | W30: {=_xlfn.XLOOKUP(V30,Stock1!I30,Stock1!F30,"")} | X30: {=_xlfn.XLOOKUP(V30,Stock1!I30,Stock1!J30,"")} | Y30: {=_xlfn.XLOOKUP("Screen Protector for Android Phone and Other",Stock1!B30,Stock1!I30,"")} | Z30: {=_xlfn.XLOOKUP("Screen Protector for Galaxy Phone",Stock1!B30,Stock1!I30,"")} | AA30: {=_xlfn.XLOOKUP("Screen Protector for Galaxy Tab",Stock1!B30,Stock1!I30,"")} | AB30: =TEXTJOIN(,,Y30,Z30,AA30) | AC30: {=_xlfn.XLOOKUP(AB30,Stock1!I30,Stock1!F30,"")} | AD30: {=_xlfn.XLOOKUP(AB30,Stock1!I30,Stock1!J30,"")} | AE30: {=_xlfn.XLOOKUP("Storage",Stock1!B30,Stock1!I30,"")} | AF30: {=_xlfn.XLOOKUP(AE30,Stock1!I30,Stock1!F30,"")} | AG30: {=_xlfn.XLOOKUP(AE30,Stock1!I30,Stock1!J30,"")}
H31: [CS]Hishield Tempered Glass FC 2.5D Samsung S26 Plus | I31: 8859216829026 | J31: {=IFERROR(_xlfn.XLOOKUP(I31,Stock1!F:F,Stock1!E:E,""),"")} -> 490 | K31: {=IFERROR(_xlfn.XLOOKUP(I31,Incentive!B:B,Incentive!E:E,""),"")} | L31: =IFERROR(VLOOKUP(I31,Stock1!F:J,5,False),"") -> 5 | M31: =IFERROR(VLOOKUP(I31,Stock2!F:J,5,False),"") -> 8 | R31: {=IFERROR(_xlfn.XLOOKUP(Q31,Stock1!F:F,Stock1!E:E,""),"")} | S31: =IFERROR(VLOOKUP(Q31,Stock1!F:J,5,False),"") | T31: =IFERROR(VLOOKUP(Q31,Stock2!F:J,5,False),"") | V31: {=_xlfn.XLOOKUP("Charger",Stock1!B31,Stock1!I31,"")} | W31: {=_xlfn.XLOOKUP(V31,Stock1!I31,Stock1!F31,"")} | X31: {=_xlfn.XLOOKUP(V31,Stock1!I31,Stock1!J31,"")} | Y31: {=_xlfn.XLOOKUP("Screen Protector for Android Phone and Other",Stock1!B31,Stock1!I31,"")} | Z31: {=_xlfn.XLOOKUP("Screen Protector for Galaxy Phone",Stock1!B31,Stock1!I31,"")} | AA31: {=_xlfn.XLOOKUP("Screen Protector for Galaxy Tab",Stock1!B31,Stock1!I31,"")} | AB31: =TEXTJOIN(,,Y31,Z31,AA31) | AC31: {=_xlfn.XLOOKUP(AB31,Stock1!I31,Stock1!F31,"")} | AD31: {=_xlfn.XLOOKUP(AB31,Stock1!I31,Stock1!J31,"")} | AE31: {=_xlfn.XLOOKUP("Storage",Stock1!B31,Stock1!I31,"")} | AF31: {=_xlfn.XLOOKUP(AE31,Stock1!I31,Stock1!F31,"")} | AG31: {=_xlfn.XLOOKUP(AE31,Stock1!I31,Stock1!J31,"")}
... H44: [CS]Hishield Tempered Glass 2.5D Clear Samsung Z Fold8 Ultra | I44: 8859216860326 | J44: {=IFERROR(_xlfn.XLOOKUP(I44,Stock1!F:F,Stock1!E:E,""),"")} -> 590 | K44: {=IFERROR(_xlfn.XLOOKUP(I44,Incentive!B:B,Incentive!E:E,""),"")} | L44: =IFERROR(VLOOKUP(I44,Stock1!F:J,5,False),"") -> 29 | M44: =IFERROR(VLOOKUP(I44,Stock2!F:J,5,False),"") | R44: {=IFERROR(_xlfn.XLOOKUP(Q44,Stock1!F:F,Stock1!E:E,""),"")} | S44: =IFERROR(VLOOKUP(Q44,Stock1!F:J,5,False),"") | T44: =IFERROR(VLOOKUP(Q44,Stock2!F:J,5,False),"") | V44: {=_xlfn.XLOOKUP("Charger",Stock1!B44,Stock1!I44,"")} | W44: {=_xlfn.XLOOKUP(V44,Stock1!I44,Stock1!F44,"")} | X44: {=_xlfn.XLOOKUP(V44,Stock1!I44,Stock1!J44,"")} | Y44: {=_xlfn.XLOOKUP("Screen Protector for Android Phone and Other",Stock1!B44,Stock1!I44,"")} | Z44: {=_xlfn.XLOOKUP("Screen Protector for Galaxy Phone",Stock1!B44,Stock1!I44,"")} | AA44: {=_xlfn.XLOOKUP("Screen Protector for Galaxy Tab",Stock1!B44,Stock1!I44,"")} | AB44: =TEXTJOIN(,,Y44,Z44,AA44) | AC44: {=_xlfn.XLOOKUP(AB44,Stock1!I44,Stock1!F44,"")} | AD44: {=_xlfn.XLOOKUP(AB44,Stock1!I44,Stock1!J44,"")} | AE44: {=_xlfn.XLOOKUP("Storage",Stock1!B44,Stock1!I44,"")} | AF44: {=_xlfn.XLOOKUP(AE44,Stock1!I44,Stock1!F44,"")} | AG44: {=_xlfn.XLOOKUP(AE44,Stock1!I44,Stock1!J44,"")}
H45: [CS]Focus TG UC Samsung Galaxy Tab A9 8.7 | I45: 8859703426066 | J45: {=IFERROR(_xlfn.XLOOKUP(I45,Stock1!F:F,Stock1!E:E,""),"")} -> 590 | K45: {=IFERROR(_xlfn.XLOOKUP(I45,Incentive!B:B,Incentive!E:E,""),"")} -> 20 | L45: =IFERROR(VLOOKUP(I45,Stock1!F:J,5,False),"") -> 5 | M45: =IFERROR(VLOOKUP(I45,Stock2!F:J,5,False),"") -> 2 | R45: {=IFERROR(_xlfn.XLOOKUP(Q45,Stock1!F:F,Stock1!E:E,""),"")} | T45: =IFERROR(VLOOKUP(Q45,Stock2!F:J,5,False),"") | V45: {=_xlfn.XLOOKUP("Charger",Stock1!B45,Stock1!I45,"")} | W45: {=_xlfn.XLOOKUP(V45,Stock1!I45,Stock1!F45,"")} | X45: {=_xlfn.XLOOKUP(V45,Stock1!I45,Stock1!J45,"")} | Y45: {=_xlfn.XLOOKUP("Screen Protector for Android Phone and Other",Stock1!B45,Stock1!I45,"")} | Z45: {=_xlfn.XLOOKUP("Screen Protector for Galaxy Phone",Stock1!B45,Stock1!I45,"")} | AA45: {=_xlfn.XLOOKUP("Screen Protector for Galaxy Tab",Stock1!B45,Stock1!I45,"")} | AB45: =TEXTJOIN(,,Y45,Z45,AA45) | AC45: {=_xlfn.XLOOKUP(AB45,Stock1!I45,Stock1!F45,"")} | AD45: {=_xlfn.XLOOKUP(AB45,Stock1!I45,Stock1!J45,"")} | AE45: {=_xlfn.XLOOKUP("Storage",Stock1!B45,Stock1!I45,"")} | AF45: {=_xlfn.XLOOKUP(AE45,Stock1!I45,Stock1!F45,"")} | AG45: {=_xlfn.XLOOKUP(AE45,Stock1!I45,Stock1!J45,"")}
H46: [CS]Focus TG UC Samsung Galaxy Tab A9 Plus 11 | I46: 8859703426073 | J46: {=IFERROR(_xlfn.XLOOKUP(I46,Stock1!F:F,Stock1!E:E,""),"")} -> 690 | K46: {=IFERROR(_xlfn.XLOOKUP(I46,Incentive!B:B,Incentive!E:E,""),"")} -> 20 | L46: =IFERROR(VLOOKUP(I46,Stock1!F:J,5,False),"") -> 6 | M46: =IFERROR(VLOOKUP(I46,Stock2!F:J,5,False),"") -> 4 | V46: {=_xlfn.XLOOKUP("Charger",Stock1!B46,Stock1!I46,"")} | W46: {=_xlfn.XLOOKUP(V46,Stock1!I46,Stock1!F46,"")} | X46: {=_xlfn.XLOOKUP(V46,Stock1!I46,Stock1!J46,"")} | Y46: {=_xlfn.XLOOKUP("Screen Protector for Android Phone and Other",Stock1!B46,Stock1!I46,"")} | Z46: {=_xlfn.XLOOKUP("Screen Protector for Galaxy Phone",Stock1!B46,Stock1!I46,"")} | AA46: {=_xlfn.XLOOKUP("Screen Protector for Galaxy Tab",Stock1!B46,Stock1!I46,"")} | AB46: =TEXTJOIN(,,Y46,Z46,AA46) | AC46: {=_xlfn.XLOOKUP(AB46,Stock1!I46,Stock1!F46,"")} | AD46: {=_xlfn.XLOOKUP(AB46,Stock1!I46,Stock1!J46,"")} | AE46: {=_xlfn.XLOOKUP("Storage",Stock1!B46,Stock1!I46,"")} | AF46: {=_xlfn.XLOOKUP(AE46,Stock1!I46,Stock1!F46,"")} | AG46: {=_xlfn.XLOOKUP(AE46,Stock1!I46,Stock1!J46,"")}
H47: [CS]Focus TG UC Samsung Galaxy Tab S10 FE Plus 13.1 | I47: 8859703435204 | J47: {=IFERROR(_xlfn.XLOOKUP(I47,Stock1!F:F,Stock1!E:E,""),"")} -> 990 | K47: {=IFERROR(_xlfn.XLOOKUP(I47,Incentive!B:B,Incentive!E:E,""),"")} -> 30 | L47: =IFERROR(VLOOKUP(I47,Stock1!F:J,5,False),"") -> 6 | M47: =IFERROR(VLOOKUP(I47,Stock2!F:J,5,False),"") -> 2 | V47: {=_xlfn.XLOOKUP("Charger",Stock1!B47,Stock1!I47,"")} | W47: {=_xlfn.XLOOKUP(V47,Stock1!I47,Stock1!F47,"")} | X47: {=_xlfn.XLOOKUP(V47,Stock1!I47,Stock1!J47,"")} | Y47: {=_xlfn.XLOOKUP("Screen Protector for Android Phone and Other",Stock1!B47,Stock1!I47,"")} | Z47: {=_xlfn.XLOOKUP("Screen Protector for Galaxy Phone",Stock1!B47,Stock1!I47,"")} | AA47: {=_xlfn.XLOOKUP("Screen Protector for Galaxy Tab",Stock1!B47,Stock1!I47,"")} | AB47: =TEXTJOIN(,,Y47,Z47,AA47) | AC47: {=_xlfn.XLOOKUP(AB47,Stock1!I47,Stock1!F47,"")} | AD47: {=_xlfn.XLOOKUP(AB47,Stock1!I47,Stock1!J47,"")} | AE47: {=_xlfn.XLOOKUP("Storage",Stock1!B47,Stock1!I47,"")} | AF47: {=_xlfn.XLOOKUP(AE47,Stock1!I47,Stock1!F47,"")} | AG47: {=_xlfn.XLOOKUP(AE47,Stock1!I47,Stock1!J47,"")}
H48: [CS]HISHIELD TemperedGlass FC 2.5D Samsung Tab S10 Lite | I48: 8859216804085 | J48: {=IFERROR(_xlfn.XLOOKUP(I48,Stock1!F:F,Stock1!E:E,""),"")} -> 690 | K48: {=IFERROR(_xlfn.XLOOKUP(I48,Incentive!B:B,Incentive!E:E,""),"")} | L48: =IFERROR(VLOOKUP(I48,Stock1!F:J,5,False),"") -> 6 | M48: =IFERROR(VLOOKUP(I48,Stock2!F:J,5,False),"") -> 3 | V48: {=_xlfn.XLOOKUP("Charger",Stock1!B48,Stock1!I48,"")} | W48: {=_xlfn.XLOOKUP(V48,Stock1!I48,Stock1!F48,"")} | X48: {=_xlfn.XLOOKUP(V48,Stock1!I48,Stock1!J48,"")} | Y48: {=_xlfn.XLOOKUP("Screen Protector for Android Phone and Other",Stock1!B48,Stock1!I48,"")} | Z48: {=_xlfn.XLOOKUP("Screen Protector for Galaxy Phone",Stock1!B48,Stock1!I48,"")} | AA48: {=_xlfn.XLOOKUP("Screen Protector for Galaxy Tab",Stock1!B48,Stock1!I48,"")} | AB48: =TEXTJOIN(,,Y48,Z48,AA48) | AC48: {=_xlfn.XLOOKUP(AB48,Stock1!I48,Stock1!F48,"")} | AD48: {=_xlfn.XLOOKUP(AB48,Stock1!I48,Stock1!J48,"")} | AE48: {=_xlfn.XLOOKUP("Storage",Stock1!B48,Stock1!I48,"")} | AF48: {=_xlfn.XLOOKUP(AE48,Stock1!I48,Stock1!F48,"")} | AG48: {=_xlfn.XLOOKUP(AE48,Stock1!I48,Stock1!J48,"")}
H49: [CS]Focus TG UC Samsung Galaxy Tab S11 | I49: 8859703436669 | J49: {=IFERROR(_xlfn.XLOOKUP(I49,Stock1!F:F,Stock1!E:E,""),"")} -> 690 | K49: {=IFERROR(_xlfn.XLOOKUP(I49,Incentive!B:B,Incentive!E:E,""),"")} | L49: =IFERROR(VLOOKUP(I49,Stock1!F:J,5,False),"") -> 10 | M49: =IFERROR(VLOOKUP(I49,Stock2!F:J,5,False),"") -> 7 | V49: {=_xlfn.XLOOKUP("Charger",Stock1!B49,Stock1!I49,"")} | W49: {=_xlfn.XLOOKUP(V49,Stock1!I49,Stock1!F49,"")} | X49: {=_xlfn.XLOOKUP(V49,Stock1!I49,Stock1!J49,"")} | Y49: {=_xlfn.XLOOKUP("Screen Protector for Android Phone and Other",Stock1!B49,Stock1!I49,"")} | Z49: {=_xlfn.XLOOKUP("Screen Protector for Galaxy Phone",Stock1!B49,Stock1!I49,"")} | AA49: {=_xlfn.XLOOKUP("Screen Protector for Galaxy Tab",Stock1!B49,Stock1!I49,"")} | AB49: =TEXTJOIN(,,Y49,Z49,AA49) | AC49: {=_xlfn.XLOOKUP(AB49,Stock1!I49,Stock1!F49,"")} | AD49: {=_xlfn.XLOOKUP(AB49,Stock1!I49,Stock1!J49,"")} | AE49: {=_xlfn.XLOOKUP("Storage",Stock1!B49,Stock1!I49,"")} | AF49: {=_xlfn.XLOOKUP(AE49,Stock1!I49,Stock1!F49,"")} | AG49: {=_xlfn.XLOOKUP(AE49,Stock1!I49,Stock1!J49,"")}
H50: [CS]HISHIELD TemperedGlass FC 2.5D Samsung Tab S11 | I50: 8859216804108 | J50: {=IFERROR(_xlfn.XLOOKUP(I50,Stock1!F:F,Stock1!E:E,""),"")} -> 690 | K50: {=IFERROR(_xlfn.XLOOKUP(I50,Incentive!B:B,Incentive!E:E,""),"")} | L50: =IFERROR(VLOOKUP(I50,Stock1!F:J,5,False),"") -> 4 | M50: =IFERROR(VLOOKUP(I50,Stock2!F:J,5,False),"") -> 8 | V50: {=_xlfn.XLOOKUP("Charger",Stock1!B50,Stock1!I50,"")} | W50: {=_xlfn.XLOOKUP(V50,Stock1!I50,Stock1!F50,"")} | X50: {=_xlfn.XLOOKUP(V50,Stock1!I50,Stock1!J50,"")} | Y50: {=_xlfn.XLOOKUP("Screen Protector for Android Phone and Other",Stock1!B50,Stock1!I50,"")} | Z50: {=_xlfn.XLOOKUP("Screen Protector for Galaxy Phone",Stock1!B50,Stock1!I50,"")} | AA50: {=_xlfn.XLOOKUP("Screen Protector for Galaxy Tab",Stock1!B50,Stock1!I50,"")} | AB50: =TEXTJOIN(,,Y50,Z50,AA50) | AC50: {=_xlfn.XLOOKUP(AB50,Stock1!I50,Stock1!F50,"")} | AD50: {=_xlfn.XLOOKUP(AB50,Stock1!I50,Stock1!J50,"")} | AE50: {=_xlfn.XLOOKUP("Storage",Stock1!B50,Stock1!I50,"")} | AF50: {=_xlfn.XLOOKUP(AE50,Stock1!I50,Stock1!F50,"")} | AG50: {=_xlfn.XLOOKUP(AE50,Stock1!I50,Stock1!J50,"")}
H51: [CS]Focus TG UC Samsung Galaxy Tab S11 Ultra | I51: 8859703436690 | J51: {=IFERROR(_xlfn.XLOOKUP(I51,Stock1!F:F,Stock1!E:E,""),"")} -> 990 | K51: {=IFERROR(_xlfn.XLOOKUP(I51,Incentive!B:B,Incentive!E:E,""),"")} | L51: =IFERROR(VLOOKUP(I51,Stock1!F:J,5,False),"") -> 1 | M51: =IFERROR(VLOOKUP(I51,Stock2!F:J,5,False),"") -> 2 | V51: {=_xlfn.XLOOKUP("Charger",Stock1!B51,Stock1!I51,"")} | W51: {=_xlfn.XLOOKUP(V51,Stock1!I51,Stock1!F51,"")} | X51: {=_xlfn.XLOOKUP(V51,Stock1!I51,Stock1!J51,"")} | Y51: {=_xlfn.XLOOKUP("Screen Protector for Android Phone and Other",Stock1!B51,Stock1!I51,"")} | Z51: {=_xlfn.XLOOKUP("Screen Protector for Galaxy Phone",Stock1!B51,Stock1!I51,"")} | AA51: {=_xlfn.XLOOKUP("Screen Protector for Galaxy Tab",Stock1!B51,Stock1!I51,"")} | AB51: =TEXTJOIN(,,Y51,Z51,AA51) | AC51: {=_xlfn.XLOOKUP(AB51,Stock1!I51,Stock1!F51,"")} | AD51: {=_xlfn.XLOOKUP(AB51,Stock1!I51,Stock1!J51,"")} | AE51: {=_xlfn.XLOOKUP("Storage",Stock1!B51,Stock1!I51,"")} | AF51: {=_xlfn.XLOOKUP(AE51,Stock1!I51,Stock1!F51,"")} | AG51: {=_xlfn.XLOOKUP(AE51,Stock1!I51,Stock1!J51,"")}
H52: [CS]Hishield TemperedGlass 0.33mm Tab S11 Ultra | I52: 8859216804122 | J52: {=IFERROR(_xlfn.XLOOKUP(I52,Stock1!F:F,Stock1!E:E,""),"")} -> 890 | K52: {=IFERROR(_xlfn.XLOOKUP(I52,Incentive!B:B,Incentive!E:E,""),"")} | L52: =IFERROR(VLOOKUP(I52,Stock1!F:J,5,False),"") -> 4 | M52: =IFERROR(VLOOKUP(I52,Stock2!F:J,5,False),"") -> 3 | V52: {=_xlfn.XLOOKUP("Charger",Stock1!B52,Stock1!I52,"")} | W52: {=_xlfn.XLOOKUP(V52,Stock1!I52,Stock1!F52,"")} | X52: {=_xlfn.XLOOKUP(V52,Stock1!I52,Stock1!J52,"")} | Y52: {=_xlfn.XLOOKUP("Screen Protector for Android Phone and Other",Stock1!B52,Stock1!I52,"")} | Z52: {=_xlfn.XLOOKUP("Screen Protector for Galaxy Phone",Stock1!B52,Stock1!I52,"")} | AA52: {=_xlfn.XLOOKUP("Screen Protector for Galaxy Tab",Stock1!B52,Stock1!I52,"")} | AB52: =TEXTJOIN(,,Y52,Z52,AA52) | AC52: {=_xlfn.XLOOKUP(AB52,Stock1!I52,Stock1!F52,"")} | AD52: {=_xlfn.XLOOKUP(AB52,Stock1!I52,Stock1!J52,"")} | AE52: {=_xlfn.XLOOKUP("Storage",Stock1!B52,Stock1!I52,"")} | AF52: {=_xlfn.XLOOKUP(AE52,Stock1!I52,Stock1!F52,"")} | AG52: {=_xlfn.XLOOKUP(AE52,Stock1!I52,Stock1!J52,"")}
H53: [CS]Focus TG UC Samsung Galaxy Tab S8 Plus 12.4 | I53: 8859703400226 | J53: {=IFERROR(_xlfn.XLOOKUP(I53,Stock1!F:F,Stock1!E:E,""),"")} -> 990 | K53: {=IFERROR(_xlfn.XLOOKUP(I53,Incentive!B:B,Incentive!E:E,""),"")} -> 30 | L53: =IFERROR(VLOOKUP(I53,Stock1!F:J,5,False),"") -> 1 | M53: =IFERROR(VLOOKUP(I53,Stock2!F:J,5,False),"") -> 4 | V53: {=_xlfn.XLOOKUP("Charger",Stock1!B53,Stock1!I53,"")} | W53: {=_xlfn.XLOOKUP(V53,Stock1!I53,Stock1!F53,"")} | X53: {=_xlfn.XLOOKUP(V53,Stock1!I53,Stock1!J53,"")} | Y53: {=_xlfn.XLOOKUP("Screen Protector for Android Phone and Other",Stock1!B53,Stock1!I53,"")} | Z53: {=_xlfn.XLOOKUP("Screen Protector for Galaxy Phone",Stock1!B53,Stock1!I53,"")} | AA53: {=_xlfn.XLOOKUP("Screen Protector for Galaxy Tab",Stock1!B53,Stock1!I53,"")} | AB53: =TEXTJOIN(,,Y53,Z53,AA53) | AC53: {=_xlfn.XLOOKUP(AB53,Stock1!I53,Stock1!F53,"")} | AD53: {=_xlfn.XLOOKUP(AB53,Stock1!I53,Stock1!J53,"")} | AE53: {=_xlfn.XLOOKUP("Storage",Stock1!B53,Stock1!I53,"")} | AF53: {=_xlfn.XLOOKUP(AE53,Stock1!I53,Stock1!F53,"")} | AG53: {=_xlfn.XLOOKUP(AE53,Stock1!I53,Stock1!J53,"")}
H54: #REF! | I54: #REF! | J54: {=IFERROR(_xlfn.XLOOKUP(I54,Stock1!F:F,Stock1!E:E,""),"")} | K54: {=IFERROR(_xlfn.XLOOKUP(I54,Incentive!B:B,Incentive!E:E,""),"")} | L54: =IFERROR(VLOOKUP(I54,Stock1!F:J,5,False),"") | M54: =IFERROR(VLOOKUP(I54,Stock2!F:J,5,False),"") | V54: {=_xlfn.XLOOKUP("Charger",Stock1!B54,Stock1!I54,"")} | W54: {=_xlfn.XLOOKUP(V54,Stock1!I54,Stock1!F54,"")} | X54: {=_xlfn.XLOOKUP(V54,Stock1!I54,Stock1!J54,"")} | Y54: {=_xlfn.XLOOKUP("Screen Protector for Android Phone and Other",Stock1!B54,Stock1!I54,"")} | Z54: {=_xlfn.XLOOKUP("Screen Protector for Galaxy Phone",Stock1!B54,Stock1!I54,"")} | AA54: {=_xlfn.XLOOKUP("Screen Protector for Galaxy Tab",Stock1!B54,Stock1!I54,"")} | AB54: =TEXTJOIN(,,Y54,Z54,AA54) | AC54: {=_xlfn.XLOOKUP(AB54,Stock1!I54,Stock1!F54,"")} | AD54: {=_xlfn.XLOOKUP(AB54,Stock1!I54,Stock1!J54,"")} | AE54: {=_xlfn.XLOOKUP("Storage",Stock1!B54,Stock1!I54,"")} | AF54: {=_xlfn.XLOOKUP(AE54,Stock1!I54,Stock1!F54,"")} | AG54: {=_xlfn.XLOOKUP(AE54,Stock1!I54,Stock1!J54,"")}
J55: {=IFERROR(_xlfn.XLOOKUP(I55,Stock1!F:F,Stock1!E:E,""),"")} | K55: {=IFERROR(_xlfn.XLOOKUP(I55,Incentive!B:B,Incentive!E:E,""),"")} | L55: =IFERROR(VLOOKUP(I55,Stock1!F:J,5,False),"") | M55: =IFERROR(VLOOKUP(I55,Stock2!F:J,5,False),"") | V55: {=_xlfn.XLOOKUP("Charger",Stock1!B55,Stock1!I55,"")} | W55: {=_xlfn.XLOOKUP(V55,Stock1!I55,Stock1!F55,"")} | X55: {=_xlfn.XLOOKUP(V55,Stock1!I55,Stock1!J55,"")} | Y55: {=_xlfn.XLOOKUP("Screen Protector for Android Phone and Other",Stock1!B55,Stock1!I55,"")} | Z55: {=_xlfn.XLOOKUP("Screen Protector for Galaxy Phone",Stock1!B55,Stock1!I55,"")} | AA55: {=_xlfn.XLOOKUP("Screen Protector for Galaxy Tab",Stock1!B55,Stock1!I55,"")} | AB55: =TEXTJOIN(,,Y55,Z55,AA55) | AC55: {=_xlfn.XLOOKUP(AB55,Stock1!I55,Stock1!F55,"")} | AD55: {=_xlfn.XLOOKUP(AB55,Stock1!I55,Stock1!J55,"")} | AE55: {=_xlfn.XLOOKUP("Storage",Stock1!B55,Stock1!I55,"")} | AF55: {=_xlfn.XLOOKUP(AE55,Stock1!I55,Stock1!F55,"")} | AG55: {=_xlfn.XLOOKUP(AE55,Stock1!I55,Stock1!J55,"")}
J56: {=IFERROR(_xlfn.XLOOKUP(I56,Stock1!F:F,Stock1!E:E,""),"")} | K56: {=IFERROR(_xlfn.XLOOKUP(I56,Incentive!B:B,Incentive!E:E,""),"")} | L56: =IFERROR(VLOOKUP(I56,Stock1!F:J,5,False),"") | M56: =IFERROR(VLOOKUP(I56,Stock2!F:J,5,False),"") | V56: {=_xlfn.XLOOKUP("Charger",Stock1!B56,Stock1!I56,"")} | W56: {=_xlfn.XLOOKUP(V56,Stock1!I56,Stock1!F56,"")} | X56: {=_xlfn.XLOOKUP(V56,Stock1!I56,Stock1!J56,"")} | Y56: {=_xlfn.XLOOKUP("Screen Protector for Android Phone and Other",Stock1!B56,Stock1!I56,"")} | Z56: {=_xlfn.XLOOKUP("Screen Protector for Galaxy Phone",Stock1!B56,Stock1!I56,"")} | AA56: {=_xlfn.XLOOKUP("Screen Protector for Galaxy Tab",Stock1!B56,Stock1!I56,"")} | AB56: =TEXTJOIN(,,Y56,Z56,AA56) | AC56: {=_xlfn.XLOOKUP(AB56,Stock1!I56,Stock1!F56,"")} | AD56: {=_xlfn.XLOOKUP(AB56,Stock1!I56,Stock1!J56,"")} | AE56: {=_xlfn.XLOOKUP("Storage",Stock1!B56,Stock1!I56,"")} | AF56: {=_xlfn.XLOOKUP(AE56,Stock1!I56,Stock1!F56,"")} | AG56: {=_xlfn.XLOOKUP(AE56,Stock1!I56,Stock1!J56,"")}
J57: {=IFERROR(_xlfn.XLOOKUP(I57,Stock1!F:F,Stock1!E:E,""),"")} | K57: {=IFERROR(_xlfn.XLOOKUP(I57,Incentive!B:B,Incentive!E:E,""),"")} | L57: =IFERROR(VLOOKUP(I57,Stock1!F:J,5,False),"") | M57: =IFERROR(VLOOKUP(I57,Stock2!F:J,5,False),"") | V57: {=_xlfn.XLOOKUP("Charger",Stock1!B57,Stock1!I57,"")} | W57: {=_xlfn.XLOOKUP(V57,Stock1!I57,Stock1!F57,"")} | X57: {=_xlfn.XLOOKUP(V57,Stock1!I57,Stock1!J57,"")} | Y57: {=_xlfn.XLOOKUP("Screen Protector for Android Phone and Other",Stock1!B57,Stock1!I57,"")} | Z57: {=_xlfn.XLOOKUP("Screen Protector for Galaxy Phone",Stock1!B57,Stock1!I57,"")} | AA57: {=_xlfn.XLOOKUP("Screen Protector for Galaxy Tab",Stock1!B57,Stock1!I57,"")} | AB57: =TEXTJOIN(,,Y57,Z57,AA57) | AC57: {=_xlfn.XLOOKUP(AB57,Stock1!I57,Stock1!F57,"")} | AD57: {=_xlfn.XLOOKUP(AB57,Stock1!I57,Stock1!J57,"")} | AE57: {=_xlfn.XLOOKUP("Storage",Stock1!B57,Stock1!I57,"")} | AF57: {=_xlfn.XLOOKUP(AE57,Stock1!I57,Stock1!F57,"")} | AG57: {=_xlfn.XLOOKUP(AE57,Stock1!I57,Stock1!J57,"")}
J58: {=IFERROR(_xlfn.XLOOKUP(I58,Stock1!F:F,Stock1!E:E,""),"")} | K58: {=IFERROR(_xlfn.XLOOKUP(I58,Incentive!B:B,Incentive!E:E,""),"")} | L58: =IFERROR(VLOOKUP(I58,Stock1!F:J,5,False),"") | M58: =IFERROR(VLOOKUP(I58,Stock2!F:J,5,False),"") | V58: {=_xlfn.XLOOKUP("Charger",Stock1!B58,Stock1!I58,"")} | W58: {=_xlfn.XLOOKUP(V58,Stock1!I58,Stock1!F58,"")} | X58: {=_xlfn.XLOOKUP(V58,Stock1!I58,Stock1!J58,"")} | Y58: {=_xlfn.XLOOKUP("Screen Protector for Android Phone and Other",Stock1!B58,Stock1!I58,"")} | Z58: {=_xlfn.XLOOKUP("Screen Protector for Galaxy Phone",Stock1!B58,Stock1!I58,"")} | AA58: {=_xlfn.XLOOKUP("Screen Protector for Galaxy Tab",Stock1!B58,Stock1!I58,"")} | AB58: =TEXTJOIN(,,Y58,Z58,AA58) | AC58: {=_xlfn.XLOOKUP(AB58,Stock1!I58,Stock1!F58,"")} | AD58: {=_xlfn.XLOOKUP(AB58,Stock1!I58,Stock1!J58,"")} | AE58: {=_xlfn.XLOOKUP("Storage",Stock1!B58,Stock1!I58,"")} | AF58: {=_xlfn.XLOOKUP(AE58,Stock1!I58,Stock1!F58,"")} | AG58: {=_xlfn.XLOOKUP(AE58,Stock1!I58,Stock1!J58,"")}
K59: {=IFERROR(_xlfn.XLOOKUP(I59,Incentive!B:B,Incentive!E:E,""),"")} | L59: =IFERROR(VLOOKUP(I59,Stock1!F:J,5,False),"") | M59: =IFERROR(VLOOKUP(I59,Stock2!F:J,5,False),"") | V59: {=_xlfn.XLOOKUP("Charger",Stock1!B59,Stock1!I59,"")} | W59: {=_xlfn.XLOOKUP(V59,Stock1!I59,Stock1!F59,"")} | X59: {=_xlfn.XLOOKUP(V59,Stock1!I59,Stock1!J59,"")} | Y59: {=_xlfn.XLOOKUP("Screen Protector for Android Phone and Other",Stock1!B59,Stock1!I59,"")} | Z59: {=_xlfn.XLOOKUP("Screen Protector for Galaxy Phone",Stock1!B59,Stock1!I59,"")} | AA59: {=_xlfn.XLOOKUP("Screen Protector for Galaxy Tab",Stock1!B59,Stock1!I59,"")} | AB59: =TEXTJOIN(,,Y59,Z59,AA59) | AC59: {=_xlfn.XLOOKUP(AB59,Stock1!I59,Stock1!F59,"")} | AD59: {=_xlfn.XLOOKUP(AB59,Stock1!I59,Stock1!J59,"")} | AE59: {=_xlfn.XLOOKUP("Storage",Stock1!B59,Stock1!I59,"")} | AF59: {=_xlfn.XLOOKUP(AE59,Stock1!I59,Stock1!F59,"")} | AG59: {=_xlfn.XLOOKUP(AE59,Stock1!I59,Stock1!J59,"")}
K60: {=IFERROR(_xlfn.XLOOKUP(I60,Incentive!B:B,Incentive!E:E,""),"")} | L60: =IFERROR(VLOOKUP(I60,Stock1!F:J,5,False),"") | M60: =IFERROR(VLOOKUP(I60,Stock2!F:J,5,False),"") | V60: {=_xlfn.XLOOKUP("Charger",Stock1!B60,Stock1!I60,"")} | W60: {=_xlfn.XLOOKUP(V60,Stock1!I60,Stock1!F60,"")} | X60: {=_xlfn.XLOOKUP(V60,Stock1!I60,Stock1!J60,"")} | Y60: {=_xlfn.XLOOKUP("Screen Protector for Android Phone and Other",Stock1!B60,Stock1!I60,"")} | Z60: {=_xlfn.XLOOKUP("Screen Protector for Galaxy Phone",Stock1!B60,Stock1!I60,"")} | AA60: {=_xlfn.XLOOKUP("Screen Protector for Galaxy Tab",Stock1!B60,Stock1!I60,"")} | AB60: =TEXTJOIN(,,Y60,Z60,AA60) | AC60: {=_xlfn.XLOOKUP(AB60,Stock1!I60,Stock1!F60,"")} | AD60: {=_xlfn.XLOOKUP(AB60,Stock1!I60,Stock1!J60,"")} | AE60: {=_xlfn.XLOOKUP("Storage",Stock1!B60,Stock1!I60,"")} | AF60: {=_xlfn.XLOOKUP(AE60,Stock1!I60,Stock1!F60,"")} | AG60: {=_xlfn.XLOOKUP(AE60,Stock1!I60,Stock1!J60,"")}
K61: {=IFERROR(_xlfn.XLOOKUP(I61,Incentive!B:B,Incentive!E:E,""),"")} | L61: =IFERROR(VLOOKUP(I61,Stock1!F:J,5,False),"") | M61: =IFERROR(VLOOKUP(I61,Stock2!F:J,5,False),"") | V61: {=_xlfn.XLOOKUP("Charger",Stock1!B61,Stock1!I61,"")} | W61: {=_xlfn.XLOOKUP(V61,Stock1!I61,Stock1!F61,"")} | X61: {=_xlfn.XLOOKUP(V61,Stock1!I61,Stock1!J61,"")} | Y61: {=_xlfn.XLOOKUP("Screen Protector for Android Phone and Other",Stock1!B61,Stock1!I61,"")} | Z61: {=_xlfn.XLOOKUP("Screen Protector for Galaxy Phone",Stock1!B61,Stock1!I61,"")} | AA61: {=_xlfn.XLOOKUP("Screen Protector for Galaxy Tab",Stock1!B61,Stock1!I61,"")} | AB61: =TEXTJOIN(,,Y61,Z61,AA61) | AC61: {=_xlfn.XLOOKUP(AB61,Stock1!I61,Stock1!F61,"")} | AD61: {=_xlfn.XLOOKUP(AB61,Stock1!I61,Stock1!J61,"")} | AE61: {=_xlfn.XLOOKUP("Storage",Stock1!B61,Stock1!I61,"")} | AF61: {=_xlfn.XLOOKUP(AE61,Stock1!I61,Stock1!F61,"")} | AG61: {=_xlfn.XLOOKUP(AE61,Stock1!I61,Stock1!J61,"")}
K62: {=IFERROR(_xlfn.XLOOKUP(I62,Incentive!B:B,Incentive!E:E,""),"")} | L62: =IFERROR(VLOOKUP(I62,Stock1!F:J,5,False),"") | M62: =IFERROR(VLOOKUP(I62,Stock2!F:J,5,False),"") | V62: {=_xlfn.XLOOKUP("Charger",Stock1!B62,Stock1!I62,"")} | W62: {=_xlfn.XLOOKUP(V62,Stock1!I62,Stock1!F62,"")} | X62: {=_xlfn.XLOOKUP(V62,Stock1!I62,Stock1!J62,"")} | Y62: {=_xlfn.XLOOKUP("Screen Protector for Android Phone and Other",Stock1!B62,Stock1!I62,"")} | Z62: {=_xlfn.XLOOKUP("Screen Protector for Galaxy Phone",Stock1!B62,Stock1!I62,"")} | AA62: {=_xlfn.XLOOKUP("Screen Protector for Galaxy Tab",Stock1!B62,Stock1!I62,"")} | AB62: =TEXTJOIN(,,Y62,Z62,AA62) | AC62: {=_xlfn.XLOOKUP(AB62,Stock1!I62,Stock1!F62,"")} | AD62: {=_xlfn.XLOOKUP(AB62,Stock1!I62,Stock1!J62,"")} | AE62: {=_xlfn.XLOOKUP("Storage",Stock1!B62,Stock1!I62,"")} | AF62: {=_xlfn.XLOOKUP(AE62,Stock1!I62,Stock1!F62,"")} | AG62: {=_xlfn.XLOOKUP(AE62,Stock1!I62,Stock1!J62,"")}
K63: {=IFERROR(_xlfn.XLOOKUP(I63,Incentive!B:B,Incentive!E:E,""),"")} | L63: =IFERROR(VLOOKUP(I63,Stock1!F:J,5,False),"") | M63: =IFERROR(VLOOKUP(I63,Stock2!F:J,5,False),"") | V63: {=_xlfn.XLOOKUP("Charger",Stock1!B63,Stock1!I63,"")} | W63: {=_xlfn.XLOOKUP(V63,Stock1!I63,Stock1!F63,"")} | X63: {=_xlfn.XLOOKUP(V63,Stock1!I63,Stock1!J63,"")} | Y63: {=_xlfn.XLOOKUP("Screen Protector for Android Phone and Other",Stock1!B63,Stock1!I63,"")} | Z63: {=_xlfn.XLOOKUP("Screen Protector for Galaxy Phone",Stock1!B63,Stock1!I63,"")} | AA63: {=_xlfn.XLOOKUP("Screen Protector for Galaxy Tab",Stock1!B63,Stock1!I63,"")} | AB63: =TEXTJOIN(,,Y63,Z63,AA63) | AC63: {=_xlfn.XLOOKUP(AB63,Stock1!I63,Stock1!F63,"")} | AD63: {=_xlfn.XLOOKUP(AB63,Stock1!I63,Stock1!J63,"")} | AE63: {=_xlfn.XLOOKUP("Storage",Stock1!B63,Stock1!I63,"")} | AF63: {=_xlfn.XLOOKUP(AE63,Stock1!I63,Stock1!F63,"")} | AG63: {=_xlfn.XLOOKUP(AE63,Stock1!I63,Stock1!J63,"")}
K64: {=IFERROR(_xlfn.XLOOKUP(I64,Incentive!B:B,Incentive!E:E,""),"")} | L64: =IFERROR(VLOOKUP(I64,Stock1!F:J,5,False),"") | M64: =IFERROR(VLOOKUP(I64,Stock2!F:J,5,False),"") | V64: {=_xlfn.XLOOKUP("Charger",Stock1!B64,Stock1!I64,"")} | W64: {=_xlfn.XLOOKUP(V64,Stock1!I64,Stock1!F64,"")} | X64: {=_xlfn.XLOOKUP(V64,Stock1!I64,Stock1!J64,"")} | Y64: {=_xlfn.XLOOKUP("Screen Protector for Android Phone and Other",Stock1!B64,Stock1!I64,"")} | Z64: {=_xlfn.XLOOKUP("Screen Protector for Galaxy Phone",Stock1!B64,Stock1!I64,"")} | AA64: {=_xlfn.XLOOKUP("Screen Protector for Galaxy Tab",Stock1!B64,Stock1!I64,"")} | AB64: =TEXTJOIN(,,Y64,Z64,AA64) | AC64: {=_xlfn.XLOOKUP(AB64,Stock1!I64,Stock1!F64,"")} | AD64: {=_xlfn.XLOOKUP(AB64,Stock1!I64,Stock1!J64,"")} | AE64: {=_xlfn.XLOOKUP("Storage",Stock1!B64,Stock1!I64,"")} | AF64: {=_xlfn.XLOOKUP(AE64,Stock1!I64,Stock1!F64,"")} | AG64: {=_xlfn.XLOOKUP(AE64,Stock1!I64,Stock1!J64,"")}
K65: {=IFERROR(_xlfn.XLOOKUP(I65,Incentive!B:B,Incentive!E:E,""),"")} | L65: =IFERROR(VLOOKUP(I65,Stock1!F:J,5,False),"") | M65: =IFERROR(VLOOKUP(I65,Stock2!F:J,5,False),"") | V65: {=_xlfn.XLOOKUP("Charger",Stock1!B65,Stock1!I65,"")} | W65: {=_xlfn.XLOOKUP(V65,Stock1!I65,Stock1!F65,"")} | X65: {=_xlfn.XLOOKUP(V65,Stock1!I65,Stock1!J65,"")} | Y65: {=_xlfn.XLOOKUP("Screen Protector for Android Phone and Other",Stock1!B65,Stock1!I65,"")} | Z65: {=_xlfn.XLOOKUP("Screen Protector for Galaxy Phone",Stock1!B65,Stock1!I65,"")} | AA65: {=_xlfn.XLOOKUP("Screen Protector for Galaxy Tab",Stock1!B65,Stock1!I65,"")} | AB65: =TEXTJOIN(,,Y65,Z65,AA65) | AC65: {=_xlfn.XLOOKUP(AB65,Stock1!I65,Stock1!F65,"")} | AD65: {=_xlfn.XLOOKUP(AB65,Stock1!I65,Stock1!J65,"")} | AE65: {=_xlfn.XLOOKUP("Storage",Stock1!B65,Stock1!I65,"")} | AF65: {=_xlfn.XLOOKUP(AE65,Stock1!I65,Stock1!F65,"")} | AG65: {=_xlfn.XLOOKUP(AE65,Stock1!I65,Stock1!J65,"")}
K66: {=IFERROR(_xlfn.XLOOKUP(I66,Incentive!B:B,Incentive!E:E,""),"")} | L66: =IFERROR(VLOOKUP(I66,Stock1!F:J,5,False),"") | M66: =IFERROR(VLOOKUP(I66,Stock2!F:J,5,False),"") | V66: {=_xlfn.XLOOKUP("Charger",Stock1!B66,Stock1!I66,"")} | W66: {=_xlfn.XLOOKUP(V66,Stock1!I66,Stock1!F66,"")} | X66: {=_xlfn.XLOOKUP(V66,Stock1!I66,Stock1!J66,"")} | Y66: {=_xlfn.XLOOKUP("Screen Protector for Android Phone and Other",Stock1!B66,Stock1!I66,"")} | Z66: {=_xlfn.XLOOKUP("Screen Protector for Galaxy Phone",Stock1!B66,Stock1!I66,"")} | AA66: {=_xlfn.XLOOKUP("Screen Protector for Galaxy Tab",Stock1!B66,Stock1!I66,"")} | AB66: =TEXTJOIN(,,Y66,Z66,AA66) | AC66: {=_xlfn.XLOOKUP(AB66,Stock1!I66,Stock1!F66,"")} | AD66: {=_xlfn.XLOOKUP(AB66,Stock1!I66,Stock1!J66,"")} | AE66: {=_xlfn.XLOOKUP("Storage",Stock1!B66,Stock1!I66,"")} | AF66: {=_xlfn.XLOOKUP(AE66,Stock1!I66,Stock1!F66,"")} | AG66: {=_xlfn.XLOOKUP(AE66,Stock1!I66,Stock1!J66,"")}
K67: {=IFERROR(_xlfn.XLOOKUP(I67,Incentive!B:B,Incentive!E:E,""),"")} | L67: =IFERROR(VLOOKUP(I67,Stock1!F:J,5,False),"") | M67: =IFERROR(VLOOKUP(I67,Stock2!F:J,5,False),"") | V67: {=_xlfn.XLOOKUP("Charger",Stock1!B67,Stock1!I67,"")} | W67: {=_xlfn.XLOOKUP(V67,Stock1!I67,Stock1!F67,"")} | X67: {=_xlfn.XLOOKUP(V67,Stock1!I67,Stock1!J67,"")} | Y67: {=_xlfn.XLOOKUP("Screen Protector for Android Phone and Other",Stock1!B67,Stock1!I67,"")} | Z67: {=_xlfn.XLOOKUP("Screen Protector for Galaxy Phone",Stock1!B67,Stock1!I67,"")} | AA67: {=_xlfn.XLOOKUP("Screen Protector for Galaxy Tab",Stock1!B67,Stock1!I67,"")} | AB67: =TEXTJOIN(,,Y67,Z67,AA67) | AC67: {=_xlfn.XLOOKUP(AB67,Stock1!I67,Stock1!F67,"")} | AD67: {=_xlfn.XLOOKUP(AB67,Stock1!I67,Stock1!J67,"")} | AE67: {=_xlfn.XLOOKUP("Storage",Stock1!B67,Stock1!I67,"")} | AF67: {=_xlfn.XLOOKUP(AE67,Stock1!I67,Stock1!F67,"")} | AG67: {=_xlfn.XLOOKUP(AE67,Stock1!I67,Stock1!J67,"")}
K68: {=IFERROR(_xlfn.XLOOKUP(I68,Incentive!B:B,Incentive!E:E,""),"")} | L68: =IFERROR(VLOOKUP(I68,Stock1!F:J,5,False),"") | M68: =IFERROR(VLOOKUP(I68,Stock2!F:J,5,False),"") | V68: {=_xlfn.XLOOKUP("Charger",Stock1!B68,Stock1!I68,"")} | W68: {=_xlfn.XLOOKUP(V68,Stock1!I68,Stock1!F68,"")} | X68: {=_xlfn.XLOOKUP(V68,Stock1!I68,Stock1!J68,"")} | Y68: {=_xlfn.XLOOKUP("Screen Protector for Android Phone and Other",Stock1!B68,Stock1!I68,"")} | Z68: {=_xlfn.XLOOKUP("Screen Protector for Galaxy Phone",Stock1!B68,Stock1!I68,"")} | AA68: {=_xlfn.XLOOKUP("Screen Protector for Galaxy Tab",Stock1!B68,Stock1!I68,"")} | AB68: =TEXTJOIN(,,Y68,Z68,AA68) | AC68: {=_xlfn.XLOOKUP(AB68,Stock1!I68,Stock1!F68,"")} | AD68: {=_xlfn.XLOOKUP(AB68,Stock1!I68,Stock1!J68,"")} | AE68: {=_xlfn.XLOOKUP("Storage",Stock1!B68,Stock1!I68,"")} | AF68: {=_xlfn.XLOOKUP(AE68,Stock1!I68,Stock1!F68,"")} | AG68: {=_xlfn.XLOOKUP(AE68,Stock1!I68,Stock1!J68,"")}
K69: {=IFERROR(_xlfn.XLOOKUP(I69,Incentive!B:B,Incentive!E:E,""),"")} | L69: =IFERROR(VLOOKUP(I69,Stock1!F:J,5,False),"") | M69: =IFERROR(VLOOKUP(I69,Stock2!F:J,5,False),"") | V69: {=_xlfn.XLOOKUP("Charger",Stock1!B69,Stock1!I69,"")} | W69: {=_xlfn.XLOOKUP(V69,Stock1!I69,Stock1!F69,"")} | X69: {=_xlfn.XLOOKUP(V69,Stock1!I69,Stock1!J69,"")} | Y69: {=_xlfn.XLOOKUP("Screen Protector for Android Phone and Other",Stock1!B69,Stock1!I69,"")} | Z69: {=_xlfn.XLOOKUP("Screen Protector for Galaxy Phone",Stock1!B69,Stock1!I69,"")} | AA69: {=_xlfn.XLOOKUP("Screen Protector for Galaxy Tab",Stock1!B69,Stock1!I69,"")} | AB69: =TEXTJOIN(,,Y69,Z69,AA69) | AC69: {=_xlfn.XLOOKUP(AB69,Stock1!I69,Stock1!F69,"")} | AD69: {=_xlfn.XLOOKUP(AB69,Stock1!I69,Stock1!J69,"")} | AE69: {=_xlfn.XLOOKUP("Storage",Stock1!B69,Stock1!I69,"")} | AF69: {=_xlfn.XLOOKUP(AE69,Stock1!I69,Stock1!F69,"")} | AG69: {=_xlfn.XLOOKUP(AE69,Stock1!I69,Stock1!J69,"")}
K70: {=IFERROR(_xlfn.XLOOKUP(I70,Incentive!B:B,Incentive!E:E,""),"")} | L70: =IFERROR(VLOOKUP(I70,Stock1!F:J,5,False),"") | M70: =IFERROR(VLOOKUP(I70,Stock2!F:J,5,False),"") | V70: {=_xlfn.XLOOKUP("Charger",Stock1!B70,Stock1!I70,"")} | W70: {=_xlfn.XLOOKUP(V70,Stock1!I70,Stock1!F70,"")} | X70: {=_xlfn.XLOOKUP(V70,Stock1!I70,Stock1!J70,"")} | Y70: {=_xlfn.XLOOKUP("Screen Protector for Android Phone and Other",Stock1!B70,Stock1!I70,"")} | Z70: {=_xlfn.XLOOKUP("Screen Protector for Galaxy Phone",Stock1!B70,Stock1!I70,"")} | AA70: {=_xlfn.XLOOKUP("Screen Protector for Galaxy Tab",Stock1!B70,Stock1!I70,"")} | AB70: =TEXTJOIN(,,Y70,Z70,AA70) | AC70: {=_xlfn.XLOOKUP(AB70,Stock1!I70,Stock1!F70,"")} | AD70: {=_xlfn.XLOOKUP(AB70,Stock1!I70,Stock1!J70,"")} | AE70: {=_xlfn.XLOOKUP("Storage",Stock1!B70,Stock1!I70,"")} | AF70: {=_xlfn.XLOOKUP(AE70,Stock1!I70,Stock1!F70,"")} | AG70: {=_xlfn.XLOOKUP(AE70,Stock1!I70,Stock1!J70,"")}
... K1002: {=IFERROR(_xlfn.XLOOKUP(I1002,Incentive!B:B,Incentive!E:E,""),"")} | L1002: =IFERROR(VLOOKUP(I1002,Stock1!F:J,5,False),"") | M1002: =IFERROR(VLOOKUP(I1002,Stock2!F:J,5,False),"") | V1002: {=_xlfn.XLOOKUP("Charger",Stock1!B1002,Stock1!I1002,"")} -> #REF! | W1002: {=_xlfn.XLOOKUP(V1002,Stock1!I1002,Stock1!F1002,"")} -> #REF! | X1002: {=_xlfn.XLOOKUP(V1002,Stock1!I1002,Stock1!J1002,"")} -> #REF! | Y1002: {=_xlfn.XLOOKUP("Screen Protector for Android Phone and Other",Stock1!B1002,Stock1!I1002,"")} -> #REF! | Z1002: {=_xlfn.XLOOKUP("Screen Protector for Galaxy Phone",Stock1!B1002,Stock1!I1002,"")} -> #REF! | AA1002: {=_xlfn.XLOOKUP("Screen Protector for Galaxy Tab",Stock1!B1002,Stock1!I1002,"")} -> #REF! | AB1002: =TEXTJOIN(,,Y1002,Z1002,AA1002) -> #REF! | AC1002: {=_xlfn.XLOOKUP(AB1002,Stock1!I1002,Stock1!F1002,"")} -> #REF! | AD1002: {=_xlfn.XLOOKUP(AB1002,Stock1!I1002,Stock1!J1002,"")} -> #REF! | AE1002: {=_xlfn.XLOOKUP("Storage",Stock1!B1002,Stock1!I1002,"")} -> #REF! | AF1002: {=_xlfn.XLOOKUP(AE1002,Stock1!I1002,Stock1!F1002,"")} -> #REF! | AG1002: {=_xlfn.XLOOKUP(AE1002,Stock1!I1002,Stock1!J1002,"")} -> #REF!

Sheet Stock1
B2: Copperwired Co.,Ltd.
B3: Aging Inventory WareHouse - All | K3: Include Cost of Pending Transfer
A4: Cat1 | B4: Cat2 | C4: Cat3 | D4: Brand | E4: Price 99 | F4: P/N | G4: KOAN SKU | H4: Apple Part | I4: Description | J4: On Hand | K4: On B/R | L4: On Alloc | M4: On T/F | N4: Unit Cost | O4: Total Cost | P4: 0-30 | Q4: 31-60 | R4: 61-90 | S4: 91-120 | T4: 121-150 | U4: 150+
A5: Audio | B5: Headphone | C5: True Wireless | D5: SAMSUNG | E5: 1490 | F5: SM-R410NZKAASA | I5: Samsung Galaxy Buds Core - Black | J5: 8 | K5: 0 | L5: 0 | M5: 0 | N5: 1114 | O5: 8912 | P5: 5570 | Q5: 0 | R5: 3342 | S5: 0 | T5: 0 | U5: 0
A6: Audio | B6: Headphone | C6: True Wireless | D6: SAMSUNG | E6: 1490 | F6: SM-R410NZWAASA | I6: Samsung Galaxy Buds Core - White | J6: 6 | K6: 0 | L6: 0 | M6: 0 | N6: 1114 | O6: 6684 | P6: 1114 | Q6: 0 | R6: 4456 | S6: 1114 | T6: 0 | U6: 0
A7: Audio | B7: Headphone | C7: True Wireless | D7: SAMSUNG | E7: 4290 | F7: SM-R420NZKAASA | I7: Samsung Galaxy Buds3 FE - Black | J7: 2 | K7: 0 | L7: 0 | M7: 0 | N7: 3207 | O7: 6414 | P7: 6414 | Q7: 0 | R7: 0 | S7: 0 | T7: 0 | U7: 0
A8: Audio | B8: Headphone | C8: True Wireless | D8: SAMSUNG | E8: 5990 | F8: SM-R540NZKAASA | I8: Samsung Galaxy Buds4 - Black | J8: 6 | K8: 0 | L8: 0 | M8: 0 | N8: 4479 | O8: 26874 | P8: 8958 | Q8: 0 | R8: 0 | S8: 0 | T8: 0 | U8: 17916
A9: Audio | B9: Headphone | C9: True Wireless | D9: SAMSUNG | E9: 5990 | F9: SM-R540NZWAASA | I9: Samsung Galaxy Buds4 - White | J9: 4 | K9: 0 | L9: 0 | M9: 0 | N9: 4479 | O9: 17916 | P9: 8958 | Q9: 4479 | R9: 0 | S9: 0 | T9: 4479 | U9: 0
A10: Audio | B10: Headphone | C10: True Wireless | D10: SAMSUNG | E10: 7990 | F10: SM-R640NZDAASA | I10: Samsung Galaxy Buds4 Pro - Pink Gold | J10: 1 | K10: 0 | L10: 0 | M10: 0 | N10: 5974 | O10: 5974 | P10: 0 | Q10: 0 | R10: 0 | S10: 5974 | T10: 0 | U10: 0
A11: Audio | B11: Headphone | C11: True Wireless | D11: SAMSUNG | E11: 7990 | F11: SM-R640NZKAASA | I11: Samsung Galaxy Buds4 Pro - Black | J11: 10 | K11: 0 | L11: 0 | M11: 0 | N11: 5974 | O11: 59740 | P11: 17922 | Q11: 23896 | R11: 0 | S11: 0 | T11: 17922 | U11: 0
A12: Audio | B12: Headphone | C12: True Wireless | D12: SAMSUNG | E12: 7990 | F12: SM-R640NZWAASA | I12: Samsung Galaxy Buds4 Pro - White | J12: 7 | K12: 0 | L12: 0 | M12: 0 | N12: 5974 | O12: 41818 | P12: 0 | Q12: 0 | R12: 0 | S12: 0 | T12: 23896 | U12: 17922
A13: Audio | B13: Speaker | C13: Compact Speaker | D13: Soundcore | E13: 899 | F13: 194644055783 | G13: S34244 | I13: Soundcore Select 4 Go Black | J13: 2 | K13: 0 | L13: 0 | M13: 0 | N13: 485.98 | O13: 971.96 | P13: 0 | Q13: 0 | R13: 0 | S13: 0 | T13: 0 | U13: 971.96
A14: Audio | B14: Speaker | C14: Compact Speaker | D14: Soundcore | E14: 899 | F14: 194644200176 | G14: S34246 | I14: Soundcore Select 4 Go Blue | J14: 2 | K14: 0 | L14: 0 | M14: 0 | N14: 522.71 | O14: 1045.42 | P14: 0 | Q14: 0 | R14: 0 | S14: 0 | T14: 0 | U14: 1045.42
A15: Computer and Tablet | B15: Samsung Galaxy Tab | C15: Samsung Galaxy Tab A | D15: SAMSUNG | E15: 7490 | F15: SM-X135GZAETHL | I15: Samsung (TSE) Galaxy Tab A11 LTE 8/128GB - Gray | J15: 8 | K15: 0 | L15: 0 | M15: 0 | N15: 6090 | O15: 48720 | P15: 18270 | Q15: 30450 | R15: 0 | S15: 0 | T15: 0 | U15: 0
A16: Computer and Tablet | B16: Samsung Galaxy Tab | C16: Samsung Galaxy Tab A | D16: SAMSUNG | E16: 8490 | F16: SM-X230NZAATHL | I16: Samsung (TSE) Galaxy Tab A11Plus Wi-Fi 6/128GB - Gray | J16: 3 | K16: 0 | L16: 0 | M16: 0 | N16: 6903 | O16: 20709 | P16: 13806 | Q16: 0 | R16: 6903 | S16: 0 | T16: 0 | U16: 0
A17: Computer and Tablet | B17: Samsung Galaxy Tab | C17: Samsung Galaxy Tab A | D17: SAMSUNG | E17: 10490 | F17: SM-X236BZAATHL | I17: Samsung (TSE) Galaxy Tab A11Plus 5G 6/128GB - Gray | J17: 6 | K17: 0 | L17: 0 | M17: 0 | N17: 8529 | O17: 51174 | P17: 17058 | Q17: 0 | R17: 17058 | S17: 17058 | T17: 0 | U17: 0
A18: Computer and Tablet | B18: Samsung Galaxy Tab | C18: Samsung Galaxy Tab S | D18: SAMSUNG | E18: 12990 | F18: F-X400NZAAFCX4 | I18: Samsung (TSE) Galaxy Tab S10Lite Wifi 6/128GB BOM Keyboard Cover - Gray | J18: 8 | K18: 0 | L18: 0 | M18: 0 | N18: 10562 | O18: 84496 | P18: 52810 | Q18: 31686 | R18: 0 | S18: 0 | T18: 0 | U18: 0
A19: Computer and Tablet | B19: Samsung Galaxy Tab | C19: Samsung Galaxy Tab S | D19: SAMSUNG | E19: 12990 | F19: F-X400NZRAFCX4 | I19: Samsung (TSE) Galaxy Tab S10Lite Wifi 6/128GB BOM Keyboard Cover - Coral Red | J19: 1 | K19: 0 | L19: 0 | M19: 0 | N19: 10562 | O19: 10562 | P19: 10562 | Q19: 0 | R19: 0 | S19: 0 | T19: 0 | U19: 0
A20: Computer and Tablet | B20: Samsung Galaxy Tab | C20: Samsung Galaxy Tab S | D20: SAMSUNG | E20: 16990 | F20: F-X406BZAAFCX4 | I20: Samsung (TSE) Galaxy Tab S10Lite 5G 6/128GB BOM Keyboard Cover - Gray | J20: 1 | K20: 0 | L20: 0 | M20: 0 | N20: 13814 | O20: 13814 | P20: 13814 | Q20: 0 | R20: 0 | S20: 0 | T20: 0 | U20: 0
A21: Computer and Tablet | B21: Samsung Galaxy Tab | C21: Samsung Galaxy Tab S | D21: SAMSUNG | E21: 16990 | F21: SM-X406BZAATHL | I21: Samsung (TSE) Galaxy Tab S10 Lite 5G 6/128GB - Gray | J21: 2 | K21: 0 | L21: 0 | M21: 0 | N21: 13001 | O21: 26002 | P21: 0 | Q21: 0 | R21: 0 | S21: 0 | T21: 0 | U21: 26002
A22: Computer and Tablet | B22: Samsung Galaxy Tab | C22: Samsung Galaxy Tab S | D22: SAMSUNG | E22: 19900 | F22: SM-X520NLBATHL | I22: Samsung (TSE) Galaxy Tab S10 FE Wifi 8/128GB - Blue | J22: 1 | K22: 0 | L22: 0 | M22: 0 | N22: 16180 | O22: 16180 | P22: 16180 | Q22: 0 | R22: 0 | S22: 0 | T22: 0 | U22: 0
A23: Computer and Tablet | B23: Samsung Galaxy Tab | C23: Samsung Galaxy Tab S | D23: SAMSUNG | E23: 22900 | F23: SM-X526BLBATHL | I23: Samsung (TSE) Galaxy Tab S10 FE 5G 8/128GB - Blue | J23: 1 | K23: 0 | L23: 0 | M23: 0 | N23: 18620 | O23: 18620 | P23: 0 | Q23: 0 | R23: 18620 | S23: 0 | T23: 0 | U23: 0
A24: Computer and Tablet | B24: Samsung Galaxy Tab | C24: Samsung Galaxy Tab S | D24: SAMSUNG | E24: 27900 | F24: SM-X620NZAETHL | I24: Samsung (TSE) Galaxy Tab S10FE Plus Wi-Fi 12/256GB - Gray | J24: 2 | K24: 0 | L24: 0 | M24: 0 | N24: 22685 | O24: 45370 | P24: 0 | Q24: 0 | R24: 45370 | S24: 0 | T24: 0 | U24: 0
A25: Computer and Tablet | B25: Samsung Galaxy Tab | C25: Samsung Galaxy Tab S | D25: SAMSUNG | E25: 28900 | F25: SM-X730NZSATHL | I25: Samsung (TSE) Galaxy Tab S11 Wi-Fi 12/128GB - Silver | J25: 1 | K25: 0 | L25: 0 | M25: 0 | N25: 23498 | O25: 23498 | P25: 23498 | Q25: 0 | R25: 0 | S25: 0 | T25: 0 | U25: 0
A26: Computer and Tablet | B26: Samsung Galaxy Tab | C26: Samsung Galaxy Tab S | D26: SAMSUNG | E26: 48900 | F26: SM-X936BZAATHL | I26: Samsung (TSE) Galaxy Tab S11Ultra 5G 12/256GB - Gray | J26: 3 | K26: 0 | L26: 0 | M26: 0 | N26: 39760 | O26: 119280 | P26: 39760 | Q26: 79520 | R26: 0 | S26: 0 | T26: 0 | U26: 0
... A28: Home and Office | B28: Home Appliances | C28: Kitchenware | D28: SAMSUNG | E28: 1990 | F28: SS-MWO-MS20A3010AL/S | I28: Samsung Microwave MS20A3010AL/ST With Glass Door 20 Liters | J28: 1 | K28: 0 | L28: 0 | M28: 0 | N28: 1645 | O28: 1645 | P28: 0 | Q28: 0 | R28: 0 | S28: 1645 | T28: 0 | U28: 0
A29: Home and Office | B29: Home Appliances | C29: Utilities and Supplies | D29: Jisulife | E29: 999 | F29: 6975061531234 | I29: Jisulife FA53 Handheld Fan (ABS) - Blue | J29: 1 | K29: 0 | L29: 0 | M29: 0 | N29: 700 | O29: 700 | P29: 0 | Q29: 0 | R29: 0 | S29: 0 | T29: 0 | U29: 700
A30: Home and Office | B30: Home Appliances | C30: Utilities and Supplies | D30: Jisulife | E30: 999 | F30: 6975061531258 | I30: Jisulife FA53 Handheld Fan (ABS) - White | J30: 2 | K30: 0 | L30: 0 | M30: 0 | N30: 700 | O30: 1400 | P30: 0 | Q30: 0 | R30: 0 | S30: 0 | T30: 700 | U30: 700
A31: Home and Office | B31: Home Appliances | C31: Utilities and Supplies | D31: Jisulife | E31: 689 | F31: 6975061532576 | I31: Jisulife Life 7 Handheld Fan (5,000 mAh) - Pink | J31: 2 | K31: 0 | L31: 0 | M31: 0 | N31: 483.18 | O31: 966.36 | P31: 0 | Q31: 0 | R31: 966.36 | S31: 0 | T31: 0 | U31: 0
A32: Home and Office | B32: Home Appliances | C32: Utilities and Supplies | D32: Jisulife | E32: 689 | F32: 6975061532583 | I32: Jisulife Life 7 Handheld Fan (5,000 mAh) - Grey | J32: 2 | K32: 0 | L32: 0 | M32: 0 | N32: 465.42 | O32: 930.84 | P32: 0 | Q32: 0 | R32: 483.18 | S32: 0 | T32: 0 | U32: 447.66
A33: Home and Office | B33: Home Appliances | C33: Utilities and Supplies | D33: Jisulife | E33: 689 | F33: 6975061532590 | I33: Jisulife Life 7 Handheld Fan (5,000 mAh) - Black | J33: 2 | K33: 0 | L33: 0 | M33: 0 | N33: 483.18 | O33: 966.36 | P33: 0 | Q33: 0 | R33: 966.36 | S33: 0 | T33: 0 | U33: 0
A34: Mobile and Computer Accessory | B34: Backup Battery | C34: Power Bank | D34: [CS]UGREEN | E34: 1090 | F34: 6941876222087 | I34: [CS]UGREEN Power Bank 10000mAh 20W Mini Magnetic Wireless Fast Charging - White | J34: 2 | K34: 0 | L34: 0 | M34: 0 | N34: 611.22 | O34: 1222.44 | P34: 0 | Q34: 0 | R34: 0 | S34: 0 | T34: 0 | U34: 1222.44
A35: Mobile and Computer Accessory | B35: Backup Battery | C35: Power Bank | D35: [CS]UGREEN | E35: 1090 | F35: 6941876258628 | I35: [CS]UGREEN Power Bank 10000mAh 20W Mini Magnetic Wireless Fast Charging - Black | J35: 2 | K35: 0 | L35: 0 | M35: 0 | N35: 611.22 | O35: 1222.44 | P35: 0 | Q35: 0 | R35: 0 | S35: 0 | T35: 0 | U35: 1222.44
A36: Mobile and Computer Accessory | B36: Backup Battery | C36: Power Bank | D36: Momax | E36: 1190 | F36: 4894222075160 | G36: S33349 | I36: MOMAX 1-Power Mini 5000mAh Bulit-in foldable USB-C connector Battery pack (Blue) | J36: 1 | K36: 0 | L36: 1 | M36: 0 | N36: 778.5 | O36: 778.5 | P36: 0 | Q36: 0 | R36: 0 | S36: 778.5 | T36: 0 | U36: 0
A37: Mobile and Computer Accessory | B37: Backup Battery | C37: Power Bank | D37: Momax | E37: 1190 | F37: 4894222075184 | G37: S33353 | I37: MOMAX 1-Power Mini 5000mAh Bulit-in foldable USB-C connector Battery pack (White) | J37: 1 | K37: 0 | L37: 1 | M37: 0 | N37: 778.5 | O37: 778.5 | P37: 0 | Q37: 0 | R37: 0 | S37: 778.5 | T37: 0 | U37: 0
A38: Mobile and Computer Accessory | B38: Backup Battery | C38: Power Bank | D38: PISEN | E38: 1990 | F38: 6902957323888 | G38: S34954 | I38: PISEN QUICK 30W QI2.0 Mag Power 10000mAh (Grey) | J38: 2 | K38: 0 | L38: 0 | M38: 0 | N38: 1208.88 | O38: 2417.76 | P38: 0 | Q38: 1208.88 | R38: 0 | S38: 1208.88 | T38: 0 | U38: 0
A39: Mobile and Computer Accessory | B39: Cable | C39: Data Cable | D39: ADAM elements | E39: 1090 | F39: 4710343478157 | G39: S36946 | I39: ADAM elements iLinio C to C Cable 100W 2 units 1M- Black | J39: 3 | K39: 0 | L39: 0 | M39: 0 | N39: 413.55 | O39: 1240.65 | P39: 0 | Q39: 1240.65 | R39: 0 | S39: 0 | T39: 0 | U39: 0
A40: Mobile and Computer Accessory | B40: Cable | C40: Data Cable | D40: ADAM elements | E40: 1090 | F40: 4710343478164 | G40: S36947 | I40: ADAM elements iLinio C to C Cable 100W 2 units 1M- Silver | J40: 10 | K40: 0 | L40: 0 | M40: 0 | N40: 413.55 | O40: 4135.5 | P40: 0 | Q40: 4135.5 | R40: 0 | S40: 0 | T40: 0 | U40: 0
A41: Mobile and Computer Accessory | B41: Cable | C41: Data Cable | D41: BELKIN | E41: 390 | F41: 745883867080 | G41: S21786 | I41: Belkin BOOST CHARGE Pro Flex Double-Braided Silicone USB-A to C 1M-White | J41: 4 | K41: 0 | L41: 0 | M41: 0 | N41: 148.78 | O41: 595.12 | P41: 0 | Q41: 595.12 | R41: 0 | S41: 0 | T41: 0 | U41: 0
A42: Mobile and Computer Accessory | B42: Cable | C42: Data Cable | D42: SAMSUNG | E42: 490 | F42: SSG-EP-DN975BBEGWW | I42: Samsung Cable C to C (SIS) - Black | J42: 11 | K42: 0 | L42: 0 | M42: 0 | N42: 343 | O42: 3773 | P42: 0 | Q42: 3773 | R42: 0 | S42: 0 | T42: 0 | U42: 0
A43: Mobile and Computer Accessory | B43: Cable | C43: Data Cable | D43: SAMSUNG | E43: 490 | F43: SSG-EP-DN975BWEGWW | I43: Samsung Cable C to C (SIS) - White | J43: 15 | K43: 0 | L43: 0 | M43: 0 | N43: 343 | O43: 5145 | P43: 0 | Q43: 5145 | R43: 0 | S43: 0 | T43: 0 | U43: 0
A44: Mobile and Computer Accessory | B44: Case for Android Phone and Other | C44: Galaxy A37 | D44: Mercury | E44: 190 | F44: 8800299712668 | I44: Mercury Jelly Case for Galaxy A37 - Clear | J44: 1 | K44: 0 | L44: 0 | M44: 0 | N44: 106.54 | O44: 106.54 | P44: 0 | Q44: 0 | R44: 0 | S44: 0 | T44: 0 | U44: 106.54
A45: Mobile and Computer Accessory | B45: Case for Android Phone and Other | C45: Galaxy A37 | D45: SAMSUNG | E45: 690 | F45: EF-PA376CBEGWW | I45: Samsung Galaxy A37 Silicone Case - Black | J45: 1 | K45: 0 | L45: 0 | M45: 0 | N45: 451 | O45: 451 | P45: 0 | Q45: 0 | R45: 0 | S45: 0 | T45: 0 | U45: 451
A46: Mobile and Computer Accessory | B46: Case for Android Phone and Other | C46: Galaxy A37 | D46: SAMSUNG | E46: 690 | F46: EF-PA376CKEGWW | I46: Samsung Galaxy A37 Silicone Case - Dark Green | J46: 1 | K46: 0 | L46: 0 | M46: 0 | N46: 451 | O46: 451 | P46: 0 | Q46: 0 | R46: 0 | S46: 0 | T46: 0 | U46: 451
A47: Mobile and Computer Accessory | B47: Case for Android Phone and Other | C47: Galaxy A37 | D47: SAMSUNG | E47: 690 | F47: EF-PA376CVEGWW | I47: Samsung Galaxy A37 Silicone Case - Light Violet | J47: 2 | K47: 0 | L47: 0 | M47: 0 | N47: 451 | O47: 902 | P47: 0 | Q47: 0 | R47: 0 | S47: 0 | T47: 0 | U47: 902
A48: Mobile and Computer Accessory | B48: Case for Android Phone and Other | C48: Galaxy A37 | D48: SAMSUNG | E48: 490 | F48: EF-QA376CTEGWW | I48: Samsung Galaxy A37 Clear Case - Transparent | J48: 1 | K48: 0 | L48: 0 | M48: 0 | N48: 321 | O48: 321 | P48: 0 | Q48: 0 | R48: 0 | S48: 0 | T48: 0 | U48: 321
A49: Mobile and Computer Accessory | B49: Case for Android Phone and Other | C49: Galaxy A37 | D49: SAMSUNG | E49: 690 | F49: EF-RA376CBEGWW | I49: Samsung Galaxy A37 Rugged Case - Black | J49: 2 | K49: 0 | L49: 0 | M49: 0 | N49: 451 | O49: 902 | P49: 0 | Q49: 0 | R49: 0 | S49: 0 | T49: 0 | U49: 902
A50: Mobile and Computer Accessory | B50: Case for Android Phone and Other | C50: Galaxy A57 | D50: SAMSUNG | E50: 690 | F50: EF-PA576CVEGWW | I50: Samsung Galaxy A57 Silicone Case - Violet | J50: 1 | K50: 0 | L50: 0 | M50: 0 | N50: 451 | O50: 451 | P50: 0 | Q50: 0 | R50: 0 | S50: 0 | T50: 0 | U50: 451
A51: Mobile and Computer Accessory | B51: Case for Android Phone and Other | C51: Galaxy A57 | D51: SAMSUNG | E51: 490 | F51: EF-QA576CTEGWW | I51: Samsung Galaxy A57 Clear Case - Transparent | J51: 1 | K51: 0 | L51: 0 | M51: 0 | N51: 321 | O51: 321 | P51: 0 | Q51: 0 | R51: 0 | S51: 0 | T51: 0 | U51: 321
A52: Mobile and Computer Accessory | B52: Case for Android Phone and Other | C52: Galaxy A57 | D52: SAMSUNG | E52: 390 | F52: EF-UA576CTEGWW | I52: Samsung Galaxy A57 Screen Protector - Transparent | J52: 2 | K52: 0 | L52: 0 | M52: 0 | N52: 255 | O52: 510 | P52: 0 | Q52: 0 | R52: 0 | S52: 0 | T52: 0 | U52: 510
A53: Mobile and Computer Accessory | B53: Case for Android Phone and Other | C53: Galaxy Flip8 | D53: SAMSUNG | E53: 1290 | F53: EF-CF776CTEGWW | I53: Samsung Galaxy Flip8 Clear Magnet Case - Transparent | J53: 3 | K53: 0 | L53: 0 | M53: 0 | N53: 844 | O53: 2532 | P53: 0 | Q53: 2532 | R53: 0 | S53: 0 | T53: 0 | U53: 0
A54: Mobile and Computer Accessory | B54: Case for Android Phone and Other | C54: Galaxy Flip8 | D54: SAMSUNG | E54: 1290 | F54: EF-EF776CBEGWW | I54: Samsung Galaxy Flip8 Silicone Ring Magnet Case - Graphite | J54: 2 | K54: 0 | L54: 0 | M54: 0 | N54: 844 | O54: 1688 | P54: 0 | Q54: 1688 | R54: 0 | S54: 0 | T54: 0 | U54: 0
A55: Mobile and Computer Accessory | B55: Case for Android Phone and Other | C55: Galaxy Flip8 | D55: SAMSUNG | E55: 1290 | F55: EF-EF776CGEGWW | I55: Samsung Galaxy Flip8 Silicone Ring Magnet Case - Mint | J55: 1 | K55: 0 | L55: 0 | M55: 0 | N55: 844 | O55: 844 | P55: 0 | Q55: 844 | R55: 0 | S55: 0 | T55: 0 | U55: 0
A56: Mobile and Computer Accessory | B56: Case for Android Phone and Other | C56: Galaxy Flip8 | D56: SAMSUNG | E56: 1290 | F56: EF-EF776CVEGWW | I56: Samsung Galaxy Flip8 Silicone Ring Magnet Case - Pink | J56: 3 | K56: 0 | L56: 0 | M56: 0 | N56: 844 | O56: 2532 | P56: 0 | Q56: 2532 | R56: 0 | S56: 0 | T56: 0 | U56: 0
... A91: Mobile and Computer Accessory | B91: Case for Android Phone and Other | C91: Samsung A Series | D91: SAMSUNG | E91: 490 | F91: EF-QA366CTEGWW | I91: Samsung Galaxy A36 Clear Case - Transparancy | J91: 2 | K91: 0 | L91: 0 | M91: 0 | N91: 321 | O91: 642 | P91: 0 | Q91: 0 | R91: 0 | S91: 0 | T91: 0 | U91: 642
A92: Mobile and Computer Accessory | B92: Case for Android Phone and Other | C92: Samsung Galaxy Flip7 | D92: Mercury | E92: 190 | F92: 8800299669900 | I92: Mercury Hard Case for Samsung Galaxy Flip7 - Clear | J92: 5 | K92: 0 | L92: 0 | M92: 0 | N92: 106.54 | O92: 532.7 | P92: 0 | Q92: 0 | R92: 0 | S92: 0 | T92: 0 | U92: 532.7
A93: Mobile and Computer Accessory | B93: Case for Android Phone and Other | C93: Samsung Galaxy Flip7 | D93: SAMSUNG | E93: 1190 | F93: EF-PF766TBEGWW | I93: Samsung Galaxy Flip7 Silicone Case with Ring - Black | J93: 4 | K93: 0 | L93: 0 | M93: 0 | N93: 779 | O93: 3116 | P93: 0 | Q93: 0 | R93: 0 | S93: 0 | T93: 0 | U93: 3116
A94: Mobile and Computer Accessory | B94: Case for Android Phone and Other | C94: Samsung Galaxy Flip7 | D94: SAMSUNG | E94: 1190 | F94: EF-PF766TNEGWW | I94: Samsung Galaxy Flip7 Silicone Case with Ring - Blue | J94: 6 | K94: 0 | L94: 0 | M94: 0 | N94: 779 | O94: 4674 | P94: 0 | Q94: 0 | R94: 0 | S94: 0 | T94: 0 | U94: 4674
A95: Mobile and Computer Accessory | B95: Case for Android Phone and Other | C95: Samsung Galaxy Flip7 | D95: SAMSUNG | E95: 2190 | F95: GP-FPF966PGBTW | I95: Samsung Galaxy Fold7 Capella Case - Frost Black | J95: 1 | K95: 0 | L95: 0 | M95: 0 | N95: 1433 | O95: 1433 | P95: 0 | Q95: 0 | R95: 0 | S95: 0 | T95: 0 | U95: 1433
A96: Mobile and Computer Accessory | B96: Case for Android Phone and Other | C96: Samsung Galaxy Fold7 | D96: Mercury | E96: 390 | F96: 8800299669979 | I96: Mercury Hard Case for Samsung Galaxy Fold7 - Clear | J96: 9 | K96: 0 | L96: 0 | M96: 0 | N96: 218.69 | O96: 1968.21 | P96: 0 | Q96: 0 | R96: 0 | S96: 0 | T96: 0 | U96: 1968.21
A97: Mobile and Computer Accessory | B97: Case for Android Phone and Other | C97: Samsung Galaxy Fold7 | D97: SAMSUNG | E97: 1790 | F97: EF-MF966CMEGWW | I97: Samsung Galaxy Fold7 Silicone Case - Mint | J97: 1 | K97: 0 | L97: 0 | M97: 0 | N97: 1171 | O97: 1171 | P97: 0 | Q97: 0 | R97: 0 | S97: 0 | T97: 0 | U97: 1171
A98: Mobile and Computer Accessory | B98: Case for Android Phone and Other | C98: Samsung Galaxy Fold7 | D98: SAMSUNG | E98: 2190 | F98: EF-XF966SBEGWW | I98: Samsung Galaxy Fold7 Carbon Shield Case - Black | J98: 11 | K98: 0 | L98: 0 | M98: 0 | N98: 1433 | O98: 15763 | P98: 0 | Q98: 0 | R98: 0 | S98: 0 | T98: 0 | U98: 15763
A99: Mobile and Computer Accessory | B99: Case for Android Phone and Other | C99: Samsung Galaxy S26 Series | D99: FOCUS | E99: 1590 | F99: 8859703437659 | I99: [CS]Focus Premium Set Samsung Galaxy S26 Ultra (FF-SL) | J99: 7 | K99: 0 | L99: 0 | M99: 0 | N99: 1040.19 | O99: 7281.33 | P99: 0 | Q99: 0 | R99: 0 | S99: 0 | T99: 7281.33 | U99: 0
A100: Mobile and Computer Accessory | B100: Case for Android Phone and Other | C100: Samsung Galaxy S26 Series | D100: Hishield | E100: 790 | F100: 8859216828746 | I100: [CS]Hishield Mobile case for S26 Ultra Clear | J100: 10 | K100: 0 | L100: 0 | M100: 0 | N100: 479.91 | O100: 4799.1 | P100: 0 | Q100: 0 | R100: 0 | S100: 4799.1 | T100: 0 | U100: 0
A101: Mobile and Computer Accessory | B101: Case for Android Phone and Other | C101: Samsung Galaxy S26 Series | D101: Hishield | E101: 790 | F101: 8859216828753 | I101: [CS]Hishield Mobile case for S26 Ultra Black | J101: 9 | K101: 0 | L101: 0 | M101: 0 | N101: 479.91 | O101: 4319.19 | P101: 0 | Q101: 0 | R101: 0 | S101: 4319.19 | T101: 0 | U101: 0
A102: Mobile and Computer Accessory | B102: Case for Android Phone and Other | C102: Samsung Galaxy S26 Series | D102: Hishield | E102: 890 | F102: 8859216829415 | I102: [CS]Hishield Impact shield Mobile case for S26 Ultra | J102: 5 | K102: 0 | L102: 0 | M102: 0 | N102: 540.65 | O102: 2703.25 | P102: 0 | Q102: 0 | R102: 0 | S102: 2703.25 | T102: 0 | U102: 0
A103: Mobile and Computer Accessory | B103: Case for Android Phone and Other | C103: Samsung Galaxy S26 Series | D103: Hishield | E103: 1690 | F103: 8859216834631 | I103: [CS]Hishield Boxset for Samsung S26 Ultra | J103: 2 | K103: 0 | L103: 0 | M103: 0 | N103: 1105.61 | O103: 2211.22 | P103: 0 | Q103: 0 | R103: 0 | S103: 2211.22 | T103: 0 | U103: 0
A104: Mobile and Computer Accessory | B104: Case for Android Phone and Other | C104: Samsung Galaxy S26 Series | D104: Mercury | E104: 290 | F104: 8800299702874 | I104: Mercury Jelly Hard Case Magsafe Galaxy S26 - Clear | J104: 5 | K104: 0 | L104: 0 | M104: 0 | N104: 162.62 | O104: 813.1 | P104: 0 | Q104: 0 | R104: 0 | S104: 0 | T104: 0 | U104: 813.1
A105: Mobile and Computer Accessory | B105: Case for Android Phone and Other | C105: Samsung Galaxy S26 Series | D105: Mercury | E105: 290 | F105: 8800299702935 | I105: Mercury Jelly Hard Case Magsafe Galaxy S26 Plus - Clear | J105: 2 | K105: 0 | L105: 0 | M105: 0 | N105: 162.62 | O105: 325.24 | P105: 0 | Q105: 0 | R105: 0 | S105: 0 | T105: 0 | U105: 325.24
A106: Mobile and Computer Accessory | B106: Case for Android Phone and Other | C106: Samsung Galaxy S26 Series | D106: Mercury | E106: 290 | F106: 8800299703239 | I106: Mercury Silicone Case Magsafe Galaxy S26 Ultra - Black | J106: 5 | K106: 0 | L106: 0 | M106: 0 | N106: 162.62 | O106: 813.1 | P106: 0 | Q106: 0 | R106: 0 | S106: 0 | T106: 0 | U106: 813.1
A107: Mobile and Computer Accessory | B107: Case for Android Phone and Other | C107: Samsung Galaxy S26 Series | D107: SAMSUNG | E107: 1090 | F107: EF-CS948CTEGWW | I107: Samsung Galaxy S26Ultra Clear Magnet Case - Transparency | J107: 1 | K107: 0 | L107: 0 | M107: 0 | N107: 713 | O107: 713 | P107: 0 | Q107: 0 | R107: 0 | S107: 0 | T107: 0 | U107: 713
A108: Mobile and Computer Accessory | B108: Case for Android Phone and Other | C108: Samsung Galaxy S26 Series | D108: SAMSUNG | E108: 1290 | F108: EF-ES942CBEGWW | I108: Samsung Galaxy S26 Silicone Magnet Case - Black | J108: 1 | K108: 0 | L108: 0 | M108: 0 | N108: 844 | O108: 844 | P108: 0 | Q108: 0 | R108: 0 | S108: 0 | T108: 0 | U108: 844
A109: Mobile and Computer Accessory | B109: Case for Android Phone and Other | C109: Samsung Galaxy S26 Series | D109: SAMSUNG | E109: 1290 | F109: EF-ES942CLEGWW | I109: Samsung Galaxy S26 Silicone Magnet Case - Lightblue | J109: 1 | K109: 0 | L109: 0 | M109: 0 | N109: 844 | O109: 844 | P109: 0 | Q109: 0 | R109: 0 | S109: 0 | T109: 0 | U109: 844
A110: Mobile and Computer Accessory | B110: Case for Android Phone and Other | C110: Samsung Galaxy S26 Series | D110: SAMSUNG | E110: 1290 | F110: EF-ES942CVEGWW | I110: Samsung Galaxy S26 Silicone Magnet Case - Blueviolet | J110: 1 | K110: 0 | L110: 0 | M110: 0 | N110: 844 | O110: 844 | P110: 0 | Q110: 0 | R110: 0 | S110: 0 | T110: 0 | U110: 844
A111: Mobile and Computer Accessory | B111: Case for Android Phone and Other | C111: Samsung Galaxy S26 Series | D111: SAMSUNG | E111: 1290 | F111: EF-ES947CBEGWW | I111: Samsung Galaxy S26Plus Silicone Magnet Case - Black | J111: 2 | K111: 0 | L111: 0 | M111: 0 | N111: 844 | O111: 1688 | P111: 0 | Q111: 0 | R111: 0 | S111: 0 | T111: 0 | U111: 1688
... A243: Other | B243: Premium | C243: Premium | D243: Extra Brand | E243: 299 | F243: PREMIUM-665479 | I243: [PM] Tablet Laptop Sleeve 13 inch | J243: 15 | K243: 0 | L243: 0 | M243: 0 | N243: 130.84 | O243: 1962.6 | P243: 0 | Q243: 0 | R243: 0 | S243: 1962.6 | T243: 0 | U243: 0
A244: Other | B244: Premium | C244: Premium for Samsung | D244: DIVOOM | E244: 1790 | F244: PM6958444604725 | G244: S35611 | I244: [PM]Divoom MiniToo - White | J244: 5 | K244: 0 | L244: 0 | M244: 0 | N244: 1044.39 | O244: 5221.95 | P244: 0 | Q244: 0 | R244: 0 | S244: 0 | T244: 0 | U244: 5221.95
A245: Other | B245: Premium | C245: Premium for Samsung | D245: SAMSUNG | E245: 2990 | F245: PM-8806090284687 | I245: Premium SAMSUNG T-series soundbar HW-T420 2.1ch with Subwoofer | J245: 17 | K245: 0 | L245: 0 | M245: 0 | N245: 1640.19 | O245: 27883.23 | P245: 0 | Q245: 0 | R245: 8200.95 | S245: 0 | T245: 0 | U245: 19682.28
A246: Other | B246: Premium | C246: Premium for Samsung | D246: SAMSUNG | E246: 1990 | F246: PM-8806097071891 | I246: Premium SAMSUNG B-series Souundbar HW-B400F 2.0ch Sub woofer | J246: 8 | K246: 0 | L246: 0 | M246: 0 | N246: 815.89 | O246: 6527.12 | P246: 0 | Q246: 0 | R246: 0 | S246: 0 | T246: 6527.12 | U246: 0
A247: Other | B247: Premium | C247: Premium for Samsung | D247: SAMSUNG | E247: 1990 | F247: PM-MS20A3010AL/ST | I247: Premium SAMSUNG Microwave oven SRT-20 liter | J247: 7 | K247: 0 | L247: 0 | M247: 0 | N247: 1308 | O247: 9156 | P247: 0 | Q247: 0 | R247: 9156 | S247: 0 | T247: 0 | U247: 0
A248: Other | B248: Premium for Home and Office | C248: Free Gift | D248: SAMSUNG | E248: 1990 | F248: PM8806094095647 | I248: [PM]Samsung The Freestyle Case - Green | J248: 1 | K248: 0 | L248: 0 | M248: 0 | N248: 0 | O248: 0 | P248: 0 | Q248: 0 | R248: 0 | S248: 0 | T248: 0 | U248: 0
A249: Other | B249: Premium for Home and Office | C249: Free Gift | D249: SAMSUNG | E249: 990 | F249: PM8806094297584 | I249: [PM]Samsung The Freestyle Skin - Green | J249: 1 | K249: 0 | L249: 0 | M249: 0 | N249: 0 | O249: 0 | P249: 0 | Q249: 0 | R249: 0 | S249: 0 | T249: 0 | U249: 0
A250: Other | B250: Premium for Mobile and Computer Accessory | C250: Free Gift | D250: FOCUS | E250: 99 | F250: 8859703434269 | I250: [CS]Focus Premium Bag For Samsung S25 Series - Black | J250: 1 | K250: 0 | L250: 0 | M250: 0 | N250: 0 | O250: 0 | P250: 0 | Q250: 0 | R250: 0 | S250: 0 | T250: 0 | U250: 0
A251: Other | B251: Premium for Smartphone | C251: Free Gift | D251: SAMSUNG | E251: 1090 | F251: Z-ADAPTER45QHB | I251: Premium SAMSUNG Adapter 45W without cable - Black | J251: 7 | K251: 0 | L251: 0 | M251: 0 | N251: 0 | O251: 0 | P251: 0 | Q251: 0 | R251: 0 | S251: 0 | T251: 0 | U251: 0
A252: Other | B252: Premium for Smartphone | C252: Free Gift | D252: SAMSUNG | E252: 1190 | F252: Z-FLIP7FECASE1 | I252: Premium SAMSUNG Flip6 Silicone Case Black | J252: 1 | K252: 0 | L252: 0 | M252: 0 | N252: 0 | O252: 0 | P252: 0 | Q252: 0 | R252: 0 | S252: 0 | T252: 0 | U252: 0
A253: Other | B253: Premium for Smartphone | C253: Free Gift | D253: SAMSUNG | E253: 1090 | F253: Z-FLIP7FECASE3 | I253: Premium SAMSUNG Flip6 Clear Case Clear Case | J253: 1 | K253: 0 | L253: 0 | M253: 0 | N253: 0 | O253: 0 | P253: 0 | Q253: 0 | R253: 0 | S253: 0 | T253: 0 | U253: 0
A254: Other | B254: Premium for Smartphone | C254: Free Gift | D254: SAMSUNG | E254: 590 | F254: Z-FLIP7FECASE4 | I254: Premium SAMSUNG Flip6 Anti-reflecting Film Film | J254: 1 | K254: 0 | L254: 0 | M254: 0 | N254: 0 | O254: 0 | P254: 0 | Q254: 0 | R254: 0 | S254: 0 | T254: 0 | U254: 0
A255: Other | B255: Premium for Smartphone | C255: Free Gift | D255: SAMSUNG | E255: 1090 | F255: Z-SMARTTAG2WMR | I255: Premium Samsung SmartTag2 - S26 Series | J255: 7 | K255: 0 | L255: 0 | M255: 0 | N255: 0 | O255: 0 | P255: 0 | Q255: 0 | R255: 0 | S255: 0 | T255: 0 | U255: 0
A256: Service, Insurance and Warranty | B256: Carrier Mobile Package | C256: AIS Postpaid | D256: AIS | E256: 38 | F256: 3IN1PRE2POSTP1XXX | I256: (AIS) SIM 3 In 1 Pre 2 Post P1Xxx | J256: 2 | K256: 0 | L256: 0 | M256: 0 | N256: 34.58 | O256: 69.16 | P256: 0 | Q256: 0 | R256: 0 | S256: 0 | T256: 0 | U256: 69.16
... A346: Smart Watch | B346: Samsung Galaxy Watch | C346: Galaxy Watch8 | D346: SAMSUNG | E346: 19900 | F346: SM-L505FZKATHL | I346: Samsung Galaxy Watch8 Classic LTE - Black | J346: 1 | K346: 0 | L346: 0 | M346: 0 | N346: 14879 | O346: 14879 | P346: 0 | Q346: 0 | R346: 0 | S346: 0 | T346: 0 | U346: 14879

Sheet Stock2
B2: Copperwired Co.,Ltd.
B3: Aging Inventory WareHouse - All | K3: Include Cost of Pending Transfer
A4: Cat1 | B4: Cat2 | C4: Cat3 | D4: Brand | E4: Price 99 | F4: P/N | G4: KOAN SKU | H4: Apple Part | I4: Description | J4: On Hand | K4: On B/R | L4: On Alloc | M4: On T/F | N4: Unit Cost | O4: Total Cost | P4: 0-30 | Q4: 31-60 | R4: 61-90 | S4: 91-120 | T4: 121-150 | U4: 150+
A5: Audio | B5: Headphone | C5: True Wireless | D5: SAMSUNG | E5: 1490 | F5: SM-R410NZKAASA | I5: Samsung Galaxy Buds Core - Black | J5: 8 | K5: 0 | L5: 0 | M5: 0 | N5: 1114 | O5: 8912 | P5: 5570 | Q5: 2228 | R5: 0 | S5: 0 | T5: 0 | U5: 1114
A6: Audio | B6: Headphone | C6: True Wireless | D6: SAMSUNG | E6: 1490 | F6: SM-R410NZWAASA | I6: Samsung Galaxy Buds Core - White | J6: 6 | K6: 0 | L6: 0 | M6: 0 | N6: 1114 | O6: 6684 | P6: 1114 | Q6: 2228 | R6: 0 | S6: 2228 | T6: 0 | U6: 1114
A7: Audio | B7: Headphone | C7: True Wireless | D7: SAMSUNG | E7: 4290 | F7: SM-R420NZAAASA | I7: Samsung Galaxy Buds3 FE - Gray | J7: 1 | K7: 0 | L7: 0 | M7: 0 | N7: 3207 | O7: 3207 | P7: 3207 | Q7: 0 | R7: 0 | S7: 0 | T7: 0 | U7: 0
A8: Audio | B8: Headphone | C8: True Wireless | D8: SAMSUNG | E8: 4290 | F8: SM-R420NZKAASA | I8: Samsung Galaxy Buds3 FE - Black | J8: 3 | K8: 0 | L8: 0 | M8: 0 | N8: 3207 | O8: 9621 | P8: 9621 | Q8: 0 | R8: 0 | S8: 0 | T8: 0 | U8: 0
A9: Audio | B9: Headphone | C9: True Wireless | D9: SAMSUNG | E9: 5990 | F9: SM-R540NZKAASA | I9: Samsung Galaxy Buds4 - Black | J9: 6 | K9: 0 | L9: 0 | M9: 0 | N9: 4479 | O9: 26874 | P9: 8958 | Q9: 0 | R9: 0 | S9: 0 | T9: 0 | U9: 17916
A10: Audio | B10: Headphone | C10: True Wireless | D10: SAMSUNG | E10: 5990 | F10: SM-R540NZWAASA | I10: Samsung Galaxy Buds4 - White | J10: 4 | K10: 0 | L10: 0 | M10: 0 | N10: 4479 | O10: 17916 | P10: 8958 | Q10: 8958 | R10: 0 | S10: 0 | T10: 0 | U10: 0
A11: Audio | B11: Headphone | C11: True Wireless | D11: SAMSUNG | E11: 7990 | F11: SM-R640NZKAASA | I11: Samsung Galaxy Buds4 Pro - Black | J11: 9 | K11: 0 | L11: 0 | M11: 0 | N11: 5974 | O11: 53766 | P11: 17922 | Q11: 29870 | R11: 5974 | S11: 0 | T11: 0 | U11: 0
A12: Audio | B12: Headphone | C12: True Wireless | D12: SAMSUNG | E12: 7990 | F12: SM-R640NZWAASA | I12: Samsung Galaxy Buds4 Pro - White | J12: 4 | K12: 0 | L12: 0 | M12: 0 | N12: 5974 | O12: 23896 | P12: 0 | Q12: 0 | R12: 0 | S12: 0 | T12: 23896 | U12: 0
A13: Audio | B13: Speaker | C13: Compact Speaker | D13: Soundcore | E13: 899 | F13: 194644055783 | G13: S34244 | I13: Soundcore Select 4 Go Black | J13: 2 | K13: 0 | L13: 0 | M13: 0 | N13: 485.98 | O13: 971.96 | P13: 0 | Q13: 0 | R13: 0 | S13: 0 | T13: 0 | U13: 971.96
A14: Audio | B14: Speaker | C14: Compact Speaker | D14: Soundcore | E14: 899 | F14: 194644200176 | G14: S34246 | I14: Soundcore Select 4 Go Blue | J14: 2 | K14: 0 | L14: 0 | M14: 0 | N14: 522.71 | O14: 1045.42 | P14: 0 | Q14: 0 | R14: 0 | S14: 0 | T14: 0 | U14: 1045.42
A15: Computer and Tablet | B15: Samsung Galaxy Tab | C15: Samsung Galaxy Tab A | D15: SAMSUNG | E15: 7490 | F15: SM-X135GZAETHL | I15: Samsung (TSE) Galaxy Tab A11 LTE 8/128GB - Gray | J15: 10 | K15: 0 | L15: 0 | M15: 0 | N15: 6090 | O15: 60900 | P15: 36540 | Q15: 24360 | R15: 0 | S15: 0 | T15: 0 | U15: 0
A16: Computer and Tablet | B16: Samsung Galaxy Tab | C16: Samsung Galaxy Tab A | D16: SAMSUNG | E16: 8490 | F16: SM-X230NZAATHL | I16: Samsung (TSE) Galaxy Tab A11Plus Wi-Fi 6/128GB - Gray | J16: 3 | K16: 0 | L16: 0 | M16: 0 | N16: 6903 | O16: 20709 | P16: 13806 | Q16: 0 | R16: 6903 | S16: 0 | T16: 0 | U16: 0
A17: Computer and Tablet | B17: Samsung Galaxy Tab | C17: Samsung Galaxy Tab A | D17: SAMSUNG | E17: 10490 | F17: SM-X236BZAATHL | I17: Samsung (TSE) Galaxy Tab A11Plus 5G 6/128GB - Gray | J17: 6 | K17: 0 | L17: 0 | M17: 0 | N17: 8529 | O17: 51174 | P17: 0 | Q17: 0 | R17: 17058 | S17: 34116 | T17: 0 | U17: 0
A18: Computer and Tablet | B18: Samsung Galaxy Tab | C18: Samsung Galaxy Tab S | D18: SAMSUNG | E18: 12990 | F18: F-X400NZAAFCX4 | I18: Samsung (TSE) Galaxy Tab S10Lite Wifi 6/128GB BOM Keyboard Cover - Gray | J18: 11 | K18: 0 | L18: 0 | M18: 0 | N18: 10562 | O18: 116182 | P18: 52810 | Q18: 63372 | R18: 0 | S18: 0 | T18: 0 | U18: 0
A19: Computer and Tablet | B19: Samsung Galaxy Tab | C19: Samsung Galaxy Tab S | D19: SAMSUNG | E19: 16990 | F19: F-X406BZAAFCX4 | I19: Samsung (TSE) Galaxy Tab S10Lite 5G 6/128GB BOM Keyboard Cover - Gray | J19: 2 | K19: 0 | L19: 0 | M19: 0 | N19: 13814 | O19: 27628 | P19: 27628 | Q19: 0 | R19: 0 | S19: 0 | T19: 0 | U19: 0
A20: Computer and Tablet | B20: Samsung Galaxy Tab | C20: Samsung Galaxy Tab S | D20: SAMSUNG | E20: 19900 | F20: SM-X520NLBATHL | I20: Samsung (TSE) Galaxy Tab S10 FE Wifi 8/128GB - Blue | J20: 1 | K20: 0 | L20: 0 | M20: 0 | N20: 16180 | O20: 16180 | P20: 16180 | Q20: 0 | R20: 0 | S20: 0 | T20: 0 | U20: 0
A21: Computer and Tablet | B21: Samsung Galaxy Tab | C21: Samsung Galaxy Tab S | D21: SAMSUNG | E21: 19900 | F21: SM-X520NZAATHL | I21: Samsung (TSE) Galaxy Tab S10 FE Wifi 8/128GB - Gray | J21: 1 | K21: 0 | L21: 0 | M21: 0 | N21: 14554 | O21: 14554 | P21: 0 | Q21: 0 | R21: 0 | S21: 0 | T21: 0 | U21: 14554
A22: Computer and Tablet | B22: Samsung Galaxy Tab | C22: Samsung Galaxy Tab S | D22: SAMSUNG | E22: 28900 | F22: SM-X730NZSATHL | I22: Samsung (TSE) Galaxy Tab S11 Wi-Fi 12/128GB - Silver | J22: 1 | K22: 0 | L22: 0 | M22: 0 | N22: 23498 | O22: 23498 | P22: 23498 | Q22: 0 | R22: 0 | S22: 0 | T22: 0 | U22: 0
A23: Computer and Tablet | B23: Samsung Galaxy Tab | C23: Samsung Galaxy Tab S | D23: SAMSUNG | E23: 48900 | F23: SM-X936BZAATHL | I23: Samsung (TSE) Galaxy Tab S11Ultra 5G 12/256GB - Gray | J23: 2 | K23: 0 | L23: 0 | M23: 0 | N23: 39760 | O23: 79520 | P23: 0 | Q23: 0 | R23: 0 | S23: 0 | T23: 79520 | U23: 0
A24: Health, Sport and Fitness | B24: Well-being | C24: Air and Weather Monitoring System | D24: SAMSUNG | E24: 7990 | F24: SS-VC-AX32BG3100GBST | I24: Samsung Smart Air Purifier AX32BG3100GBST | J24: 1 | K24: 0 | L24: 0 | M24: 0 | N24: 3105 | O24: 3105 | P24: 0 | Q24: 0 | R24: 0 | S24: 3105 | T24: 0 | U24: 0
A25: Home and Office | B25: Home Appliances | C25: Personal Care and Utilities | D25: Cool A Styler | E25: 899 | F25: 8859698210176 | I25: [CS]Cool A Styler High Speed Hair Dryer CA-V11 - Blue | J25: 1 | K25: 0 | L25: 0 | M25: 0 | N25: 588.13 | O25: 588.13 | P25: 0 | Q25: 0 | R25: 0 | S25: 0 | T25: 0 | U25: 588.13
A26: Home and Office | B26: Home Appliances | C26: Personal Care and Utilities | D26: Cool A Styler | E26: 899 | F26: 8859698210183 | I26: [CS]Cool A Styler High Speed Hair Dryer CA-V11 - Pink | J26: 1 | K26: 0 | L26: 0 | M26: 0 | N26: 588.13 | O26: 588.13 | P26: 0 | Q26: 0 | R26: 0 | S26: 0 | T26: 0 | U26: 588.13
... A31: Mobile and Computer Accessory | B31: Backup Battery | C31: Power Bank | D31: [CS]UGREEN | E31: 1090 | F31: 6941876258628 | I31: [CS]UGREEN Power Bank 10000mAh 20W Mini Magnetic Wireless Fast Charging - Black | J31: 1 | K31: 0 | L31: 0 | M31: 0 | N31: 611.22 | O31: 611.22 | P31: 0 | Q31: 0 | R31: 0 | S31: 0 | T31: 0 | U31: 611.22
A32: Mobile and Computer Accessory | B32: Cable | C32: Data Cable | D32: ADAM elements | E32: 1090 | F32: 4710343478157 | G32: S36946 | I32: ADAM elements iLinio C to C Cable 100W 2 units 1M- Black | J32: 2 | K32: 0 | L32: 0 | M32: 0 | N32: 413.55 | O32: 827.1 | P32: 0 | Q32: 827.1 | R32: 0 | S32: 0 | T32: 0 | U32: 0
A33: Mobile and Computer Accessory | B33: Cable | C33: Data Cable | D33: ADAM elements | E33: 1090 | F33: 4710343478164 | G33: S36947 | I33: ADAM elements iLinio C to C Cable 100W 2 units 1M- Silver | J33: 3 | K33: 0 | L33: 0 | M33: 0 | N33: 413.55 | O33: 1240.65 | P33: 0 | Q33: 1240.65 | R33: 0 | S33: 0 | T33: 0 | U33: 0
A34: Mobile and Computer Accessory | B34: Cable | C34: Data Cable | D34: BELKIN | E34: 390 | F34: 745883867080 | G34: S21786 | I34: Belkin BOOST CHARGE Pro Flex Double-Braided Silicone USB-A to C 1M-White | J34: 5 | K34: 0 | L34: 0 | M34: 0 | N34: 148.78 | O34: 743.9 | P34: 0 | Q34: 743.9 | R34: 0 | S34: 0 | T34: 0 | U34: 0
A35: Mobile and Computer Accessory | B35: Cable | C35: Data Cable | D35: SAMSUNG | E35: 490 | F35: SSG-EP-DN975BBEGWW | I35: Samsung Cable C to C (SIS) - Black | J35: 6 | K35: 0 | L35: 0 | M35: 0 | N35: 343 | O35: 2058 | P35: 0 | Q35: 2058 | R35: 0 | S35: 0 | T35: 0 | U35: 0
A36: Mobile and Computer Accessory | B36: Cable | C36: Data Cable | D36: SAMSUNG | E36: 490 | F36: SSG-EP-DN975BWEGWW | I36: Samsung Cable C to C (SIS) - White | J36: 15 | K36: 0 | L36: 0 | M36: 0 | N36: 343 | O36: 5145 | P36: 0 | Q36: 5145 | R36: 0 | S36: 0 | T36: 0 | U36: 0
A37: Mobile and Computer Accessory | B37: Case for Android Phone and Other | C37: Galaxy A36 | D37: Mercury | E37: 190 | F37: 8800299642811 | I37: Mercury Jelly Case for Galaxy A36 - Clear | J37: 3 | K37: 0 | L37: 0 | M37: 0 | N37: 106.54 | O37: 319.62 | P37: 0 | Q37: 0 | R37: 0 | S37: 0 | T37: 0 | U37: 319.62
A38: Mobile and Computer Accessory | B38: Case for Android Phone and Other | C38: Galaxy A37 | D38: Mercury | E38: 190 | F38: 8800299712668 | I38: Mercury Jelly Case for Galaxy A37 - Clear | J38: 2 | K38: 0 | L38: 0 | M38: 0 | N38: 106.54 | O38: 213.08 | P38: 0 | Q38: 0 | R38: 0 | S38: 0 | T38: 0 | U38: 213.08
A39: Mobile and Computer Accessory | B39: Case for Android Phone and Other | C39: Galaxy A37 | D39: SAMSUNG | E39: 690 | F39: EF-RA376CBEGWW | I39: Samsung Galaxy A37 Rugged Case - Black | J39: 2 | K39: 0 | L39: 0 | M39: 0 | N39: 451 | O39: 902 | P39: 0 | Q39: 0 | R39: 0 | S39: 0 | T39: 0 | U39: 902
A40: Mobile and Computer Accessory | B40: Case for Android Phone and Other | C40: Galaxy A57 | D40: SAMSUNG | E40: 690 | F40: EF-PA576CVEGWW | I40: Samsung Galaxy A57 Silicone Case - Violet | J40: 1 | K40: 0 | L40: 0 | M40: 0 | N40: 451 | O40: 451 | P40: 0 | Q40: 0 | R40: 0 | S40: 0 | T40: 0 | U40: 451
A41: Mobile and Computer Accessory | B41: Case for Android Phone and Other | C41: Galaxy A57 | D41: SAMSUNG | E41: 490 | F41: EF-QA576CTEGWW | I41: Samsung Galaxy A57 Clear Case - Transparent | J41: 2 | K41: 0 | L41: 0 | M41: 0 | N41: 321 | O41: 642 | P41: 0 | Q41: 0 | R41: 0 | S41: 0 | T41: 0 | U41: 642
A42: Mobile and Computer Accessory | B42: Case for Android Phone and Other | C42: Galaxy A57 | D42: SAMSUNG | E42: 690 | F42: EF-RA576CBEGWW | I42: Samsung Galaxy A57 Rugged Case - Black | J42: 1 | K42: 0 | L42: 0 | M42: 0 | N42: 451 | O42: 451 | P42: 0 | Q42: 0 | R42: 0 | S42: 0 | T42: 0 | U42: 451
A43: Mobile and Computer Accessory | B43: Case for Android Phone and Other | C43: Galaxy A57 | D43: SAMSUNG | E43: 390 | F43: EF-UA576CTEGWW | I43: Samsung Galaxy A57 Screen Protector - Transparent | J43: 1 | K43: 0 | L43: 0 | M43: 0 | N43: 255 | O43: 255 | P43: 0 | Q43: 0 | R43: 0 | S43: 0 | T43: 0 | U43: 255
A44: Mobile and Computer Accessory | B44: Case for Android Phone and Other | C44: Galaxy Flip8 | D44: SAMSUNG | E44: 1290 | F44: EF-CF776CTEGWW | I44: Samsung Galaxy Flip8 Clear Magnet Case - Transparent | J44: 3 | K44: 0 | L44: 0 | M44: 0 | N44: 844 | O44: 2532 | P44: 0 | Q44: 2532 | R44: 0 | S44: 0 | T44: 0 | U44: 0
A45: Mobile and Computer Accessory | B45: Case for Android Phone and Other | C45: Galaxy Flip8 | D45: SAMSUNG | E45: 1290 | F45: EF-EF776CBEGWW | I45: Samsung Galaxy Flip8 Silicone Ring Magnet Case - Graphite | J45: 3 | K45: 0 | L45: 0 | M45: 0 | N45: 844 | O45: 2532 | P45: 0 | Q45: 2532 | R45: 0 | S45: 0 | T45: 0 | U45: 0
A46: Mobile and Computer Accessory | B46: Case for Android Phone and Other | C46: Galaxy Flip8 | D46: SAMSUNG | E46: 1290 | F46: EF-EF776CGEGWW | I46: Samsung Galaxy Flip8 Silicone Ring Magnet Case - Mint | J46: 1 | K46: 0 | L46: 0 | M46: 0 | N46: 844 | O46: 844 | P46: 0 | Q46: 844 | R46: 0 | S46: 0 | T46: 0 | U46: 0
